Workbook
Name basevendeurs: #REF!
Name basevendeurs: #REF!
Name basevendeurs: #REF!
Name basevendeurs: #REF!
Name basevendeurs: #REF!
Name basevendeurs: #REF!
Name basevendeurs: #REF!
Name basevendeurs: #REF!
Name basevendeurs: #REF!
Name basevendeurs: #REF!
Name basevendeurs: #REF!
Name basevendeurs: #REF!
Name CD: #REF!
Name CD: #REF!
Name CD: #REF!
Name CD: #REF!
Name CD: #REF!
Name CD: #REF!
Name CD: #REF!
Name CD: #REF!
Name CD: #REF!
Name CD: #REF!
Name CD: #REF!
Name CD: #REF!
Name ChronologieNative_Date_de_Facturation: #N/A
Name ChronologieNative_Date_de_Facturation1: #N/A
Name ChronologieNative_Date_de_Facturation12: #N/A
Name ChronologieNative_Date_de_Facturation121: #N/A
Name ChronologieNative_Date_de_Facturation1211: #N/A
Name ChronologieNative_Date_de_Facturation1221: #N/A
Name ChronologieNative_Date_de_Facturation12211: #N/A
Name ChronologieNative_Date_de_Facturation122111: #N/A
Name ChronologieNative_Date_de_Facturation12212: #N/A
Name ChronologieNative_Date_de_Facturation122121: #N/A
Name ChronologieNative_Date_de_Facturation1221211: #N/A
Name ChronologieNative_Date_de_Facturation2: #N/A
Name LSPBL: #REF!
Name LSPBL: #REF!
Name LSPBL: #REF!
Name LSPBL: #REF!
Name LSPBL: #REF!
Name LSPBL: #REF!
Name LSPBL: #REF!
Name LSPBL: #REF!
Name LSPBL: #REF!
Name LSPBL: #REF!
Name LSPBL: #REF!
Name LSPBL: #REF!
Name nbredemois: #REF!
Name Segment_Equipe: #N/A
Name Segment_Equipe1: #N/A
Name Segment_Etat: #N/A
Name Segment_Etat1: #N/A
Name Segment_Etat11: #N/A
Name Segment_Etat111: #N/A
Name Segment_Etat12: #N/A
Name Segment_Etat121: #N/A
Name Segment_Etat1211: #N/A
Name Segment_Marge_négative: #N/A
Name Segment_Marge_nette: #N/A

Sheet Suppression CD
A1: Site | B1: Etat | C1: Marque | D1: Date de Facturation | E1: Date de Livraison | F1: Manque Marge | G1: PB Marge | H1: Justif ? | I1: Solde Client | J1: Validé DF | K1: Solde client2 | L1: Vendeur | M1: N° VN | N1: N° CDE | O1: Châssis | P1: CLIENT | Q1: Marge nette | R1: Marge restante | S1: % PV | T1: OP Clos | U1: OP Ouverts | V1: OP non visible | W1: libellé OP non visible | X1: TX COM | Y1: TX COM Opticar | Z1: Commission de Base | AA1: Prime opération | AB1: Total COM | AC1: Sté de Financement | AD1: EXT GIE | AE1: Forfait immat | AF1: nbre de forfait | AG1: nbre de livraison | AH1: OP "+ / -" | AI1: date | AJ1: % forfait | AK1: Site3 | AL1: Marque4 | AM1: non utilisé | AN1: Equipe | AO1: Marge nette recalculée | AP1: % PV5 | AQ1: Marge négativr

Sheet Base Vendeurs
A1: aaa
A2: ADTDE | B2: Val de Lys
A3: ARKDE | B3: Valauto Arras
A4: ARLFO | B4: Valauto Arras
A5: ARLKO | B5: Valauto Arras
A6: ARLPA | B6: Valauto Arras
A7: ARMPO | B7: Valauto Arras
A8: ARPDE | B8: Valauto Arras
A9: ARRDE | B9: Valauto Arras
A10: ARTRE | B10: Valauto Arras
A11: ARXPAD | B11: Valauto Arras
A12: ASACH | B12: Val de Lys
A13: ASCDI | B13: Val de Lys
... A221: VATDR | B221: Valauto Hainaut AUDI

Sheet Base Sites
A2: 60 | B2: Val de Lys Automobiles
A3: 30 | B3: Valauto Lambersart VW
A4: 10 | B4: Valauto Roncq
A5: 80 | B5: Valauto Artois
A6: NI | B6: Valauto Béthune
A7: 30 | B7: Valauto Lomme (avant le 01/07/19)
A8: 70 | B8: Valauto Lomme
A9: 30 | B9: Valauto Lambersart Sk
A10: 20 | B10: Valauto Professionnels
A11: 15 | B11: Valauto Hainaut
A12: 25 | B12: Valauto Maubeuge
A13: 35 | B13: Valauto Cambrai
A14: 45 | B14: Valauto Arras

Sheet Marges_Marques N 5
A1: VALAUTO - Analyse des Marges VN / MARQUE
B7: Nbre de LIV. | C7: PV MOYEN Hors Transport | D7: Moyenne de Total COM | E7: Marge nette moyenne
A8: Total général

Sheet Marges_Vendeurs N 7
A1: VALAUTO - Marges VN / Vendeurs
A3: =+'Marges_Marques N 5'!A3 -> 0
A5: Marque | B5: VW
B7: Nbre de LIV. | C7: PV MOYEN Hors Transport | D7: Marge nette moyenne | E7: Moyenne de Total COM
A8: ASCDI | B8: 1 | C8: 45183.33 | D8: 1405.52 | E8: 131.052
A9: LTHVI | B9: 1 | C9: 40900.84 | D9: 2927.69 | E9: 245.4348
A10: LTMEL | B10: 9 | C10: 41121.347 | D10: 103.51778 | E10: 0
A11: RQCSA | B11: 8 | C11: 25496.534 | D11: 1242.475 | E11: 153.90894
A12: RQFST | B12: 1 | C12: 42741.67 | D12: 949.85 | E12: 85.485
A13: RQHWI | B13: 6 | C13: 36682.702 | D13: 1727.55 | E13: 130.54873
A14: RQNBA | B14: 2 | C14: 27382.075 | D14: 1025.635 | E14: 67.65405
A15: RQSVA | B15: 3 | C15: 37284.75 | D15: 1459.6233 | E15: 221.05043
A16: RXNTA | B16: 14 | C16: 36730.361 | D16: 1700.0036 | E16: 153.7475
A17: VSGNI | B17: 9 | C17: 36496.627 | D17: 1122.2133 | E17: 106.89453
A18: VSYPA | B18: 8 | C18: 34190.285 | D18: 687.3975 | E18: 62.98895
A19: VSGLE | B19: 1 | C19: 39350 | D19: 457.84 | E19: 36.284
A20: 0 | B20: 1 | C20: 40146.96 | D20: 0 | E20: 0
A21: RQBER | B21: 4 | C21: 30207.215 | D21: -1241.245 | E21: 0
A22: VSFCA | B22: 7 | C22: 34114.203 | D22: 719.13429 | E22: 82.411143
A23: RQLGU | B23: 4 | C23: 42431.732 | D23: 3416.0575 | E23: 364.01135
A24: VSRPO | B24: 1 | C24: 45503.3 | D24: 3569.28 | E24: 275.0556
A25: LTBCL | B25: 6 | C25: 27840.755 | D25: 1549.4533 | E25: 187.06878
A26: LTTDU | B26: 1 | C26: 44902.49 | D26: -4671.67 | E26: 0
A27: LTNFA | B27: 5 | C27: 35279.022 | D27: 1151.206 | E27: 114.18822
A28: LTSVA | B28: 1 | C28: 30581.27 | D28: 1513.03 | E28: 141.803
A29: LTJEL | B29: 1 | C29: 31503.32 | D29: 2497.16 | E29: 192.1728
A30: ASTDU | B30: 2 | C30: 26770.42 | D30: 1490.585 | E30: 118.7137
A31: ASYPA | B31: 6 | C31: 34652.13 | D31: 1527.61 | E31: 169.04035
A32: ASMCO | B32: 2 | C32: 18910.545 | D32: 625.75 | E32: 42.46
A33: Total général | B33: 104 | C33: 34710.372 | D33: 1133.6444 | E33: 121.16927
A49: Marque | B49: (Plusieurs éléments)
B51: Nbre de LIV. | C51: PV MOYEN Hors Transport | D51: Marge nette moyenne | E51: Moyenne de Total COM
A52: Total général
A75: Marque | B75: (Plusieurs éléments)
B77: Nbre de LIV. | C77: PV MOYEN Hors Transport | D77: Marge nette moyenne | E77: Moyenne de Total COM
A78: Total général
A97: Marque | B97: (Plusieurs éléments)
B99: Nbre de LIV. | C99: PV MOYEN Hors Transport | D99: Marge nette moyenne | E99: Moyenne de Total COM
A100: Total général
A116: Marque | B116: (Plusieurs éléments)
B118: Nbre de LIV. | C118: PV MOYEN Hors Transport | D118: Marge nette moyenne | E118: Moyenne de Total COM
A119: Total général

Sheet Marges_Sites N 6
A1: VALAUTO - Marges VN / Vendeurs
O4: …..
B7: Nbre de LIV. | C7: Somme de Total | D7: Somme de Marge nette | E7: Moyenne de Marge nette recalculée2
A8: VW | B8: 11 | C8: 344458.04 | D8: 14803.85 | E8: 1345.8045
A9: ASYPA | B9: 6 | C9: 207912.78 | D9: 9165.66 | E9: 1527.61
A10: 60 | B10: 6 | C10: 207912.78 | D10: 9165.66 | E10: 1527.61
A11: ASTDU | B11: 2 | C11: 53540.84 | D11: 2981.17 | E11: 1490.585
A12: 30 | B12: 1 | C12: 22665 | D12: 935.91 | E12: 935.91
A13: 60 | B13: 1 | C13: 30875.84 | D13: 2045.26 | E13: 2045.26
A14: ASCDI | B14: 1 | C14: 45183.33 | D14: 1405.52 | E14: 1405.52
A15: ASMCO | B15: 2 | C15: 37821.09 | D15: 1251.5 | E15: 625.75
A16: 60 | B16: 2 | C16: 37821.09 | D16: 1251.5 | E16: 625.75
A17: Total général | B17: 11 | C17: 344458.04 | D17: 14803.85 | E17: 1345.8045

Sheet Marges VN recalculées
A1: Site | B1: 70
A2: Marque | B2: (Tous)
A4: Étiquettes de lignes | B4: Nombre de N° VN | C4: Somme de Marge nette recalculée | D4: Moyenne de Marge nette | E4: Moyenne de Marge nette recalculée
A5: I10 | B5: 5 | C5: 4184.19 | D5: 836.838 | E5: 836.838
A6: I20 | B6: 13 | C6: 13470.74 | D6: 1032.3646 | E6: 1036.2108
A7: I30 | B7: 3 | C7: 5178.87 | D7: 1726.29 | E7: 1726.29
A8: IONIQ | B8: 12 | C8: 18510.94 | D8: 1503.745 | E8: 1542.5783
A9: KONA | B9: 32 | C9: 55182.47 | D9: 1699.4522 | E9: 1724.4522
A10: SANTA FE | B10: 3 | C10: 7036.53 | D10: 2345.51 | E10: 2345.51
A11: TUCSON | B11: 13 | C11: 26501.81 | D11: 1996.2931 | E11: 2038.6008
A12: Total général | B12: 81 | C12: 130065.55 | D12: 1582.7105 | E12: 1605.7475

Sheet Marges VN
A1: Site | B1: Etat | C1: Marque | D1: Date de Facturation | E1: Date de Livraison | F1: Manque Marge | G1: PB Marge | H1: Justif ? | I1: Solde Client | J1: Validé DF | K1: Solde client2 | L1: Vendeur | M1: N° VN | N1: N° CDE | O1: Châssis | P1: CLIENT | Q1: Modèle livré | R1: Prix de Vte | S1: Options | T1: Total | U1: Jours de Stock | V1: Marge nette | W1: Marge s/transport | X1: déduction diverse | Y1: Marge restante | Z1: % PV | AA1: OP Clos | AB1: OP Ouverts | AC1: OP non visible | AD1: libellé OP non visible | AE1: TX COM | AF1: TX COM Opticar | AG1: Commission de Base | AH1: Prime opération | AI1: Total COM | AJ1: Sté de Financement | AK1: EXT GIE | AL1: Forfait immat | AM1: nbre de forfait | AN1: nbre de livraison | AO1: OP "+ / -" | AP1: date | AQ1: % forfait | AR1: AU | AS1: Marque4 | AT1: non utilisé | AU1: Equipe | AV1: Marge nette recalculée | AW1: % PV5 | AX1: Marge négative | AY1: TOTAL COM VENDEUR
A2: 60 | B2: C | C2: VW | D2: 46038 | E2: 46044 | K2: 0 | L2: RQCSA | M2: 89 | O2: WVGZZZE2XRP505667 | P2: DA COSTA LAETITIA | Q2: ID 5 | R2: 41363.33 | S2: 1433.33 | T2: =+R2+S2 -> 42796.66 | U2: 353 | V2: -4240.68 | W2: 95 | Y2: =+V2-W2+X2 -> -4335.68 | Z2: =(V2+X2)/T2 -> -0.099089041 | AA2: -2995.77 | AB2: 0 | AD2: marge négative // 1/2 cmm // Prise d'ordre le 08/01 et livraison le 22/01/2026 | AF2: 0.13 | AG2: =+Y2*AE2 -> 0 | AH2: 200 | AI2: =+AG2+AH2 -> 200 | AM2: =IF(AL2>0,100%,0%) -> 0 | AN2: =IF(A2>0,1,"") -> 1 | AQ2: =IF(AN2="","",+AM2/AN2) -> 0 | AR2: =IF(A2="","",VLOOKUP(A2,'Base Sites'!A:B,2,FALSE)) -> Val de Lys Automobiles | AS2: =IF(C2="VW","VOLKSWAGEN",IF(C2="SE","SEAT",IF(C2="NI","NISSAN",IF(C2="HY","HYUNDAI",IF(C2="VU","VUL",IF(C2="sk","SKODA",IF(C2="ltsk","SKODA",IF(C2="CUPRA","CUPRA",IF(C2="AUDI","AUDI",""))))))))) -> VOLKSWAGEN | AU2: =IF(A2="","",VLOOKUP(L2,'Base Vendeurs'!A:B,2,FALSE)) -> Valauto Roncq VW | AV2: =+V2+AO2 -> -4240.68 | AW2: =IF(A2="","",+AV2/T2) -> -0.099089041 | AX2: =IF(AV2<0,"OUI","NON") -> OUI | AY2: =+MargesVN[[#This Row],[Total COM]]+MargesVN[[#This Row],[EXT GIE]]+MargesVN[[#This Row],[Forfait immat]] -> 200
A3: 60 | B3: C | C3: VW | D3: 46052 | E3: 46046 | I3: x | J3: X | K3: -150 | L3: ASLME | M3: 94 | N3: 2705 | O3: WVGZZZCS8SY037022 | P3: POLET CLEMENT | Q3: TAIGO | R3: 24822.33 | S3: -145.84 | T3: =+R3+S3 -> 24676.49 | U3: 123 | V3: 380.41 | W3: 95 | Y3: =+V3-W3+X3 -> 285.41 | Z3: =(V3+X3)/T3 -> 0.015415888 | AA3: -2641.12 | AB3: 0 | AD3: ok vn payé / solde client acpte 2025 non déduit ni rbt | AE3: 0.13 | AF3: 0.13 | AG3: =+Y3*AE3 -> 37.1033 | AI3: =+AG3+AH3 -> 37.1033 | AJ3: VWB | AK3: 30 | AL3: 50 | AM3: =IF(AL3>0,100%,0%) -> 1 | AN3: =IF(A3>0,1,"") -> 1 | AQ3: =IF(AN3="","",+AM3/AN3) -> 1 | AR3: =IF(A3="","",VLOOKUP(A3,'Base Sites'!A:B,2,FALSE)) -> Val de Lys Automobiles | AS3: =IF(C3="VW","VOLKSWAGEN",IF(C3="SE","SEAT",IF(C3="NI","NISSAN",IF(C3="HY","HYUNDAI",IF(C3="VU","VUL",IF(C3="sk","SKODA",IF(C3="ltsk","SKODA",IF(C3="CUPRA","CUPRA",IF(C3="AUDI","AUDI",""))))))))) -> VOLKSWAGEN | AU3: =IF(A3="","",VLOOKUP(L3,'Base Vendeurs'!A:B,2,FALSE)) -> Val de Lys | AV3: =+V3+AO3 -> 380.41 | AW3: =IF(A3="","",+AV3/T3) -> 0.015415888 | AX3: =IF(AV3<0,"OUI","NON") -> NON | AY3: =+MargesVN[[#This Row],[Total COM]]+MargesVN[[#This Row],[EXT GIE]]+MargesVN[[#This Row],[Forfait immat]] -> 117.1033
A4: 60 | B4: C | C4: VW | D4: 46198 | E4: 46199 | L4: ASNMA | M4: 97 | N4: 3504 | O4: WVGZZZA15SK002127 | P4: BRANLE WILLY | Q4: T ROC | R4: 42230.67 | S4: 1083.33 | T4: =+R4+S4 -> 43314 | U4: 171 | V4: 484.39 | W4: 95 | Y4: =+V4-W4+X4 -> 389.39 | Z4: =(V4+X4)/T4 -> 0.01118322 | AA4: -5764.54 | AB4: 0 | AD4: 0 comm demandée // Forfait | AF4: 0.12 | AG4: =+Y4*AE4 -> 0 | AH4: 200 | AI4: =+AG4+AH4 -> 200 | AK4: 30 | AM4: =IF(AL4>0,100%,0%) -> 0 | AN4: =IF(A4>0,1,"") -> 1 | AQ4: =IF(AN4="","",+AM4/AN4) -> 0 | AR4: =IF(A4="","",VLOOKUP(A4,'Base Sites'!A:B,2,FALSE)) -> Val de Lys Automobiles | AS4: =IF(C4="VW","VOLKSWAGEN",IF(C4="SE","SEAT",IF(C4="NI","NISSAN",IF(C4="HY","HYUNDAI",IF(C4="VU","VUL",IF(C4="sk","SKODA",IF(C4="ltsk","SKODA",IF(C4="CUPRA","CUPRA",IF(C4="AUDI","AUDI",""))))))))) -> VOLKSWAGEN | AU4: =IF(A4="","",VLOOKUP(L4,'Base Vendeurs'!A:B,2,FALSE)) -> Val de Lys | AV4: =+V4+AO4 -> 484.39 | AW4: =IF(A4="","",+AV4/T4) -> 0.01118322 | AX4: =IF(AV4<0,"OUI","NON") -> NON | AY4: =+MargesVN[[#This Row],[Total COM]]+MargesVN[[#This Row],[EXT GIE]]+MargesVN[[#This Row],[Forfait immat]] -> 230
A5: 60 | B5: C | C5: VW | D5: 46202 | E5: 46203 | L5: ASALA | M5: 98 | N5: 3631 | O5: WVGZZZE21TE048962 | P5: VANDROMME DAVID | Q5: ID 4 | R5: 37605 | S5: 1433.33 | T5: =+R5+S5 -> 39038.33 | U5: 63 | V5: 875.76 | W5: 95 | Y5: =+V5-W5+X5 -> 780.76 | Z5: =(V5+X5)/T5 -> 0.022433337 | AA5: 0 | AB5: 0 | AE5: 0.1 | AF5: 0.12 | AG5: =+Y5*AE5 -> 78.076 | AI5: =+AG5+AH5 -> 78.076 | AJ5: VWB | AM5: =IF(AL5>0,100%,0%) -> 0 | AN5: =IF(A5>0,1,"") -> 1 | AQ5: =IF(AN5="","",+AM5/AN5) -> 0 | AR5: =IF(A5="","",VLOOKUP(A5,'Base Sites'!A:B,2,FALSE)) -> Val de Lys Automobiles | AS5: =IF(C5="VW","VOLKSWAGEN",IF(C5="SE","SEAT",IF(C5="NI","NISSAN",IF(C5="HY","HYUNDAI",IF(C5="VU","VUL",IF(C5="sk","SKODA",IF(C5="ltsk","SKODA",IF(C5="CUPRA","CUPRA",IF(C5="AUDI","AUDI",""))))))))) -> VOLKSWAGEN | AU5: =IF(A5="","",VLOOKUP(L5,'Base Vendeurs'!A:B,2,FALSE)) -> Val de Lys | AV5: =+V5+AO5 -> 875.76 | AW5: =IF(A5="","",+AV5/T5) -> 0.022433337 | AX5: =IF(AV5<0,"OUI","NON") -> NON | AY5: =+MargesVN[[#This Row],[Total COM]]+MargesVN[[#This Row],[EXT GIE]]+MargesVN[[#This Row],[Forfait immat]] -> 78.076
A6: 10 | B6: C | C6: CUPRA | D6: 46154 | E6: 46165 | K6: 0 | L6: ARNLE | M6: 572 | O6: VSSZZZK1ZNP023607 | P6: ROBERT MALIKA | Q6: Cupra el-Born | R6: 28388.74 | S6: 0 | T6: =+R6+S6 -> 28388.74 | U6: 1258 | V6: -2998.39 | W6: 0 | Y6: =+V6-W6+X6 -> -2998.39 | Z6: =(V6+X6)/T6 -> -0.10561899 | AA6: 0 | AB6: 0 | AD6: marge négative // manque signatures | AF6: 0.1 | AG6: =+Y6*AE6 -> 0 | AH6: 150 | AI6: =+AG6+AH6 -> 150 | AK6: 0 | AL6: 50 | AM6: =IF(AL6>0,100%,0%) -> 1 | AN6: =IF(A6>0,1,"") -> 1 | AQ6: =IF(AN6="","",+AM6/AN6) -> 1 | AR6: =IF(A6="","",VLOOKUP(A6,'Base Sites'!A:B,2,FALSE)) -> Valauto Roncq | AS6: =IF(C6="VW","VOLKSWAGEN",IF(C6="SE","SEAT",IF(C6="NI","NISSAN",IF(C6="HY","HYUNDAI",IF(C6="VU","VUL",IF(C6="sk","SKODA",IF(C6="ltsk","SKODA",IF(C6="CUPRA","CUPRA",IF(C6="AUDI","AUDI",""))))))))) -> CUPRA | AU6: =IF(A6="","",VLOOKUP(L6,'Base Vendeurs'!A:B,2,FALSE)) -> Valauto Arras | AV6: =+V6+AO6 -> -2998.39 | AW6: =IF(A6="","",+AV6/T6) -> -0.10561899 | AX6: =IF(AV6<0,"OUI","NON") -> OUI | AY6: =+MargesVN[[#This Row],[Total COM]]+MargesVN[[#This Row],[EXT GIE]]+MargesVN[[#This Row],[Forfait immat]] -> 200
A7: 10 | B7: C | C7: VW | D7: 46098 | E7: 46099 | K7: 0 | L7: RQGDI | M7: 594 | N7: 511408 | O7: WVGZZZE20RP506374 | P7: CH CONSULTING | Q7: ID 5 | R7: 41363.33 | S7: 1433.33 | T7: =+R7+S7 -> 42796.66 | U7: 413 | V7: -6904.53 | W7: 95 | Y7: =+V7-W7+X7 -> -6999.53 | Z7: =(V7+X7)/T7 -> -0.16133338 | AA7: -2995.77 | AB7: 0 | AD7: marge négative // challenge // VN vendu 38493,76€ au lieu de 38990€ | AF7: 0.13 | AG7: =+Y7*AE7 -> 0 | AH7: 200 | AI7: =+AG7+AH7 -> 200 | AJ7: VWB | AL7: 50 | AM7: =IF(AL7>0,100%,0%) -> 1 | AN7: =IF(A7>0,1,"") -> 1 | AQ7: =IF(AN7="","",+AM7/AN7) -> 1 | AR7: =IF(A7="","",VLOOKUP(A7,'Base Sites'!A:B,2,FALSE)) -> Valauto Roncq | AS7: =IF(C7="VW","VOLKSWAGEN",IF(C7="SE","SEAT",IF(C7="NI","NISSAN",IF(C7="HY","HYUNDAI",IF(C7="VU","VUL",IF(C7="sk","SKODA",IF(C7="ltsk","SKODA",IF(C7="CUPRA","CUPRA",IF(C7="AUDI","AUDI",""))))))))) -> VOLKSWAGEN | AU7: =IF(A7="","",VLOOKUP(L7,'Base Vendeurs'!A:B,2,FALSE)) -> Valauto Roncq VW | AV7: =+V7+AO7 -> -6904.53 | AW7: =IF(A7="","",+AV7/T7) -> -0.16133338 | AX7: =IF(AV7<0,"OUI","NON") -> OUI | AY7: =+MargesVN[[#This Row],[Total COM]]+MargesVN[[#This Row],[EXT GIE]]+MargesVN[[#This Row],[Forfait immat]] -> 250
A8: 10 | B8: C | C8: SK | D8: 46069 | E8: 46070 | K8: 0 | L8: RQTHC | M8: 609 | N8: 511811 | O8: TMBJB7PSXST106889 | P8: PARIS TERMINAL SA | Q8: KODIAQ | R8: 40833.33 | S8: 2775 | T8: =+R8+S8 -> 43608.33 | U8: 146 | V8: 1189.23 | W8: 35.01 | Y8: =+V8-W8+X8 -> 1154.22 | Z8: =(V8+X8)/T8 -> 0.027270707 | AA8: -4712 | AB8: 0 | AE8: 0.13 | AF8: 0.13 | AG8: =+Y8*AE8 -> 150.0486 | AI8: =+AG8+AH8 -> 150.0486 | AM8: =IF(AL8>0,100%,0%) -> 0 | AN8: =IF(A8>0,1,"") -> 1 | AQ8: =IF(AN8="","",+AM8/AN8) -> 0 | AR8: =IF(A8="","",VLOOKUP(A8,'Base Sites'!A:B,2,FALSE)) -> Valauto Roncq | AS8: =IF(C8="VW","VOLKSWAGEN",IF(C8="SE","SEAT",IF(C8="NI","NISSAN",IF(C8="HY","HYUNDAI",IF(C8="VU","VUL",IF(C8="sk","SKODA",IF(C8="ltsk","SKODA",IF(C8="CUPRA","CUPRA",IF(C8="AUDI","AUDI",""))))))))) -> SKODA | AU8: =IF(A8="","",VLOOKUP(L8,'Base Vendeurs'!A:B,2,FALSE)) -> Valauto Roncq Skoda | AV8: =+V8+AO8 -> 1189.23 | AW8: =IF(A8="","",+AV8/T8) -> 0.027270707 | AX8: =IF(AV8<0,"OUI","NON") -> NON | AY8: =+MargesVN[[#This Row],[Total COM]]+MargesVN[[#This Row],[EXT GIE]]+MargesVN[[#This Row],[Forfait immat]] -> 150.0486
A9: 10 | B9: NP | C9: VW | D9: 46078 | E9: 46076 | I9: x | K9: 24432.88 | L9: LTBDU | M9: 612 | O9: WVGZZZCS9TY011112 | P9: BAILLEUL KLEBER | Q9: TAIGO | R9: 27264 | S9: 922.83 | T9: =+R9+S9 -> 28186.83 | U9: 118 | V9: 964.11 | W9: 95 | Y9: =+V9-W9+X9 -> 869.11 | Z9: =(V9+X9)/T9 -> 0.034204272 | AA9: -2921.79 | AB9: 0 | AD9: solde client mq financement | AE9: 0.13 | AF9: 0.13 | AG9: =+Y9*AE9 -> 112.9843 | AI9: =+AG9+AH9 -> 112.9843 | AK9: 30 | AL9: 50 | AM9: =IF(AL9>0,100%,0%) -> 1 | AN9: =IF(A9>0,1,"") -> 1 | AQ9: =IF(AN9="","",+AM9/AN9) -> 1 | AR9: =IF(A9="","",VLOOKUP(A9,'Base Sites'!A:B,2,FALSE)) -> Valauto Roncq | AS9: =IF(C9="VW","VOLKSWAGEN",IF(C9="SE","SEAT",IF(C9="NI","NISSAN",IF(C9="HY","HYUNDAI",IF(C9="VU","VUL",IF(C9="sk","SKODA",IF(C9="ltsk","SKODA",IF(C9="CUPRA","CUPRA",IF(C9="AUDI","AUDI",""))))))))) -> VOLKSWAGEN | AU9: =IF(A9="","",VLOOKUP(L9,'Base Vendeurs'!A:B,2,FALSE)) -> Valauto Lambersart VW | AV9: =+V9+AO9 -> 964.11 | AW9: =IF(A9="","",+AV9/T9) -> 0.034204272 | AX9: =IF(AV9<0,"OUI","NON") -> NON | AY9: =+MargesVN[[#This Row],[Total COM]]+MargesVN[[#This Row],[EXT GIE]]+MargesVN[[#This Row],[Forfait immat]] -> 192.9843
A10: 10 | B10: C | C10: VW | D10: 46064 | E10: 46064 | K10: 0 | L10: RXNTA | M10: 615 | N10: 515962 | O10: WVGZZZCT4TW424074 | P10: DELSARTE BERTIL | Q10: TIGUAN | R10: 48155 | S10: 5220.84 | T10: =+R10+S10 -> 53375.84 | U10: 57 | V10: 1025.17 | W10: 95 | Y10: =+V10-W10+X10 -> 930.17 | Z10: =(V10+X10)/T10 -> 0.01920663 | AA10: -4803.83 | AB10: -2000 | AE10: 0.13 | AF10: 0.13 | AG10: =+Y10*AE10 -> 120.9221 | AI10: =+AG10+AH10 -> 120.9221 | AK10: 30 | AM10: =IF(AL10>0,100%,0%) -> 0 | AN10: =IF(A10>0,1,"") -> 1 | AQ10: =IF(AN10="","",+AM10/AN10) -> 0 | AR10: =IF(A10="","",VLOOKUP(A10,'Base Sites'!A:B,2,FALSE)) -> Valauto Roncq | AS10: =IF(C10="VW","VOLKSWAGEN",IF(C10="SE","SEAT",IF(C10="NI","NISSAN",IF(C10="HY","HYUNDAI",IF(C10="VU","VUL",IF(C10="sk","SKODA",IF(C10="ltsk","SKODA",IF(C10="CUPRA","CUPRA",IF(C10="AUDI","AUDI",""))))))))) -> VOLKSWAGEN | AU10: =IF(A10="","",VLOOKUP(L10,'Base Vendeurs'!A:B,2,FALSE)) -> Valauto Roubaix | AV10: =+V10+AO10 -> 1025.17 | AW10: =IF(A10="","",+AV10/T10) -> 0.01920663 | AX10: =IF(AV10<0,"OUI","NON") -> NON | AY10: =+MargesVN[[#This Row],[Total COM]]+MargesVN[[#This Row],[EXT GIE]]+MargesVN[[#This Row],[Forfait immat]] -> 150.9221
A11: 10 | B11: C | C11: VW | D11: 46128 | E11: 46121 | L11: RXNTA | M11: 616 | O11: WVGZZZCT5TW519887 | P11: OUALI SLIMANE | Q11: TIGUAN | R11: 44655 | S11: 8791.67 | T11: =+R11+S11 -> 53446.67 | U11: 73 | V11: 1382.28 | W11: 95 | Y11: =+V11-W11+X11 -> 1287.28 | Z11: =(V11+X11)/T11 -> 0.02586279 | AA11: -5810.2 | AB11: 0 | AE11: 0.13 | AF11: 0.13 | AG11: =+Y11*AE11 -> 167.3464 | AI11: =+AG11+AH11 -> 167.3464 | AK11: 30 | AM11: =IF(AL11>0,100%,0%) -> 0 | AN11: =IF(A11>0,1,"") -> 1 | AQ11: =IF(AN11="","",+AM11/AN11) -> 0 | AR11: =IF(A11="","",VLOOKUP(A11,'Base Sites'!A:B,2,FALSE)) -> Valauto Roncq | AS11: =IF(C11="VW","VOLKSWAGEN",IF(C11="SE","SEAT",IF(C11="NI","NISSAN",IF(C11="HY","HYUNDAI",IF(C11="VU","VUL",IF(C11="sk","SKODA",IF(C11="ltsk","SKODA",IF(C11="CUPRA","CUPRA",IF(C11="AUDI","AUDI",""))))))))) -> VOLKSWAGEN | AU11: =IF(A11="","",VLOOKUP(L11,'Base Vendeurs'!A:B,2,FALSE)) -> Valauto Roubaix | AV11: =+V11+AO11 -> 1382.28 | AW11: =IF(A11="","",+AV11/T11) -> 0.02586279 | AX11: =IF(AV11<0,"OUI","NON") -> NON | AY11: =+MargesVN[[#This Row],[Total COM]]+MargesVN[[#This Row],[EXT GIE]]+MargesVN[[#This Row],[Forfait immat]] -> 197.3464
A12: 10 | B12: C | C12: VW | D12: 46136 | E12: 46144 | K12: 0 | L12: RXNTA | M12: 619 | N12: 516067 | O12: WVGZZZC17TY067136 | P12: TOUAF AHMED | Q12: T CROSS | R12: 28389 | S12: -1516.67 | T12: =+R12+S12 -> 26872.33 | U12: 46 | V12: 1076.06 | W12: 95 | Y12: =+V12-W12+X12 -> 981.06 | Z12: =(V12+X12)/T12 -> 0.04004342 | AA12: 0 | AB12: -3349.99 | AE12: 0.1 | AF12: 0.1 | AG12: =+Y12*AE12 -> 98.106 | AI12: =+AG12+AH12 -> 98.106 | AK12: 30 | AM12: =IF(AL12>0,100%,0%) -> 0 | AN12: =IF(A12>0,1,"") -> 1 | AQ12: =IF(AN12="","",+AM12/AN12) -> 0 | AR12: =IF(A12="","",VLOOKUP(A12,'Base Sites'!A:B,2,FALSE)) -> Valauto Roncq | AS12: =IF(C12="VW","VOLKSWAGEN",IF(C12="SE","SEAT",IF(C12="NI","NISSAN",IF(C12="HY","HYUNDAI",IF(C12="VU","VUL",IF(C12="sk","SKODA",IF(C12="ltsk","SKODA",IF(C12="CUPRA","CUPRA",IF(C12="AUDI","AUDI",""))))))))) -> VOLKSWAGEN | AU12: =IF(A12="","",VLOOKUP(L12,'Base Vendeurs'!A:B,2,FALSE)) -> Valauto Roubaix | AV12: =+V12+AO12 -> 1076.06 | AW12: =IF(A12="","",+AV12/T12) -> 0.04004342 | AX12: =IF(AV12<0,"OUI","NON") -> NON | AY12: =+MargesVN[[#This Row],[Total COM]]+MargesVN[[#This Row],[EXT GIE]]+MargesVN[[#This Row],[Forfait immat]] -> 128.106
A13: 10 | B13: C | C13: VW | D13: 46177 | E13: 46177 | K13: 0 | L13: RXNTA | M13: 620 | O13: WVGZZZA26TV038191 | P13: CRENEAU ERIC | Q13: T ROC | R13: 24380.67 | S13: 808.33 | T13: =+R13+S13 -> 25189 | U13: 62 | V13: 657.87 | W13: 95 | Y13: =+V13-W13+X13 -> 562.87 | Z13: =(V13+X13)/T13 -> 0.026117353 | AA13: 0 | AB13: -1250 | AE13: 0.13 | AF13: 0.12 | AG13: =+Y13*AE13 -> 73.1731 | AI13: =+AG13+AH13 -> 73.1731 | AK13: 30 | AM13: =IF(AL13>0,100%,0%) -> 0 | AN13: =IF(A13>0,1,"") -> 1 | AQ13: =IF(AN13="","",+AM13/AN13) -> 0 | AR13: =IF(A13="","",VLOOKUP(A13,'Base Sites'!A:B,2,FALSE)) -> Valauto Roncq | AS13: =IF(C13="VW","VOLKSWAGEN",IF(C13="SE","SEAT",IF(C13="NI","NISSAN",IF(C13="HY","HYUNDAI",IF(C13="VU","VUL",IF(C13="sk","SKODA",IF(C13="ltsk","SKODA",IF(C13="CUPRA","CUPRA",IF(C13="AUDI","AUDI",""))))))))) -> VOLKSWAGEN | AU13: =IF(A13="","",VLOOKUP(L13,'Base Vendeurs'!A:B,2,FALSE)) -> Valauto Roubaix | AV13: =+V13+AO13 -> 657.87 | AW13: =IF(A13="","",+AV13/T13) -> 0.026117353 | AX13: =IF(AV13<0,"OUI","NON") -> NON | AY13: =+MargesVN[[#This Row],[Total COM]]+MargesVN[[#This Row],[EXT GIE]]+MargesVN[[#This Row],[Forfait immat]] -> 103.1731
A14: 10 | B14: NL | C14: CUPRA | D14: 46148 | L14: VSJTI | M14: 621 | O14: VSSZZZP4T1068908 | P14: PROLYNE | Q14: TERRAMAR | R14: 49204.33 | S14: 1612.5 | T14: =+R14+S14 -> 50816.83 | U14: 20 | V14: 331.87 | W14: 22 | Y14: =+V14-W14+X14 -> 309.87 | Z14: =(V14+X14)/T14 -> 0.0065307104 | AA14: 0 | AB14: 611.67 | AF14: 0 | AG14: =+Y14*AE14 -> 0 | AI14: =+AG14+AH14 -> 0 | AK14: 0 | AL14: 0 | AM14: =IF(AL14>0,100%,0%) -> 0 | AN14: =IF(A14>0,1,"") -> 1 | AQ14: =IF(AN14="","",+AM14/AN14) -> 0 | AR14: =IF(A14="","",VLOOKUP(A14,'Base Sites'!A:B,2,FALSE)) -> Valauto Roncq | AS14: =IF(C14="VW","VOLKSWAGEN",IF(C14="SE","SEAT",IF(C14="NI","NISSAN",IF(C14="HY","HYUNDAI",IF(C14="VU","VUL",IF(C14="sk","SKODA",IF(C14="ltsk","SKODA",IF(C14="CUPRA","CUPRA",IF(C14="AUDI","AUDI",""))))))))) -> CUPRA | AU14: =IF(A14="","",VLOOKUP(L14,'Base Vendeurs'!A:B,2,FALSE)) -> Sociétés EST | AV14: =+V14+AO14 -> 331.87 | AW14: =IF(A14="","",+AV14/T14) -> 0.0065307104 | AX14: =IF(AV14<0,"OUI","NON") -> NON | AY14: =+MargesVN[[#This Row],[Total COM]]+MargesVN[[#This Row],[EXT GIE]]+MargesVN[[#This Row],[Forfait immat]] -> 0
A15: 70 | B15: C | C15: HY | D15: 46058 | E15: 46053 | K15: 0 | L15: LETLE | M15: 5059 | N15: 2104841989 | O15: KMHKR81EFPU180873 | P15: MERIEN VALENTIN | Q15: IONIQ | R15: 49500.48 | S15: 750 | T15: =+R15+S15 -> 50250.48 | U15: 986 | V15: -12931.51 | W15: -0.01 | Y15: =+V15-W15+X15 -> -12931.5 | Z15: =(V15+X15)/T15 -> -0.25734102 | AA15: -4681.54 | AB15: 0 | AD15: marge négative // Vieux stock | AF15: 0.13 | AG15: =+Y15*AE15 -> 0 | AH15: 300 | AI15: =+AG15+AH15 -> 300 | AK15: 0 | AL15: 100 | AM15: =IF(AL15>0,100%,0%) -> 1 | AN15: =IF(A15>0,1,"") -> 1 | AQ15: =IF(AN15="","",+AM15/AN15) -> 1 | AR15: =IF(A15="","",VLOOKUP(A15,'Base Sites'!A:B,2,FALSE)) -> Valauto Lomme | AS15: =IF(C15="VW","VOLKSWAGEN",IF(C15="SE","SEAT",IF(C15="NI","NISSAN",IF(C15="HY","HYUNDAI",IF(C15="VU","VUL",IF(C15="sk","SKODA",IF(C15="ltsk","SKODA",IF(C15="CUPRA","CUPRA",IF(C15="AUDI","AUDI",""))))))))) -> HYUNDAI | AU15: =IF(A15="","",VLOOKUP(L15,'Base Vendeurs'!A:B,2,FALSE)) -> Hyundai Lomme | AV15: =+V15+AO15 -> -12931.51 | AW15: =IF(A15="","",+AV15/T15) -> -0.25734102 | AX15: =IF(AV15<0,"OUI","NON") -> OUI | AY15: =+MargesVN[[#This Row],[Total COM]]+MargesVN[[#This Row],[EXT GIE]]+MargesVN[[#This Row],[Forfait immat]] -> 400
A16: 70 | B16: C | C16: HY | D16: 46169 | E16: 46172 | K16: 0 | L16: LELBO | M16: 5084 | N16: 2104860376 | O16: TMAK281GFPJ093622 | P16: SONNEVILLE MARYSE | Q16: KONA | R16: 34754.09 | S16: 0 | T16: =+R16+S16 -> 34754.09 | U16: 1072 | V16: -11953.03 | W16: 0 | Y16: =+V16-W16+X16 -> -11953.03 | Z16: =(V16+X16)/T16 -> -0.34393161 | AA16: -2084.76 | AB16: 0 | AD16: marge négative // Forfait vieux stock | AF16: 0.13 | AG16: =+Y16*AE16 -> 0 | AH16: 300 | AI16: =+AG16+AH16 -> 300 | AJ16: Hyundai Finance | AK16: 0 | AL16: 0 | AM16: =IF(AL16>0,100%,0%) -> 1 | AN16: =IF(A16>0,1,"") -> 1 | AQ16: =IF(AN16="","",+AM16/AN16) -> 1 | AR16: =IF(A16="","",VLOOKUP(A16,'Base Sites'!A:B,2,FALSE)) -> Valauto Lomme | AS16: =IF(C16="VW","VOLKSWAGEN",IF(C16="SE","SEAT",IF(C16="NI","NISSAN",IF(C16="HY","HYUNDAI",IF(C16="VU","VUL",IF(C16="sk","SKODA",IF(C16="ltsk","SKODA",IF(C16="CUPRA","CUPRA",IF(C16="AUDI","AUDI",""))))))))) -> HYUNDAI | AU16: =IF(A16="","",VLOOKUP(L16,'Base Vendeurs'!A:B,2,FALSE)) -> Hyundai Lomme | AV16: =+V16+AO16 -> -11953.03 | AW16: =IF(A16="","",+AV16/T16) -> -0.34393161 | AX16: =IF(AV16<0,"OUI","NON") -> OUI | AY16: =+MargesVN[[#This Row],[Total COM]]+MargesVN[[#This Row],[EXT GIE]]+MargesVN[[#This Row],[Forfait immat]] -> 300
A17: 70 | B17: C | C17: HY | D17: 46119 | E17: 46121 | K17: 0 | L17: LEGCH | M17: 5141 | N17: 2104937191 | O17: TMAH881A9RJ002231 | P17: CARRE DIDIER | Q17: KONA | R17: 34670.76 | S17: 541.67 | T17: =+R17+S17 -> 35212.43 | U17: 946 | V17: -3575.79 | W17: 0 | Y17: =+V17-W17+X17 -> -3575.79 | Z17: =(V17+X17)/T17 -> -0.10154908 | AA17: -6795.26 | AB17: 0 | AD17: Marge négative // Forfait vieux stock // 1 AN pour livrer | AF17: 0.13 | AG17: =+Y17*AE17 -> 0 | AI17: =+AG17+AH17 -> 0 | AJ17: Hyundai Finance | AK17: 0 | AL17: 50 | AM17: =IF(AL17>0,100%,0%) -> 1 | AN17: =IF(A17>0,1,"") -> 1 | AQ17: =IF(AN17="","",+AM17/AN17) -> 1 | AR17: =IF(A17="","",VLOOKUP(A17,'Base Sites'!A:B,2,FALSE)) -> Valauto Lomme | AS17: =IF(C17="VW","VOLKSWAGEN",IF(C17="SE","SEAT",IF(C17="NI","NISSAN",IF(C17="HY","HYUNDAI",IF(C17="VU","VUL",IF(C17="sk","SKODA",IF(C17="ltsk","SKODA",IF(C17="CUPRA","CUPRA",IF(C17="AUDI","AUDI",""))))))))) -> HYUNDAI | AU17: =IF(A17="","",VLOOKUP(L17,'Base Vendeurs'!A:B,2,FALSE)) -> Hyundai Lomme | AV17: =+V17+AO17 -> -3575.79 | AW17: =IF(A17="","",+AV17/T17) -> -0.10154908 | AX17: =IF(AV17<0,"OUI","NON") -> OUI | AY17: =+MargesVN[[#This Row],[Total COM]]+MargesVN[[#This Row],[EXT GIE]]+MargesVN[[#This Row],[Forfait immat]] -> 50
A18: 70 | B18: C | C18: HY | D18: 46063 | E18: 46066 | K18: 0 | L18: LETLE | M18: 5258 | N18: 2104698357 | O18: TMAH381BGPJ154164 | P18: PRUD'HOMME DOMINIQUE | Q18: I30 | R18: 25129.09 | S18: 0 | T18: =+R18+S18 -> 25129.09 | U18: 806 | V18: -1615.07 | Y18: =+V18-W18+X18 -> -1615.07 | Z18: =(V18+X18)/T18 -> -0.064270931 | AA18: -2322.66 | AB18: 0 | AD18: marge négative // Challenge vieux stock | AF18: 0.13 | AG18: =+Y18*AE18 -> 0 | AH18: 300 | AI18: =+AG18+AH18 -> 300 | AK18: 0 | AL18: 0 | AM18: =IF(AL18>0,100%,0%) -> 1 | AN18: =IF(A18>0,1,"") -> 1 | AQ18: =IF(AN18="","",+AM18/AN18) -> 1 | AR18: =IF(A18="","",VLOOKUP(A18,'Base Sites'!A:B,2,FALSE)) -> Valauto Lomme | AS18: =IF(C18="VW","VOLKSWAGEN",IF(C18="SE","SEAT",IF(C18="NI","NISSAN",IF(C18="HY","HYUNDAI",IF(C18="VU","VUL",IF(C18="sk","SKODA",IF(C18="ltsk","SKODA",IF(C18="CUPRA","CUPRA",IF(C18="AUDI","AUDI",""))))))))) -> HYUNDAI | AU18: =IF(A18="","",VLOOKUP(L18,'Base Vendeurs'!A:B,2,FALSE)) -> Hyundai Lomme | AV18: =+V18+AO18 -> -1615.07 | AW18: =IF(A18="","",+AV18/T18) -> -0.064270931 | AX18: =IF(AV18<0,"OUI","NON") -> OUI | AY18: =+MargesVN[[#This Row],[Total COM]]+MargesVN[[#This Row],[EXT GIE]]+MargesVN[[#This Row],[Forfait immat]] -> 300
A19: 70 | B19: C | C19: HY | D19: 46163 | E19: 46164 | L19: LELBO | M19: 5270 | N19: 2105035660 | O19: KMHKR81FPPU181397 | P19: LILA | Q19: IONIQ | R19: 53083.81 | S19: 333.33 | T19: =+R19+S19 -> 53417.14 | U19: 896 | V19: -8143.94 | W19: 0.01 | Y19: =+V19-W19+X19 -> -8143.95 | Z19: =(V19+X19)/T19 -> -0.1524593 | AA19: -17930.68 | AB19: 0 | AD19: marge négative // Forfait vieux stock | AF19: 0.13 | AG19: =+Y19*AE19 -> 0 | AH19: 300 | AI19: =+AG19+AH19 -> 300 | AJ19: Banque | AK19: 0 | AL19: 0 | AM19: =IF(AL19>0,100%,0%) -> 1 | AN19: =IF(A19>0,1,"") -> 1 | AQ19: =IF(AN19="","",+AM19/AN19) -> 1 | AR19: =IF(A19="","",VLOOKUP(A19,'Base Sites'!A:B,2,FALSE)) -> Valauto Lomme | AS19: =IF(C19="VW","VOLKSWAGEN",IF(C19="SE","SEAT",IF(C19="NI","NISSAN",IF(C19="HY","HYUNDAI",IF(C19="VU","VUL",IF(C19="sk","SKODA",IF(C19="ltsk","SKODA",IF(C19="CUPRA","CUPRA",IF(C19="AUDI","AUDI",""))))))))) -> HYUNDAI | AU19: =IF(A19="","",VLOOKUP(L19,'Base Vendeurs'!A:B,2,FALSE)) -> Hyundai Lomme | AV19: =+V19+AO19 -> -8143.94 | AW19: =IF(A19="","",+AV19/T19) -> -0.1524593 | AX19: =IF(AV19<0,"OUI","NON") -> OUI | AY19: =+MargesVN[[#This Row],[Total COM]]+MargesVN[[#This Row],[EXT GIE]]+MargesVN[[#This Row],[Forfait immat]] -> 300
A20: 70 | B20: C | C20: HY | D20: 46163 | E20: 46164 | L20: LELBO | M20: 5304 | N20: 2105046851 | O20: KMHKR81EFPU225522 | P20: LILA | Q20: IONIQ | R20: 49833.81 | S20: 0 | T20: =+R20+S20 -> 49833.81 | U20: 864 | V20: -8054.43 | W20: 0 | Y20: =+V20-W20+X20 -> -8054.43 | Z20: =(V20+X20)/T20 -> -0.16162581 | AA20: -11808.7 | AB20: 0 | AD20: marge négative // Forfait vieux stock | AF20: 0.13 | AG20: =+Y20*AE20 -> 0 | AH20: 300 | AI20: =+AG20+AH20 -> 300 | AJ20: Banque | AK20: 0 | AL20: 0 | AM20: =IF(AL20>0,100%,0%) -> 1 | AN20: =IF(A20>0,1,"") -> 1 | AQ20: =IF(AN20="","",+AM20/AN20) -> 1 | AR20: =IF(A20="","",VLOOKUP(A20,'Base Sites'!A:B,2,FALSE)) -> Valauto Lomme | AS20: =IF(C20="VW","VOLKSWAGEN",IF(C20="SE","SEAT",IF(C20="NI","NISSAN",IF(C20="HY","HYUNDAI",IF(C20="VU","VUL",IF(C20="sk","SKODA",IF(C20="ltsk","SKODA",IF(C20="CUPRA","CUPRA",IF(C20="AUDI","AUDI",""))))))))) -> HYUNDAI | AU20: =IF(A20="","",VLOOKUP(L20,'Base Vendeurs'!A:B,2,FALSE)) -> Hyundai Lomme | AV20: =+V20+AO20 -> -8054.43 | AW20: =IF(A20="","",+AV20/T20) -> -0.16162581 | AX20: =IF(AV20<0,"OUI","NON") -> OUI | AY20: =+MargesVN[[#This Row],[Total COM]]+MargesVN[[#This Row],[EXT GIE]]+MargesVN[[#This Row],[Forfait immat]] -> 300
A21: 70 | B21: C | C21: HY | D21: 46163 | E21: 46164 | L21: LELBO | M21: 5308 | N21: 2105048641 | O21: KMHKR81FPPU210158 | P21: LILA | Q21: IONIQ | R21: 52750.48 | S21: 750 | T21: =+R21+S21 -> 53500.48 | U21: 862 | V21: -8130.31 | W21: 0 | Y21: =+V21-W21+X21 -> -8130.31 | Z21: =(V21+X21)/T21 -> -0.15196705 | AA21: -12677.69 | AB21: 0 | AD21: marge négative // Forfait vieux stock | AF21: 0.13 | AG21: =+Y21*AE21 -> 0 | AH21: 300 | AI21: =+AG21+AH21 -> 300 | AJ21: Banque | AK21: 0 | AL21: 0 | AM21: =IF(AL21>0,100%,0%) -> 1 | AN21: =IF(A21>0,1,"") -> 1 | AQ21: =IF(AN21="","",+AM21/AN21) -> 1 | AR21: =IF(A21="","",VLOOKUP(A21,'Base Sites'!A:B,2,FALSE)) -> Valauto Lomme | AS21: =IF(C21="VW","VOLKSWAGEN",IF(C21="SE","SEAT",IF(C21="NI","NISSAN",IF(C21="HY","HYUNDAI",IF(C21="VU","VUL",IF(C21="sk","SKODA",IF(C21="ltsk","SKODA",IF(C21="CUPRA","CUPRA",IF(C21="AUDI","AUDI",""))))))))) -> HYUNDAI | AU21: =IF(A21="","",VLOOKUP(L21,'Base Vendeurs'!A:B,2,FALSE)) -> Hyundai Lomme | AV21: =+V21+AO21 -> -8130.31 | AW21: =IF(A21="","",+AV21/T21) -> -0.15196705 | AX21: =IF(AV21<0,"OUI","NON") -> OUI | AY21: =+MargesVN[[#This Row],[Total COM]]+MargesVN[[#This Row],[EXT GIE]]+MargesVN[[#This Row],[Forfait immat]] -> 300
A22: 70 | B22: C | C22: HY | D22: 46058 | E22: 46052 | K22: 0 | L22: LELBO | M22: 5368 | N22: 2105174011 | O22: TMAH351BGPJ227180 | P22: RIBEAUCOURT EDOUARD | Q22: I30 | R22: 24295.76 | S22: 583.33 | T22: =+R22+S22 -> 24879.09 | U22: 685 | V22: -2510.82 | W22: 0 | Y22: =+V22-W22+X22 -> -2510.82 | Z22: =(V22+X22)/T22 -> -0.10092089 | AA22: -2818.02 | AB22: 0 | AD22: marge négative // Challenge vieux stock | AF22: 0.13 | AG22: =+Y22*AE22 -> 0 | AH22: 300 | AI22: =+AG22+AH22 -> 300 | AK22: 0 | AL22: 0 | AM22: =IF(AL22>0,100%,0%) -> 1 | AN22: =IF(A22>0,1,"") -> 1 | AQ22: =IF(AN22="","",+AM22/AN22) -> 1 | AR22: =IF(A22="","",VLOOKUP(A22,'Base Sites'!A:B,2,FALSE)) -> Valauto Lomme | AS22: =IF(C22="VW","VOLKSWAGEN",IF(C22="SE","SEAT",IF(C22="NI","NISSAN",IF(C22="HY","HYUNDAI",IF(C22="VU","VUL",IF(C22="sk","SKODA",IF(C22="ltsk","SKODA",IF(C22="CUPRA","CUPRA",IF(C22="AUDI","AUDI",""))))))))) -> HYUNDAI | AU22: =IF(A22="","",VLOOKUP(L22,'Base Vendeurs'!A:B,2,FALSE)) -> Hyundai Lomme | AV22: =+V22+AO22 -> -2510.82 | AW22: =IF(A22="","",+AV22/T22) -> -0.10092089 | AX22: =IF(AV22<0,"OUI","NON") -> OUI | AY22: =+MargesVN[[#This Row],[Total COM]]+MargesVN[[#This Row],[EXT GIE]]+MargesVN[[#This Row],[Forfait immat]] -> 300
A23: 70 | B23: C | C23: HY | D23: 46175 | E23: 46176 | K23: 0 | L23: LELBO | M23: 5393 | N23: 2105209894 | O23: KMHM541A9PA017624 | P23: BELLAY CHRISTOPHE | Q23: IONIQ | R23: 51167.14 | S23: 825 | T23: =+R23+S23 -> 51992.14 | U23: 771 | V23: -6596.57 | W23: 0 | Y23: =+V23-W23+X23 -> -6596.57 | Z23: =(V23+X23)/T23 -> -0.12687629 | AA23: -9944.77 | AB23: 0 | AD23: marge négative // Challenge vieux stock | AF23: 0.13 | AG23: =+Y23*AE23 -> 0 | AH23: 300 | AI23: =+AG23+AH23 -> 300 | AK23: 0 | AM23: =IF(AL23>0,100%,0%) -> 0 | AN23: =IF(A23>0,1,"") -> 1 | AQ23: =IF(AN23="","",+AM23/AN23) -> 0 | AR23: =IF(A23="","",VLOOKUP(A23,'Base Sites'!A:B,2,FALSE)) -> Valauto Lomme | AS23: =IF(C23="VW","VOLKSWAGEN",IF(C23="SE","SEAT",IF(C23="NI","NISSAN",IF(C23="HY","HYUNDAI",IF(C23="VU","VUL",IF(C23="sk","SKODA",IF(C23="ltsk","SKODA",IF(C23="CUPRA","CUPRA",IF(C23="AUDI","AUDI",""))))))))) -> HYUNDAI | AU23: =IF(A23="","",VLOOKUP(L23,'Base Vendeurs'!A:B,2,FALSE)) -> Hyundai Lomme | AV23: =+V23+AO23 -> -6596.57 | AW23: =IF(A23="","",+AV23/T23) -> -0.12687629 | AX23: =IF(AV23<0,"OUI","NON") -> OUI | AY23: =+MargesVN[[#This Row],[Total COM]]+MargesVN[[#This Row],[EXT GIE]]+MargesVN[[#This Row],[Forfait immat]] -> 300
A24: 70 | B24: C | C24: HY | D24: 46024 | E24: 46027 | K24: 0 | L24: LEGCH | M24: 5519 | N24: 2105325853 | O24: NLHBN51H8SZ493976 | P24: DELMARE ERIC | Q24: I20 | R24: 16545.76 | S24: 458.33 | T24: =+R24+S24 -> 17004.09 | U24: 519 | V24: 739.64 | W24: 0 | Y24: =+V24-W24+X24 -> 739.64 | Z24: =(V24+X24)/T24 -> 0.04349777 | AA24: -792 | AB24: 0 | AE24: 0.13 | AF24: 0.13 | AG24: =+Y24*AE24 -> 96.1532 | AI24: =+AG24+AH24 -> 96.1532 | AK24: 0 | AL24: 100 | AM24: =IF(AL24>0,100%,0%) -> 1 | AN24: =IF(A24>0,1,"") -> 1 | AQ24: =IF(AN24="","",+AM24/AN24) -> 1 | AR24: =IF(A24="","",VLOOKUP(A24,'Base Sites'!A:B,2,FALSE)) -> Valauto Lomme | AS24: =IF(C24="VW","VOLKSWAGEN",IF(C24="SE","SEAT",IF(C24="NI","NISSAN",IF(C24="HY","HYUNDAI",IF(C24="VU","VUL",IF(C24="sk","SKODA",IF(C24="ltsk","SKODA",IF(C24="CUPRA","CUPRA",IF(C24="AUDI","AUDI",""))))))))) -> HYUNDAI | AU24: =IF(A24="","",VLOOKUP(L24,'Base Vendeurs'!A:B,2,FALSE)) -> Hyundai Lomme | AV24: =+V24+AO24 -> 739.64 | AW24: =IF(A24="","",+AV24/T24) -> 0.04349777 | AX24: =IF(AV24<0,"OUI","NON") -> NON | AY24: =+MargesVN[[#This Row],[Total COM]]+MargesVN[[#This Row],[EXT GIE]]+MargesVN[[#This Row],[Forfait immat]] -> 196.1532
A25: 70 | B25: C | C25: HY | D25: 46163 | E25: 46164 | K25: 0 | L25: LELBO | M25: 5530 | N25: 2105362616 | O25: KMHKR81A2SU316365 | P25: NOUGAOUI NABIL | Q25: IONIQ | R25: 49042.14 | S25: 575 | T25: =+R25+S25 -> 49617.14 | U25: 631 | V25: -4215.91 | W25: 0 | Y25: =+V25-W25+X25 -> -4215.91 | Z25: =(V25+X25)/T25 -> -0.084968823 | AA25: -11650.7 | AB25: 0 | AD25: mage négative // Forfait vieux stock | AF25: 0.13 | AG25: =+Y25*AE25 -> 0 | AH25: 300 | AI25: =+AG25+AH25 -> 300 | AJ25: Banque | AK25: 0 | AL25: 0 | AM25: =IF(AL25>0,100%,0%) -> 1 | AN25: =IF(A25>0,1,"") -> 1 | AQ25: =IF(AN25="","",+AM25/AN25) -> 1 | AR25: =IF(A25="","",VLOOKUP(A25,'Base Sites'!A:B,2,FALSE)) -> Valauto Lomme | AS25: =IF(C25="VW","VOLKSWAGEN",IF(C25="SE","SEAT",IF(C25="NI","NISSAN",IF(C25="HY","HYUNDAI",IF(C25="VU","VUL",IF(C25="sk","SKODA",IF(C25="ltsk","SKODA",IF(C25="CUPRA","CUPRA",IF(C25="AUDI","AUDI",""))))))))) -> HYUNDAI | AU25: =IF(A25="","",VLOOKUP(L25,'Base Vendeurs'!A:B,2,FALSE)) -> Hyundai Lomme | AV25: =+V25+AO25 -> -4215.91 | AW25: =IF(A25="","",+AV25/T25) -> -0.084968823 | AX25: =IF(AV25<0,"OUI","NON") -> OUI | AY25: =+MargesVN[[#This Row],[Total COM]]+MargesVN[[#This Row],[EXT GIE]]+MargesVN[[#This Row],[Forfait immat]] -> 300
A26: 70 | B26: C | C26: HY | D26: 46043 | E26: 46045 | K26: 0 | L26: LEGJA | M26: 5579 | N26: 2105325861 | O26: NLHBN51G0SZ549836 | P26: VERKINDERE CAMILLE | Q26: I20 | R26: 19879.09 | S26: 458.33 | T26: =+R26+S26 -> 20337.42 | U26: 443 | V26: 806.89 | W26: 0 | Y26: =+V26-W26+X26 -> 806.89 | Z26: =(V26+X26)/T26 -> 0.039675141 | AA26: -2021.76 | AB26: 0 | AE26: 0.13 | AF26: 0.13 | AG26: =+Y26*AE26 -> 104.8957 | AI26: =+AG26+AH26 -> 104.8957 | AJ26: Hyundai Finance | AK26: 30 | AL26: 100 | AM26: =IF(AL26>0,100%,0%) -> 1 | AN26: =IF(A26>0,1,"") -> 1 | AQ26: =IF(AN26="","",+AM26/AN26) -> 1 | AR26: =IF(A26="","",VLOOKUP(A26,'Base Sites'!A:B,2,FALSE)) -> Valauto Lomme | AS26: =IF(C26="VW","VOLKSWAGEN",IF(C26="SE","SEAT",IF(C26="NI","NISSAN",IF(C26="HY","HYUNDAI",IF(C26="VU","VUL",IF(C26="sk","SKODA",IF(C26="ltsk","SKODA",IF(C26="CUPRA","CUPRA",IF(C26="AUDI","AUDI",""))))))))) -> HYUNDAI | AU26: =IF(A26="","",VLOOKUP(L26,'Base Vendeurs'!A:B,2,FALSE)) -> Hyundai Lomme | AV26: =+V26+AO26 -> 806.89 | AW26: =IF(A26="","",+AV26/T26) -> 0.039675141 | AX26: =IF(AV26<0,"OUI","NON") -> NON | AY26: =+MargesVN[[#This Row],[Total COM]]+MargesVN[[#This Row],[EXT GIE]]+MargesVN[[#This Row],[Forfait immat]] -> 234.8957
A27: 70 | B27: C | C27: HY | D27: 46114 | E27: 46116 | K27: 0 | L27: LELBO | M27: 5593 | N27: 2105467969 | O27: NLHBN81G7SZ532095 | P27: THIRON MARIE-CAMILLE | Q27: BAYON | R27: 21795.76 | S27: 166.67 | T27: =+R27+S27 -> 21962.43 | U27: 486 | V27: 547.27 | W27: 0 | Y27: =+V27-W27+X27 -> 547.27 | Z27: =(V27+X27)/T27 -> 0.024918463 | AA27: -3569.26 | AB27: 0 | AD27: VN vendu 19990€ au lieu de 21990€ | AF27: 0.13 | AG27: =+Y27*AE27 -> 0 | AH27: 150 | AI27: =+AG27+AH27 -> 150 | AK27: 0 | AM27: =IF(AL27>0,100%,0%) -> 0 | AN27: =IF(A27>0,1,"") -> 1 | AQ27: =IF(AN27="","",+AM27/AN27) -> 0 | AR27: =IF(A27="","",VLOOKUP(A27,'Base Sites'!A:B,2,FALSE)) -> Valauto Lomme | AS27: =IF(C27="VW","VOLKSWAGEN",IF(C27="SE","SEAT",IF(C27="NI","NISSAN",IF(C27="HY","HYUNDAI",IF(C27="VU","VUL",IF(C27="sk","SKODA",IF(C27="ltsk","SKODA",IF(C27="CUPRA","CUPRA",IF(C27="AUDI","AUDI",""))))))))) -> HYUNDAI | AU27: =IF(A27="","",VLOOKUP(L27,'Base Vendeurs'!A:B,2,FALSE)) -> Hyundai Lomme | AV27: =+V27+AO27 -> 547.27 | AW27: =IF(A27="","",+AV27/T27) -> 0.024918463 | AX27: =IF(AV27<0,"OUI","NON") -> NON | AY27: =+MargesVN[[#This Row],[Total COM]]+MargesVN[[#This Row],[EXT GIE]]+MargesVN[[#This Row],[Forfait immat]] -> 150
A28: 70 | B28: C | C28: HY | D28: 46154 | E28: 46157 | L28: LEGCH | M28: 5604 | N28: 2105476163 | O28: NLHBN51G4SZ562234 | P28: COUTEREAU CAMILLE | Q28: I20 | R28: 18712.43 | S28: 166.67 | T28: =+R28+S28 -> 18879.1 | U28: 526 | V28: 1351.98 | W28: -0.01 | X28: -354.08 | Y28: =+V28-W28+X28 -> 997.91 | Z28: =(V28+X28)/T28 -> 0.052857393 | AA28: -2257.26 | AB28: 0 | AE28: 0.12 | AF28: 0.13 | AG28: =+Y28*AE28 -> 119.7492 | AI28: =+AG28+AH28 -> 119.7492 | AJ28: Hyundai Finance | AK28: 0 | AL28: 50 | AM28: =IF(AL28>0,100%,0%) -> 1 | AN28: =IF(A28>0,1,"") -> 1 | AQ28: =IF(AN28="","",+AM28/AN28) -> 1 | AR28: =IF(A28="","",VLOOKUP(A28,'Base Sites'!A:B,2,FALSE)) -> Valauto Lomme | AS28: =IF(C28="VW","VOLKSWAGEN",IF(C28="SE","SEAT",IF(C28="NI","NISSAN",IF(C28="HY","HYUNDAI",IF(C28="VU","VUL",IF(C28="sk","SKODA",IF(C28="ltsk","SKODA",IF(C28="CUPRA","CUPRA",IF(C28="AUDI","AUDI",""))))))))) -> HYUNDAI | AU28: =IF(A28="","",VLOOKUP(L28,'Base Vendeurs'!A:B,2,FALSE)) -> Hyundai Lomme | AV28: =+V28+AO28 -> 1351.98 | AW28: =IF(A28="","",+AV28/T28) -> 0.071612524 | AX28: =IF(AV28<0,"OUI","NON") -> NON | AY28: =+MargesVN[[#This Row],[Total COM]]+MargesVN[[#This Row],[EXT GIE]]+MargesVN[[#This Row],[Forfait immat]] -> 169.7492
A29: 70 | B29: C | C29: HY | D29: 46176 | E29: 46178 | L29: LEGCH | M29: 5606 | N29: 2105476168 | O29: NLHBR81G7SZ491584 | P29: SAWADOGO AURELIEN | Q29: BAYON | R29: 23045.76 | S29: 166.67 | T29: =+R29+S29 -> 23212.43 | U29: 548 | V29: -590.08 | W29: 0 | Y29: =+V29-W29+X29 -> -590.08 | Z29: =(V29+X29)/T29 -> -0.025420863 | AA29: -3679.26 | AB29: 0 | AD29: marge négative // 0 forfait demandé | AF29: 0.13 | AG29: =+Y29*AE29 -> 0 | AI29: =+AG29+AH29 -> 0 | AJ29: Hyundai Finance | AK29: 0 | AM29: =IF(AL29>0,100%,0%) -> 0 | AN29: =IF(A29>0,1,"") -> 1 | AQ29: =IF(AN29="","",+AM29/AN29) -> 0 | AR29: =IF(A29="","",VLOOKUP(A29,'Base Sites'!A:B,2,FALSE)) -> Valauto Lomme | AS29: =IF(C29="VW","VOLKSWAGEN",IF(C29="SE","SEAT",IF(C29="NI","NISSAN",IF(C29="HY","HYUNDAI",IF(C29="VU","VUL",IF(C29="sk","SKODA",IF(C29="ltsk","SKODA",IF(C29="CUPRA","CUPRA",IF(C29="AUDI","AUDI",""))))))))) -> HYUNDAI | AU29: =IF(A29="","",VLOOKUP(L29,'Base Vendeurs'!A:B,2,FALSE)) -> Hyundai Lomme | AV29: =+V29+AO29 -> -590.08 | AW29: =IF(A29="","",+AV29/T29) -> -0.025420863 | AX29: =IF(AV29<0,"OUI","NON") -> OUI | AY29: =+MargesVN[[#This Row],[Total COM]]+MargesVN[[#This Row],[EXT GIE]]+MargesVN[[#This Row],[Forfait immat]] -> 0
A30: 70 | B30: C | C30: HY | D30: 46198 | E30: 46178 | L30: LEGCH | M30: 5622 | N30: 2105493478 | O30: NLHDR51C1SZ333228 | P30: PARMENTIER MARIE-JEANNE | Q30: I10 | R30: 16670.76 | S30: 416.67 | T30: =+R30+S30 -> 17087.43 | U30: 553 | V30: 968.3 | W30: 0 | Y30: =+V30-W30+X30 -> 968.3 | Z30: =(V30+X30)/T30 -> 0.056667386 | AA30: -1830.26 | AB30: 0 | AE30: 0.13 | AF30: 0.13 | AG30: =+Y30*AE30 -> 125.879 | AI30: =+AG30+AH30 -> 125.879 | AJ30: Hyundai Finance | AK30: 30 | AL30: 100 | AM30: =IF(AL30>0,100%,0%) -> 1 | AN30: =IF(A30>0,1,"") -> 1 | AQ30: =IF(AN30="","",+AM30/AN30) -> 1 | AR30: =IF(A30="","",VLOOKUP(A30,'Base Sites'!A:B,2,FALSE)) -> Valauto Lomme | AS30: =IF(C30="VW","VOLKSWAGEN",IF(C30="SE","SEAT",IF(C30="NI","NISSAN",IF(C30="HY","HYUNDAI",IF(C30="VU","VUL",IF(C30="sk","SKODA",IF(C30="ltsk","SKODA",IF(C30="CUPRA","CUPRA",IF(C30="AUDI","AUDI",""))))))))) -> HYUNDAI | AU30: =IF(A30="","",VLOOKUP(L30,'Base Vendeurs'!A:B,2,FALSE)) -> Hyundai Lomme | AV30: =+V30+AO30 -> 968.3 | AW30: =IF(A30="","",+AV30/T30) -> 0.056667386 | AX30: =IF(AV30<0,"OUI","NON") -> NON | AY30: =+MargesVN[[#This Row],[Total COM]]+MargesVN[[#This Row],[EXT GIE]]+MargesVN[[#This Row],[Forfait immat]] -> 255.879
A31: 70 | B31: C | C31: HY | D31: 46192 | E31: 46192 | K31: 0 | L31: LEGJA | M31: 5676 | N31: 2105579562 | O31: NLHBR81G8SZ600781 | P31: FLAMENT AURELIEN | Q31: BAYON | R31: 23420.76 | S31: 0 | T31: =+R31+S31 -> 23420.76 | U31: 478 | V31: 297.1 | W31: 0 | Y31: =+V31-W31+X31 -> 297.1 | Z31: =(V31+X31)/T31 -> 0.012685327 | AA31: -1389.76 | AB31: -2292 | AD31: 0 comm demandée // Challenge VD | AF31: 0.13 | AG31: =+Y31*AE31 -> 0 | AH31: 300 | AI31: =+AG31+AH31 -> 300 | AJ31: Hyundai Finance | AK31: 0 | AL31: 100 | AM31: =IF(AL31>0,100%,0%) -> 1 | AN31: =IF(A31>0,1,"") -> 1 | AQ31: =IF(AN31="","",+AM31/AN31) -> 1 | AR31: =IF(A31="","",VLOOKUP(A31,'Base Sites'!A:B,2,FALSE)) -> Valauto Lomme | AS31: =IF(C31="VW","VOLKSWAGEN",IF(C31="SE","SEAT",IF(C31="NI","NISSAN",IF(C31="HY","HYUNDAI",IF(C31="VU","VUL",IF(C31="sk","SKODA",IF(C31="ltsk","SKODA",IF(C31="CUPRA","CUPRA",IF(C31="AUDI","AUDI",""))))))))) -> HYUNDAI | AU31: =IF(A31="","",VLOOKUP(L31,'Base Vendeurs'!A:B,2,FALSE)) -> Hyundai Lomme | AV31: =+V31+AO31 -> 297.1 | AW31: =IF(A31="","",+AV31/T31) -> 0.012685327 | AX31: =IF(AV31<0,"OUI","NON") -> NON | AY31: =+MargesVN[[#This Row],[Total COM]]+MargesVN[[#This Row],[EXT GIE]]+MargesVN[[#This Row],[Forfait immat]] -> 400
A32: 70 | B32: C | C32: HY | D32: 46072 | E32: 46074 | K32: 0 | L32: LEGJA | M32: 5682 | N32: 2105499998 | O32: KMHP58119SU095400 | P32: GROUX OLIVIER | Q32: SANTA FE | R32: 49000.48 | S32: 833.33 | T32: =+R32+S32 -> 49833.81 | U32: 358 | V32: 8945.1 | W32: -0.01 | X32: -7166 | Y32: =+V32-W32+X32 -> 1779.11 | Z32: =(V32+X32)/T32 -> 0.035700662 | AA32: -10334.54 | AB32: 0 | AD32: marge négative // Challenge vieux stock | AF32: 0.13 | AG32: =+Y32*AE32 -> 0 | AH32: 300 | AI32: =+AG32+AH32 -> 300 | AK32: 0 | AL32: 100 | AM32: =IF(AL32>0,100%,0%) -> 1 | AN32: =IF(A32>0,1,"") -> 1 | AQ32: =IF(AN32="","",+AM32/AN32) -> 1 | AR32: =IF(A32="","",VLOOKUP(A32,'Base Sites'!A:B,2,FALSE)) -> Valauto Lomme | AS32: =IF(C32="VW","VOLKSWAGEN",IF(C32="SE","SEAT",IF(C32="NI","NISSAN",IF(C32="HY","HYUNDAI",IF(C32="VU","VUL",IF(C32="sk","SKODA",IF(C32="ltsk","SKODA",IF(C32="CUPRA","CUPRA",IF(C32="AUDI","AUDI",""))))))))) -> HYUNDAI | AU32: =IF(A32="","",VLOOKUP(L32,'Base Vendeurs'!A:B,2,FALSE)) -> Hyundai Lomme | AV32: =+V32+AO32 -> 8945.1 | AW32: =IF(A32="","",+AV32/T32) -> 0.17949862 | AX32: =IF(AV32<0,"OUI","NON") -> NON | AY32: =+MargesVN[[#This Row],[Total COM]]+MargesVN[[#This Row],[EXT GIE]]+MargesVN[[#This Row],[Forfait immat]] -> 400
A33: 70 | B33: C | C33: HY | D33: 46028 | E33: 46028 | K33: 0 | L33: LEGCH | M33: 5702 | N33: 2105621085 | O33: TMAJB811XSJ333148 | P33: GUNST PHILIPPE | Q33: TUCSON | R33: 40792.14 | S33: 541.67 | T33: =+R33+S33 -> 41333.81 | U33: 288 | V33: 2630.27 | W33: 0 | Y33: =+V33-W33+X33 -> 2630.27 | Z33: =(V33+X33)/T33 -> 0.063634831 | AA33: -4131.54 | AB33: 0 | AE33: 0.13 | AF33: 0.13 | AG33: =+Y33*AE33 -> 341.9351 | AI33: =+AG33+AH33 -> 341.9351 | AJ33: Hyundai Finance | AK33: 0 | AL33: 50 | AM33: =IF(AL33>0,100%,0%) -> 1 | AN33: =IF(A33>0,1,"") -> 1 | AQ33: =IF(AN33="","",+AM33/AN33) -> 1 | AR33: =IF(A33="","",VLOOKUP(A33,'Base Sites'!A:B,2,FALSE)) -> Valauto Lomme | AS33: =IF(C33="VW","VOLKSWAGEN",IF(C33="SE","SEAT",IF(C33="NI","NISSAN",IF(C33="HY","HYUNDAI",IF(C33="VU","VUL",IF(C33="sk","SKODA",IF(C33="ltsk","SKODA",IF(C33="CUPRA","CUPRA",IF(C33="AUDI","AUDI",""))))))))) -> HYUNDAI | AU33: =IF(A33="","",VLOOKUP(L33,'Base Vendeurs'!A:B,2,FALSE)) -> Hyundai Lomme | AV33: =+V33+AO33 -> 2630.27 | AW33: =IF(A33="","",+AV33/T33) -> 0.063634831 | AX33: =IF(AV33<0,"OUI","NON") -> NON | AY33: =+MargesVN[[#This Row],[Total COM]]+MargesVN[[#This Row],[EXT GIE]]+MargesVN[[#This Row],[Forfait immat]] -> 391.9351
A34: 70 | B34: C | C34: HY | D34: 46065 | E34: 46067 | K34: 0 | L34: LELBO | M34: 5774 | N34: 2105737341 | O34: KMHB15124TW037827 | P34: NOLTE ALEXANDRE | Q34: INSTER | R34: 20379.09 | S34: 250 | T34: =+R34+S34 -> 20629.09 | U34: 227 | V34: 1706.88 | W34: 0 | Y34: =+V34-W34+X34 -> 1706.88 | Z34: =(V34+X34)/T34 -> 0.08274141 | AA34: -2070.26 | AB34: 0 | AE34: 0.13 | AF34: 0.13 | AG34: =+Y34*AE34 -> 221.8944 | AI34: =+AG34+AH34 -> 221.8944 | AJ34: Hyundai Finance | AK34: 0 | AL34: 0 | AM34: =IF(AL34>0,100%,0%) -> 1 | AN34: =IF(A34>0,1,"") -> 1 | AQ34: =IF(AN34="","",+AM34/AN34) -> 1 | AR34: =IF(A34="","",VLOOKUP(A34,'Base Sites'!A:B,2,FALSE)) -> Valauto Lomme | AS34: =IF(C34="VW","VOLKSWAGEN",IF(C34="SE","SEAT",IF(C34="NI","NISSAN",IF(C34="HY","HYUNDAI",IF(C34="VU","VUL",IF(C34="sk","SKODA",IF(C34="ltsk","SKODA",IF(C34="CUPRA","CUPRA",IF(C34="AUDI","AUDI",""))))))))) -> HYUNDAI | AU34: =IF(A34="","",VLOOKUP(L34,'Base Vendeurs'!A:B,2,FALSE)) -> Hyundai Lomme | AV34: =+V34+AO34 -> 1706.88 | AW34: =IF(A34="","",+AV34/T34) -> 0.08274141 | AX34: =IF(AV34<0,"OUI","NON") -> NON | AY34: =+MargesVN[[#This Row],[Total COM]]+MargesVN[[#This Row],[EXT GIE]]+MargesVN[[#This Row],[Forfait immat]] -> 221.8944
A35: 70 | B35: C | C35: HY | D35: 46059 | E35: 46053 | K35: 0 | L35: LELBO | M35: 5776 | N35: 2105723724 | O35: TMAH881B1SJ064706 | P35: BELBACHIR ANAIS | Q35: KONA | R35: 30254.09 | S35: 541.67 | T35: =+R35+S35 -> 30795.76 | U35: 213 | V35: 1170.18 | W35: 0 | Y35: =+V35-W35+X35 -> 1170.18 | Z35: =(V35+X35)/T35 -> 0.037998088 | AA35: -3180.26 | AB35: 0 | AE35: 0.13 | AF35: 0.13 | AG35: =+Y35*AE35 -> 152.1234 | AI35: =+AG35+AH35 -> 152.1234 | AJ35: Hyundai Finance | AK35: 0 | AL35: 0 | AM35: =IF(AL35>0,100%,0%) -> 1 | AN35: =IF(A35>0,1,"") -> 1 | AQ35: =IF(AN35="","",+AM35/AN35) -> 1 | AR35: =IF(A35="","",VLOOKUP(A35,'Base Sites'!A:B,2,FALSE)) -> Valauto Lomme | AS35: =IF(C35="VW","VOLKSWAGEN",IF(C35="SE","SEAT",IF(C35="NI","NISSAN",IF(C35="HY","HYUNDAI",IF(C35="VU","VUL",IF(C35="sk","SKODA",IF(C35="ltsk","SKODA",IF(C35="CUPRA","CUPRA",IF(C35="AUDI","AUDI",""))))))))) -> HYUNDAI | AU35: =IF(A35="","",VLOOKUP(L35,'Base Vendeurs'!A:B,2,FALSE)) -> Hyundai Lomme | AV35: =+V35+AO35 -> 1170.18 | AW35: =IF(A35="","",+AV35/T35) -> 0.037998088 | AX35: =IF(AV35<0,"OUI","NON") -> NON | AY35: =+MargesVN[[#This Row],[Total COM]]+MargesVN[[#This Row],[EXT GIE]]+MargesVN[[#This Row],[Forfait immat]] -> 152.1234
A36: 70 | B36: C | C36: HY | D36: 46059 | E36: 46044 | L36: LEGCH | M36: 5787 | N36: 2105758814 | O36: KMHHE8115SU132110 | P36: POTIER MARIE-JOSE | Q36: KONA | R36: 33004.09 | S36: 833.34 | T36: =+R36+S36 -> 33837.43 | U36: 190 | V36: 2830.09 | W36: 0 | Y36: =+V36-W36+X36 -> 2830.09 | Z36: =(V36+X36)/T36 -> 0.083637853 | AA36: -4014.76 | AB36: 0 | AE36: 0.13 | AF36: 0.13 | AG36: =+Y36*AE36 -> 367.9117 | AI36: =+AG36+AH36 -> 367.9117 | AJ36: Hyundai Finance | AK36: 0 | AL36: 100 | AM36: =IF(AL36>0,100%,0%) -> 1 | AN36: =IF(A36>0,1,"") -> 1 | AQ36: =IF(AN36="","",+AM36/AN36) -> 1 | AR36: =IF(A36="","",VLOOKUP(A36,'Base Sites'!A:B,2,FALSE)) -> Valauto Lomme | AS36: =IF(C36="VW","VOLKSWAGEN",IF(C36="SE","SEAT",IF(C36="NI","NISSAN",IF(C36="HY","HYUNDAI",IF(C36="VU","VUL",IF(C36="sk","SKODA",IF(C36="ltsk","SKODA",IF(C36="CUPRA","CUPRA",IF(C36="AUDI","AUDI",""))))))))) -> HYUNDAI | AU36: =IF(A36="","",VLOOKUP(L36,'Base Vendeurs'!A:B,2,FALSE)) -> Hyundai Lomme | AV36: =+V36+AO36 -> 2830.09 | AW36: =IF(A36="","",+AV36/T36) -> 0.083637853 | AX36: =IF(AV36<0,"OUI","NON") -> NON | AY36: =+MargesVN[[#This Row],[Total COM]]+MargesVN[[#This Row],[EXT GIE]]+MargesVN[[#This Row],[Forfait immat]] -> 467.9117
A37: 70 | B37: C | C37: HY | D37: 46059 | E37: 46060 | K37: 0 | L37: LETLE | M37: 5791 | N37: 2105758816 | O37: NLHBN51G5SZ631710 | P37: PLATTEAU THIERRY | Q37: I20 | R37: 20045.76 | S37: 458.33 | T37: =+R37+S37 -> 20504.09 | U37: 189 | V37: 1619.64 | W37: 0 | Y37: =+V37-W37+X37 -> 1619.64 | Z37: =(V37+X37)/T37 -> 0.07899107 | AA37: -792 | AB37: 0 | AE37: 0.13 | AF37: 0.13 | AG37: =+Y37*AE37 -> 210.5532 | AI37: =+AG37+AH37 -> 210.5532 | AJ37: Hyundai Finance | AK37: 0 | AL37: 50 | AM37: =IF(AL37>0,100%,0%) -> 1 | AN37: =IF(A37>0,1,"") -> 1 | AQ37: =IF(AN37="","",+AM37/AN37) -> 1 | AR37: =IF(A37="","",VLOOKUP(A37,'Base Sites'!A:B,2,FALSE)) -> Valauto Lomme | AS37: =IF(C37="VW","VOLKSWAGEN",IF(C37="SE","SEAT",IF(C37="NI","NISSAN",IF(C37="HY","HYUNDAI",IF(C37="VU","VUL",IF(C37="sk","SKODA",IF(C37="ltsk","SKODA",IF(C37="CUPRA","CUPRA",IF(C37="AUDI","AUDI",""))))))))) -> HYUNDAI | AU37: =IF(A37="","",VLOOKUP(L37,'Base Vendeurs'!A:B,2,FALSE)) -> Hyundai Lomme | AV37: =+V37+AO37 -> 1619.64 | AW37: =IF(A37="","",+AV37/T37) -> 0.07899107 | AX37: =IF(AV37<0,"OUI","NON") -> NON | AY37: =+MargesVN[[#This Row],[Total COM]]+MargesVN[[#This Row],[EXT GIE]]+MargesVN[[#This Row],[Forfait immat]] -> 260.5532
A38: 70 | B38: C | C38: HY | D38: 46191 | E38: 46192 | K38: 0 | L38: LEGCH | M38: 5793 | N38: 2105765574 | O38: KMHMY8158TA006285 | P38: BABOL SERVICES | Q38: IONIQ 9 | R38: 71750.48 | S38: 0 | T38: =+R38+S38 -> 71750.48 | U38: 316 | V38: 1864.83 | W38: 0 | Y38: =+V38-W38+X38 -> 1864.83 | Z38: =(V38+X38)/T38 -> 0.025990488 | AA38: -4304.54 | AB38: -15209.39 | AE38: 0.13 | AF38: 0.13 | AG38: =+Y38*AE38 -> 242.4279 | AI38: =+AG38+AH38 -> 242.4279 | AK38: 0 | AL38: 50 | AM38: =IF(AL38>0,100%,0%) -> 1 | AN38: =IF(A38>0,1,"") -> 1 | AQ38: =IF(AN38="","",+AM38/AN38) -> 1 | AR38: =IF(A38="","",VLOOKUP(A38,'Base Sites'!A:B,2,FALSE)) -> Valauto Lomme | AS38: =IF(C38="VW","VOLKSWAGEN",IF(C38="SE","SEAT",IF(C38="NI","NISSAN",IF(C38="HY","HYUNDAI",IF(C38="VU","VUL",IF(C38="sk","SKODA",IF(C38="ltsk","SKODA",IF(C38="CUPRA","CUPRA",IF(C38="AUDI","AUDI",""))))))))) -> HYUNDAI | AU38: =IF(A38="","",VLOOKUP(L38,'Base Vendeurs'!A:B,2,FALSE)) -> Hyundai Lomme | AV38: =+V38+AO38 -> 1864.83 | AW38: =IF(A38="","",+AV38/T38) -> 0.025990488 | AX38: =IF(AV38<0,"OUI","NON") -> NON | AY38: =+MargesVN[[#This Row],[Total COM]]+MargesVN[[#This Row],[EXT GIE]]+MargesVN[[#This Row],[Forfait immat]] -> 292.4279
A39: 70 | B39: C | C39: HY | D39: 46154 | E39: 46157 | K39: 0 | L39: LEGJA | M39: 5804 | N39: 2105787175 | O39: TMAJE8114SJ415030 | P39: VERREYDT JEREMY | Q39: TUCSON | R39: 39958.81 | S39: 541.67 | T39: =+R39+S39 -> 40500.48 | U39: 256 | V39: 2173.61 | W39: 0 | Y39: =+V39-W39+X39 -> 2173.61 | Z39: =(V39+X39)/T39 -> 0.053668747 | AA39: -5330.54 | AB39: 0 | AE39: 0.12 | AF39: 0.13 | AG39: =+Y39*AE39 -> 260.8332 | AI39: =+AG39+AH39 -> 260.8332 | AK39: 0 | AL39: 50 | AM39: =IF(AL39>0,100%,0%) -> 1 | AN39: =IF(A39>0,1,"") -> 1 | AQ39: =IF(AN39="","",+AM39/AN39) -> 1 | AR39: =IF(A39="","",VLOOKUP(A39,'Base Sites'!A:B,2,FALSE)) -> Valauto Lomme | AS39: =IF(C39="VW","VOLKSWAGEN",IF(C39="SE","SEAT",IF(C39="NI","NISSAN",IF(C39="HY","HYUNDAI",IF(C39="VU","VUL",IF(C39="sk","SKODA",IF(C39="ltsk","SKODA",IF(C39="CUPRA","CUPRA",IF(C39="AUDI","AUDI",""))))))))) -> HYUNDAI | AU39: =IF(A39="","",VLOOKUP(L39,'Base Vendeurs'!A:B,2,FALSE)) -> Hyundai Lomme | AV39: =+V39+AO39 -> 2173.61 | AW39: =IF(A39="","",+AV39/T39) -> 0.053668747 | AX39: =IF(AV39<0,"OUI","NON") -> NON | AY39: =+MargesVN[[#This Row],[Total COM]]+MargesVN[[#This Row],[EXT GIE]]+MargesVN[[#This Row],[Forfait immat]] -> 310.8332
A40: 70 | B40: C | C40: HY | D40: 46092 | E40: 46094 | L40: LEGJA | M40: 5811 | N40: 2105787158 | O40: KMHHB8111TU166507 | P40: WILCZAK EDOUARD | Q40: KONA | R40: 35504.09 | S40: 458.33 | T40: =+R40+S40 -> 35962.42 | U40: 191 | V40: 1082.31 | W40: 0 | Y40: =+V40-W40+X40 -> 1082.31 | Z40: =(V40+X40)/T40 -> 0.030095583 | AA40: -3784.26 | AB40: 0 | AE40: 0.13 | AF40: 0.13 | AG40: =+Y40*AE40 -> 140.7003 | AI40: =+AG40+AH40 -> 140.7003 | AJ40: Hyundai Finance | AL40: 100 | AM40: =IF(AL40>0,100%,0%) -> 1 | AN40: =IF(A40>0,1,"") -> 1 | AQ40: =IF(AN40="","",+AM40/AN40) -> 1 | AR40: =IF(A40="","",VLOOKUP(A40,'Base Sites'!A:B,2,FALSE)) -> Valauto Lomme | AS40: =IF(C40="VW","VOLKSWAGEN",IF(C40="SE","SEAT",IF(C40="NI","NISSAN",IF(C40="HY","HYUNDAI",IF(C40="VU","VUL",IF(C40="sk","SKODA",IF(C40="ltsk","SKODA",IF(C40="CUPRA","CUPRA",IF(C40="AUDI","AUDI",""))))))))) -> HYUNDAI | AU40: =IF(A40="","",VLOOKUP(L40,'Base Vendeurs'!A:B,2,FALSE)) -> Hyundai Lomme | AV40: =+V40+AO40 -> 1082.31 | AW40: =IF(A40="","",+AV40/T40) -> 0.030095583 | AX40: =IF(AV40<0,"OUI","NON") -> NON | AY40: =+MargesVN[[#This Row],[Total COM]]+MargesVN[[#This Row],[EXT GIE]]+MargesVN[[#This Row],[Forfait immat]] -> 240.7003
A41: 70 | B41: C | C41: HY | D41: 46147 | E41: 46147 | K41: 0 | L41: LELBO | M41: 5819 | N41: 2105803404 | O41: KMHB35117TW043591 | P41: RONSE VIRGINIE | Q41: INSTER | R41: 27287.43 | S41: 500 | T41: =+R41+S41 -> 27787.43 | U41: 229 | V41: 33.27 | W41: -0.01 | Y41: =+V41-W41+X41 -> 33.28 | Z41: =(V41+X41)/T41 -> 0.001197304 | AA41: -2482.26 | AB41: 0 | AE41: 0.12 | AF41: 0.13 | AG41: =+Y41*AE41 -> 3.9936 | AI41: =+AG41+AH41 -> 3.9936 | AJ41: Hyundai Finance | AK41: 0 | AM41: =IF(AL41>0,100%,0%) -> 0 | AN41: =IF(A41>0,1,"") -> 1 | AQ41: =IF(AN41="","",+AM41/AN41) -> 0 | AR41: =IF(A41="","",VLOOKUP(A41,'Base Sites'!A:B,2,FALSE)) -> Valauto Lomme | AS41: =IF(C41="VW","VOLKSWAGEN",IF(C41="SE","SEAT",IF(C41="NI","NISSAN",IF(C41="HY","HYUNDAI",IF(C41="VU","VUL",IF(C41="sk","SKODA",IF(C41="ltsk","SKODA",IF(C41="CUPRA","CUPRA",IF(C41="AUDI","AUDI",""))))))))) -> HYUNDAI | AU41: =IF(A41="","",VLOOKUP(L41,'Base Vendeurs'!A:B,2,FALSE)) -> Hyundai Lomme | AV41: =+V41+AO41 -> 33.27 | AW41: =IF(A41="","",+AV41/T41) -> 0.001197304 | AX41: =IF(AV41<0,"OUI","NON") -> NON | AY41: =+MargesVN[[#This Row],[Total COM]]+MargesVN[[#This Row],[EXT GIE]]+MargesVN[[#This Row],[Forfait immat]] -> 3.9936
A42: 70 | B42: C | C42: HY | D42: 46058 | E42: 46060 | I42: x | J42: x | K42: 75209.44 | L42: LEGJA | M42: 5827 | N42: 2105815379 | O42: TMAJB8119SJ419695 | P42: ARVAL SERVICE LEASE | Q42: TUCSON | R42: 30875.48 | S42: 541.67 | T42: =+R42+S42 -> 31417.15 | U42: 127 | V42: 274.79 | W42: -0.01 | Y42: =+V42-W42+X42 -> 274.8 | Z42: =(V42+X42)/T42 -> 0.0087464967 | AA42: -3863.32 | AB42: 0 | AD42: ok vn payé | AE42: 0.07 | AF42: 0.07 | AG42: =+Y42*AE42 -> 19.236 | AI42: =+AG42+AH42 -> 19.236 | AJ42: Hyundai Leasing | AK42: 0 | AL42: 50 | AM42: =IF(AL42>0,100%,0%) -> 1 | AN42: =IF(A42>0,1,"") -> 1 | AQ42: =IF(AN42="","",+AM42/AN42) -> 1 | AR42: =IF(A42="","",VLOOKUP(A42,'Base Sites'!A:B,2,FALSE)) -> Valauto Lomme | AS42: =IF(C42="VW","VOLKSWAGEN",IF(C42="SE","SEAT",IF(C42="NI","NISSAN",IF(C42="HY","HYUNDAI",IF(C42="VU","VUL",IF(C42="sk","SKODA",IF(C42="ltsk","SKODA",IF(C42="CUPRA","CUPRA",IF(C42="AUDI","AUDI",""))))))))) -> HYUNDAI | AU42: =IF(A42="","",VLOOKUP(L42,'Base Vendeurs'!A:B,2,FALSE)) -> Hyundai Lomme | AV42: =+V42+AO42 -> 274.79 | AW42: =IF(A42="","",+AV42/T42) -> 0.0087464967 | AX42: =IF(AV42<0,"OUI","NON") -> NON | AY42: =+MargesVN[[#This Row],[Total COM]]+MargesVN[[#This Row],[EXT GIE]]+MargesVN[[#This Row],[Forfait immat]] -> 69.236
A43: 70 | B43: C | C43: HY | D43: 46085 | E43: 46077 | K43: 0 | L43: LEGCH | M43: 5836 | N43: 2105817499 | O43: TMAJB8116SJ415880 | P43: PIAT ISABELLE | Q43: TUCSON | R43: 30875.48 | S43: 541.67 | T43: =+R43+S43 -> 31417.15 | U43: 154 | V43: 1209.3 | W43: -0.01 | Y43: =+V43-W43+X43 -> 1209.31 | Z43: =(V43+X43)/T43 -> 0.038491716 | AA43: -2917 | AB43: 0 | AE43: 0.13 | AF43: 0.13 | AG43: =+Y43*AE43 -> 157.2103 | AI43: =+AG43+AH43 -> 157.2103 | AJ43: Hyundai Finance | AK43: 0 | AL43: 100 | AM43: =IF(AL43>0,100%,0%) -> 1 | AN43: =IF(A43>0,1,"") -> 1 | AQ43: =IF(AN43="","",+AM43/AN43) -> 1 | AR43: =IF(A43="","",VLOOKUP(A43,'Base Sites'!A:B,2,FALSE)) -> Valauto Lomme | AS43: =IF(C43="VW","VOLKSWAGEN",IF(C43="SE","SEAT",IF(C43="NI","NISSAN",IF(C43="HY","HYUNDAI",IF(C43="VU","VUL",IF(C43="sk","SKODA",IF(C43="ltsk","SKODA",IF(C43="CUPRA","CUPRA",IF(C43="AUDI","AUDI",""))))))))) -> HYUNDAI | AU43: =IF(A43="","",VLOOKUP(L43,'Base Vendeurs'!A:B,2,FALSE)) -> Hyundai Lomme | AV43: =+V43+AO43 -> 1209.3 | AW43: =IF(A43="","",+AV43/T43) -> 0.038491716 | AX43: =IF(AV43<0,"OUI","NON") -> NON | AY43: =+MargesVN[[#This Row],[Total COM]]+MargesVN[[#This Row],[EXT GIE]]+MargesVN[[#This Row],[Forfait immat]] -> 257.2103
A44: 70 | B44: C | C44: HY | D44: 46072 | E44: 46072 | I44: x | J44: x | K44: 75209.44 | L44: LELBO | M44: 5841 | N44: 2105818258 | O44: TMAJF812XSJ386882 | P44: ARVAL SERVICE LEASE | Q44: TUCSON | R44: 34833.81 | S44: 541.67 | T44: =+R44+S44 -> 35375.48 | U44: 141 | V44: 514.38 | W44: 0 | Y44: =+V44-W44+X44 -> 514.38 | Z44: =(V44+X44)/T44 -> 0.01454058 | AA44: -4739.23 | AB44: -689.5 | AD44: ok vn payé | AE44: 0.13 | AF44: 0.13 | AG44: =+Y44*AE44 -> 66.8694 | AI44: =+AG44+AH44 -> 66.8694 | AJ44: Hyundai Leasing | AK44: 0 | AL44: 0 | AM44: =IF(AL44>0,100%,0%) -> 1 | AN44: =IF(A44>0,1,"") -> 1 | AQ44: =IF(AN44="","",+AM44/AN44) -> 1 | AR44: =IF(A44="","",VLOOKUP(A44,'Base Sites'!A:B,2,FALSE)) -> Valauto Lomme | AS44: =IF(C44="VW","VOLKSWAGEN",IF(C44="SE","SEAT",IF(C44="NI","NISSAN",IF(C44="HY","HYUNDAI",IF(C44="VU","VUL",IF(C44="sk","SKODA",IF(C44="ltsk","SKODA",IF(C44="CUPRA","CUPRA",IF(C44="AUDI","AUDI",""))))))))) -> HYUNDAI | AU44: =IF(A44="","",VLOOKUP(L44,'Base Vendeurs'!A:B,2,FALSE)) -> Hyundai Lomme | AV44: =+V44+AO44 -> 514.38 | AW44: =IF(A44="","",+AV44/T44) -> 0.01454058 | AX44: =IF(AV44<0,"OUI","NON") -> NON | AY44: =+MargesVN[[#This Row],[Total COM]]+MargesVN[[#This Row],[EXT GIE]]+MargesVN[[#This Row],[Forfait immat]] -> 66.8694
A45: 70 | B45: C | C45: HY | D45: 46030 | E45: 46023 | F45: x | J45: X | K45: 0 | L45: LELBO | M45: 5846 | N45: 2105833195 | O45: KMHB5512XTW052319 | P45: VERSCHEURE FRANCIS | Q45: INSTER | R45: 21629.09 | S45: 250 | T45: =+R45+S45 -> 21879.09 | U45: 79 | V45: 1070.83 | W45: 0 | Y45: =+V45-W45+X45 -> 1070.83 | Z45: =(V45+X45)/T45 -> 0.048943078 | AA45: -833 | AB45: 0 | AD45: déjà commissionnée | AF45: 0.07 | AG45: =+Y45*AE45 -> 0 | AI45: =+AG45+AH45 -> 0 | AJ45: Hyundai Finance | AK45: 0 | AL45: premium | AM45: =IF(AL45>0,100%,0%) -> 1 | AN45: =IF(A45>0,1,"") -> 1 | AQ45: =IF(AN45="","",+AM45/AN45) -> 1 | AR45: =IF(A45="","",VLOOKUP(A45,'Base Sites'!A:B,2,FALSE)) -> Valauto Lomme | AS45: =IF(C45="VW","VOLKSWAGEN",IF(C45="SE","SEAT",IF(C45="NI","NISSAN",IF(C45="HY","HYUNDAI",IF(C45="VU","VUL",IF(C45="sk","SKODA",IF(C45="ltsk","SKODA",IF(C45="CUPRA","CUPRA",IF(C45="AUDI","AUDI",""))))))))) -> HYUNDAI | AU45: =IF(A45="","",VLOOKUP(L45,'Base Vendeurs'!A:B,2,FALSE)) -> Hyundai Lomme | AV45: =+V45+AO45 -> 1070.83 | AW45: =IF(A45="","",+AV45/T45) -> 0.048943078 | AX45: =IF(AV45<0,"OUI","NON") -> NON | AY45: =+MargesVN[[#This Row],[Total COM]]+MargesVN[[#This Row],[EXT GIE]]+MargesVN[[#This Row],[Forfait immat]] -> #VALUE!
A46: 70 | B46: C | C46: HY | D46: 46063 | E46: 46067 | K46: 0 | L46: LEGJA | M46: 5851 | N46: 2105840895 | O46: TMAJA8119SJ433759 | P46: DEBON LOUIS | Q46: TUCSON | R46: 36617.14 | S46: 541.67 | T46: =+R46+S46 -> 37158.81 | U46: 112 | V46: 2697.22 | W46: 0 | Y46: =+V46-W46+X46 -> 2697.22 | Z46: =(V46+X46)/T46 -> 0.072586286 | AA46: -2017.91 | AB46: -1250 | AE46: 0.13 | AF46: 0.13 | AG46: =+Y46*AE46 -> 350.6386 | AI46: =+AG46+AH46 -> 350.6386 | AJ46: Hyundai Finance | AK46: 0 | AL46: 50 | AM46: =IF(AL46>0,100%,0%) -> 1 | AN46: =IF(A46>0,1,"") -> 1 | AQ46: =IF(AN46="","",+AM46/AN46) -> 1 | AR46: =IF(A46="","",VLOOKUP(A46,'Base Sites'!A:B,2,FALSE)) -> Valauto Lomme | AS46: =IF(C46="VW","VOLKSWAGEN",IF(C46="SE","SEAT",IF(C46="NI","NISSAN",IF(C46="HY","HYUNDAI",IF(C46="VU","VUL",IF(C46="sk","SKODA",IF(C46="ltsk","SKODA",IF(C46="CUPRA","CUPRA",IF(C46="AUDI","AUDI",""))))))))) -> HYUNDAI | AU46: =IF(A46="","",VLOOKUP(L46,'Base Vendeurs'!A:B,2,FALSE)) -> Hyundai Lomme | AV46: =+V46+AO46 -> 2697.22 | AW46: =IF(A46="","",+AV46/T46) -> 0.072586286 | AX46: =IF(AV46<0,"OUI","NON") -> NON | AY46: =+MargesVN[[#This Row],[Total COM]]+MargesVN[[#This Row],[EXT GIE]]+MargesVN[[#This Row],[Forfait immat]] -> 400.6386
A47: 70 | B47: C | C47: HY | D47: 46111 | E47: 46112 | L47: LEGCH | M47: 5862 | N47: 2105847198 | O47: TMAJA8114SJ429182 | P47: MEYER FABRICE | Q47: TUCSON | R47: 35792.14 | S47: 541.67 | T47: =+R47+S47 -> 36333.81 | U47: 151 | V47: 6503.57 | W47: 0 | X47: -3900 | Y47: =+V47-W47+X47 -> 2603.57 | Z47: =(V47+X47)/T47 -> 0.07165695 | AA47: -2916 | AB47: -1667 | AE47: 0.13 | AF47: 0.13 | AG47: =+Y47*AE47 -> 338.4641 | AI47: =+AG47+AH47 -> 338.4641 | AJ47: Hyundai Finance | AK47: 0 | AL47: 100 | AM47: =IF(AL47>0,100%,0%) -> 1 | AN47: =IF(A47>0,1,"") -> 1 | AQ47: =IF(AN47="","",+AM47/AN47) -> 1 | AR47: =IF(A47="","",VLOOKUP(A47,'Base Sites'!A:B,2,FALSE)) -> Valauto Lomme | AS47: =IF(C47="VW","VOLKSWAGEN",IF(C47="SE","SEAT",IF(C47="NI","NISSAN",IF(C47="HY","HYUNDAI",IF(C47="VU","VUL",IF(C47="sk","SKODA",IF(C47="ltsk","SKODA",IF(C47="CUPRA","CUPRA",IF(C47="AUDI","AUDI",""))))))))) -> HYUNDAI | AU47: =IF(A47="","",VLOOKUP(L47,'Base Vendeurs'!A:B,2,FALSE)) -> Hyundai Lomme | AV47: =+V47+AO47 -> 6503.57 | AW47: =IF(A47="","",+AV47/T47) -> 0.17899499 | AX47: =IF(AV47<0,"OUI","NON") -> NON | AY47: =+MargesVN[[#This Row],[Total COM]]+MargesVN[[#This Row],[EXT GIE]]+MargesVN[[#This Row],[Forfait immat]] -> 438.4641
A48: 70 | B48: C | C48: HY | D48: 46114 | E48: 46115 | K48: 0 | L48: LEGJA | M48: 5864 | N48: 2105847208 | O48: TMAJC8129SJ392214 | P48: GLADE DAVY | Q48: TUCSON | R48: 36417.14 | S48: 541.67 | T48: =+R48+S48 -> 36958.81 | U48: 154 | V48: 724.8 | W48: 0 | Y48: =+V48-W48+X48 -> 724.8 | Z48: =(V48+X48)/T48 -> 0.019611021 | AA48: -4623.06 | AB48: 0 | AE48: 0.13 | AF48: 0.13 | AG48: =+Y48*AE48 -> 94.224 | AI48: =+AG48+AH48 -> 94.224 | AJ48: Hyundai Finance | AK48: 0 | AM48: =IF(AL48>0,100%,0%) -> 0 | AN48: =IF(A48>0,1,"") -> 1 | AQ48: =IF(AN48="","",+AM48/AN48) -> 0 | AR48: =IF(A48="","",VLOOKUP(A48,'Base Sites'!A:B,2,FALSE)) -> Valauto Lomme | AS48: =IF(C48="VW","VOLKSWAGEN",IF(C48="SE","SEAT",IF(C48="NI","NISSAN",IF(C48="HY","HYUNDAI",IF(C48="VU","VUL",IF(C48="sk","SKODA",IF(C48="ltsk","SKODA",IF(C48="CUPRA","CUPRA",IF(C48="AUDI","AUDI",""))))))))) -> HYUNDAI | AU48: =IF(A48="","",VLOOKUP(L48,'Base Vendeurs'!A:B,2,FALSE)) -> Hyundai Lomme | AV48: =+V48+AO48 -> 724.8 | AW48: =IF(A48="","",+AV48/T48) -> 0.019611021 | AX48: =IF(AV48<0,"OUI","NON") -> NON | AY48: =+MargesVN[[#This Row],[Total COM]]+MargesVN[[#This Row],[EXT GIE]]+MargesVN[[#This Row],[Forfait immat]] -> 94.224
A49: 70 | B49: C | C49: HY | D49: 46108 | E49: 46113 | L49: LETLE | M49: 5867 | N49: 2105847196 | O49: TMAJD8118SJ424431 | P49: LANGLOIS JEAN PIERRE | Q49: TUCSON | R49: 34958.81 | S49: 541.67 | T49: =+R49+S49 -> 35500.48 | U49: 148 | V49: 1916.81 | W49: 0 | Y49: =+V49-W49+X49 -> 1916.81 | Z49: =(V49+X49)/T49 -> 0.053993918 | AA49: -2546.54 | AB49: 0 | AE49: 0.13 | AF49: 0.13 | AG49: =+Y49*AE49 -> 249.1853 | AI49: =+AG49+AH49 -> 249.1853 | AK49: 0 | AL49: 100 | AM49: =IF(AL49>0,100%,0%) -> 1 | AN49: =IF(A49>0,1,"") -> 1 | AQ49: =IF(AN49="","",+AM49/AN49) -> 1 | AR49: =IF(A49="","",VLOOKUP(A49,'Base Sites'!A:B,2,FALSE)) -> Valauto Lomme | AS49: =IF(C49="VW","VOLKSWAGEN",IF(C49="SE","SEAT",IF(C49="NI","NISSAN",IF(C49="HY","HYUNDAI",IF(C49="VU","VUL",IF(C49="sk","SKODA",IF(C49="ltsk","SKODA",IF(C49="CUPRA","CUPRA",IF(C49="AUDI","AUDI",""))))))))) -> HYUNDAI | AU49: =IF(A49="","",VLOOKUP(L49,'Base Vendeurs'!A:B,2,FALSE)) -> Hyundai Lomme | AV49: =+V49+AO49 -> 1916.81 | AW49: =IF(A49="","",+AV49/T49) -> 0.053993918 | AX49: =IF(AV49<0,"OUI","NON") -> NON | AY49: =+MargesVN[[#This Row],[Total COM]]+MargesVN[[#This Row],[EXT GIE]]+MargesVN[[#This Row],[Forfait immat]] -> 349.1853
A50: 70 | B50: NC | C50: HY | D50: 46093 | E50: 46104 | G50: x | L50: LELBO | M50: 5868 | N50: 2105847228 | O50: TMAJE8118SJ420800 | P50: AYVENS / TEMSYS | Q50: TUCSON | R50: 39958.81 | S50: 541.67 | T50: =+R50+S50 -> 40500.48 | U50: 133 | V50: 578.98 | W50: -0.01 | Y50: =+V50-W50+X50 -> 578.99 | Z50: =(V50+X50)/T50 -> 0.014295633 | AA50: -4992.64 | AB50: 411.66 | AD50: Ecart de marge | AE50: 0.13 | AF50: 0.13 | AG50: =+Y50*AE50 -> 75.2687 | AI50: =+AG50+AH50 -> 75.2687 | AJ50: Temsys | AK50: 0 | AM50: =IF(AL50>0,100%,0%) -> 0 | AN50: =IF(A50>0,1,"") -> 1 | AQ50: =IF(AN50="","",+AM50/AN50) -> 0 | AR50: =IF(A50="","",VLOOKUP(A50,'Base Sites'!A:B,2,FALSE)) -> Valauto Lomme | AS50: =IF(C50="VW","VOLKSWAGEN",IF(C50="SE","SEAT",IF(C50="NI","NISSAN",IF(C50="HY","HYUNDAI",IF(C50="VU","VUL",IF(C50="sk","SKODA",IF(C50="ltsk","SKODA",IF(C50="CUPRA","CUPRA",IF(C50="AUDI","AUDI",""))))))))) -> HYUNDAI | AU50: =IF(A50="","",VLOOKUP(L50,'Base Vendeurs'!A:B,2,FALSE)) -> Hyundai Lomme | AV50: =+V50+AO50 -> 578.98 | AW50: =IF(A50="","",+AV50/T50) -> 0.014295633 | AX50: =IF(AV50<0,"OUI","NON") -> NON | AY50: =+MargesVN[[#This Row],[Total COM]]+MargesVN[[#This Row],[EXT GIE]]+MargesVN[[#This Row],[Forfait immat]] -> 75.2687
A51: 70 | B51: C | C51: HY | D51: 46062 | E51: 46064 | K51: 0 | L51: LEGJA | M51: 5874 | N51: 2105847252 | O51: NLHBN81G8SZ658269 | P51: KERVAREC HUGUES | Q51: BAYON | R51: 21795.76 | S51: 458.33 | T51: =+R51+S51 -> 22254.09 | U51: 97 | V51: 1205.13 | W51: 0 | Y51: =+V51-W51+X51 -> 1205.13 | Z51: =(V51+X51)/T51 -> 0.054153192 | AA51: -1250 | AB51: 0 | AE51: 0.13 | AF51: 0.13 | AG51: =+Y51*AE51 -> 156.6669 | AI51: =+AG51+AH51 -> 156.6669 | AK51: 0 | AL51: 100 | AM51: =IF(AL51>0,100%,0%) -> 1 | AN51: =IF(A51>0,1,"") -> 1 | AQ51: =IF(AN51="","",+AM51/AN51) -> 1 | AR51: =IF(A51="","",VLOOKUP(A51,'Base Sites'!A:B,2,FALSE)) -> Valauto Lomme | AS51: =IF(C51="VW","VOLKSWAGEN",IF(C51="SE","SEAT",IF(C51="NI","NISSAN",IF(C51="HY","HYUNDAI",IF(C51="VU","VUL",IF(C51="sk","SKODA",IF(C51="ltsk","SKODA",IF(C51="CUPRA","CUPRA",IF(C51="AUDI","AUDI",""))))))))) -> HYUNDAI | AU51: =IF(A51="","",VLOOKUP(L51,'Base Vendeurs'!A:B,2,FALSE)) -> Hyundai Lomme | AV51: =+V51+AO51 -> 1205.13 | AW51: =IF(A51="","",+AV51/T51) -> 0.054153192 | AX51: =IF(AV51<0,"OUI","NON") -> NON | AY51: =+MargesVN[[#This Row],[Total COM]]+MargesVN[[#This Row],[EXT GIE]]+MargesVN[[#This Row],[Forfait immat]] -> 256.6669
A52: 70 | B52: C | C52: HY | D52: 46059 | E52: 46052 | K52: 0 | L52: LELBO | M52: 5875 | N52: 2105845486 | O52: KMHHB8117TU175132 | P52: IMALOUS GWENAELLE | Q52: KONA | R52: 28837.43 | S52: 0 | T52: =+R52+S52 -> 28837.43 | U52: 98 | V52: 1884.13 | W52: -0.01 | Y52: =+V52-W52+X52 -> 1884.14 | Z52: =(V52+X52)/T52 -> 0.065336266 | AA52: -2334 | AB52: 0 | AE52: 0.13 | AF52: 0.13 | AG52: =+Y52*AE52 -> 244.9382 | AI52: =+AG52+AH52 -> 244.9382 | AJ52: Hyundai Finance | AK52: 0 | AL52: 100 | AM52: =IF(AL52>0,100%,0%) -> 1 | AN52: =IF(A52>0,1,"") -> 1 | AQ52: =IF(AN52="","",+AM52/AN52) -> 1 | AR52: =IF(A52="","",VLOOKUP(A52,'Base Sites'!A:B,2,FALSE)) -> Valauto Lomme | AS52: =IF(C52="VW","VOLKSWAGEN",IF(C52="SE","SEAT",IF(C52="NI","NISSAN",IF(C52="HY","HYUNDAI",IF(C52="VU","VUL",IF(C52="sk","SKODA",IF(C52="ltsk","SKODA",IF(C52="CUPRA","CUPRA",IF(C52="AUDI","AUDI",""))))))))) -> HYUNDAI | AU52: =IF(A52="","",VLOOKUP(L52,'Base Vendeurs'!A:B,2,FALSE)) -> Hyundai Lomme | AV52: =+V52+AO52 -> 1884.13 | AW52: =IF(A52="","",+AV52/T52) -> 0.065336266 | AX52: =IF(AV52<0,"OUI","NON") -> NON | AY52: =+MargesVN[[#This Row],[Total COM]]+MargesVN[[#This Row],[EXT GIE]]+MargesVN[[#This Row],[Forfait immat]] -> 344.9382
A53: 70 | B53: C | C53: HY | D53: 46028 | E53: 46030 | L53: LEGCH | M53: 5880 | N53: 2105856765 | O53: NLHBM51H4SZ627000 | P53: HANZOFF ROMANE | Q53: I20 | R53: 16545.76 | S53: 458.33 | T53: =+R53+S53 -> 17004.09 | U53: 50 | V53: 450.17 | W53: 0 | Y53: =+V53-W53+X53 -> 450.17 | Z53: =(V53+X53)/T53 -> 0.026474219 | AA53: -792 | AB53: 0 | AE53: 0.07 | AF53: 0.07 | AG53: =+Y53*AE53 -> 31.5119 | AI53: =+AG53+AH53 -> 31.5119 | AJ53: Hyundai Finance | AK53: 0 | AL53: 50 | AM53: =IF(AL53>0,100%,0%) -> 1 | AN53: =IF(A53>0,1,"") -> 1 | AQ53: =IF(AN53="","",+AM53/AN53) -> 1 | AR53: =IF(A53="","",VLOOKUP(A53,'Base Sites'!A:B,2,FALSE)) -> Valauto Lomme | AS53: =IF(C53="VW","VOLKSWAGEN",IF(C53="SE","SEAT",IF(C53="NI","NISSAN",IF(C53="HY","HYUNDAI",IF(C53="VU","VUL",IF(C53="sk","SKODA",IF(C53="ltsk","SKODA",IF(C53="CUPRA","CUPRA",IF(C53="AUDI","AUDI",""))))))))) -> HYUNDAI | AU53: =IF(A53="","",VLOOKUP(L53,'Base Vendeurs'!A:B,2,FALSE)) -> Hyundai Lomme | AV53: =+V53+AO53 -> 450.17 | AW53: =IF(A53="","",+AV53/T53) -> 0.026474219 | AX53: =IF(AV53<0,"OUI","NON") -> NON | AY53: =+MargesVN[[#This Row],[Total COM]]+MargesVN[[#This Row],[EXT GIE]]+MargesVN[[#This Row],[Forfait immat]] -> 81.5119
A54: 70 | B54: C | C54: HY | D54: 46087 | E54: 46097 | K54: 0 | L54: LEGCH | M54: 5883 | N54: 2105856767 | O54: NLHBM51H1SZ627651 | P54: RAKOTOBE ONINTSOA | Q54: I20 | R54: 16545.76 | S54: 458.33 | T54: =+R54+S54 -> 17004.09 | U54: 109 | V54: 582.34 | W54: 0 | Y54: =+V54-W54+X54 -> 582.34 | Z54: =(V54+X54)/T54 -> 0.034247055 | AA54: -1458 | AB54: 0 | AE54: 0.13 | AF54: 0.13 | AG54: =+Y54*AE54 -> 75.7042 | AI54: =+AG54+AH54 -> 75.7042 | AJ54: Hyundai Finance | AK54: 0 | AL54: 50 | AM54: =IF(AL54>0,100%,0%) -> 1 | AN54: =IF(A54>0,1,"") -> 1 | AQ54: =IF(AN54="","",+AM54/AN54) -> 1 | AR54: =IF(A54="","",VLOOKUP(A54,'Base Sites'!A:B,2,FALSE)) -> Valauto Lomme | AS54: =IF(C54="VW","VOLKSWAGEN",IF(C54="SE","SEAT",IF(C54="NI","NISSAN",IF(C54="HY","HYUNDAI",IF(C54="VU","VUL",IF(C54="sk","SKODA",IF(C54="ltsk","SKODA",IF(C54="CUPRA","CUPRA",IF(C54="AUDI","AUDI",""))))))))) -> HYUNDAI | AU54: =IF(A54="","",VLOOKUP(L54,'Base Vendeurs'!A:B,2,FALSE)) -> Hyundai Lomme | AV54: =+V54+AO54 -> 582.34 | AW54: =IF(A54="","",+AV54/T54) -> 0.034247055 | AX54: =IF(AV54<0,"OUI","NON") -> NON | AY54: =+MargesVN[[#This Row],[Total COM]]+MargesVN[[#This Row],[EXT GIE]]+MargesVN[[#This Row],[Forfait immat]] -> 125.7042
A55: 70 | B55: C | C55: HY | D55: 46121 | E55: 46122 | K55: 0 | L55: LELBO | M55: 5888 | N55: 2105873891 | O55: TMAJB812XTJ442235 | P55: RIVALS CELINE | Q55: TUCSON | R55: 45292.14 | S55: 541.67 | T55: =+R55+S55 -> 45833.81 | U55: 136 | V55: 1854.72 | W55: 0 | Y55: =+V55-W55+X55 -> 1854.72 | Z55: =(V55+X55)/T55 -> 0.040466197 | AA55: -4832.54 | AB55: -833 | AE55: 0.13 | AF55: 0.13 | AG55: =+Y55*AE55 -> 241.1136 | AI55: =+AG55+AH55 -> 241.1136 | AJ55: Hyundai Finance | AK55: 0 | AL55: 100 | AM55: =IF(AL55>0,100%,0%) -> 1 | AN55: =IF(A55>0,1,"") -> 1 | AQ55: =IF(AN55="","",+AM55/AN55) -> 1 | AR55: =IF(A55="","",VLOOKUP(A55,'Base Sites'!A:B,2,FALSE)) -> Valauto Lomme | AS55: =IF(C55="VW","VOLKSWAGEN",IF(C55="SE","SEAT",IF(C55="NI","NISSAN",IF(C55="HY","HYUNDAI",IF(C55="VU","VUL",IF(C55="sk","SKODA",IF(C55="ltsk","SKODA",IF(C55="CUPRA","CUPRA",IF(C55="AUDI","AUDI",""))))))))) -> HYUNDAI | AU55: =IF(A55="","",VLOOKUP(L55,'Base Vendeurs'!A:B,2,FALSE)) -> Hyundai Lomme | AV55: =+V55+AO55 -> 1854.72 | AW55: =IF(A55="","",+AV55/T55) -> 0.040466197 | AX55: =IF(AV55<0,"OUI","NON") -> NON | AY55: =+MargesVN[[#This Row],[Total COM]]+MargesVN[[#This Row],[EXT GIE]]+MargesVN[[#This Row],[Forfait immat]] -> 341.1136
A56: 70 | B56: C | C56: HY | D56: 46024 | E56: 46025 | K56: 0 | L56: LETLE | M56: 5890 | N56: 2105873805 | O56: NLHBM81G3SZ677833 | P56: LUCAS ALEXIS | Q56: BAYON | R56: 18962.43 | S56: 458.33 | T56: =+R56+S56 -> 19420.76 | U56: 36 | V56: 1887.53 | W56: -0.01 | Y56: =+V56-W56+X56 -> 1887.54 | Z56: =(V56+X56)/T56 -> 0.097191356 | AA56: -1874.67 | AB56: 0 | AE56: 0.13 | AF56: 0.13 | AG56: =+Y56*AE56 -> 245.3802 | AI56: =+AG56+AH56 -> 245.3802 | AJ56: Hyundai Finance | AK56: 0 | AL56: 100 | AM56: =IF(AL56>0,100%,0%) -> 1 | AN56: =IF(A56>0,1,"") -> 1 | AQ56: =IF(AN56="","",+AM56/AN56) -> 1 | AR56: =IF(A56="","",VLOOKUP(A56,'Base Sites'!A:B,2,FALSE)) -> Valauto Lomme | AS56: =IF(C56="VW","VOLKSWAGEN",IF(C56="SE","SEAT",IF(C56="NI","NISSAN",IF(C56="HY","HYUNDAI",IF(C56="VU","VUL",IF(C56="sk","SKODA",IF(C56="ltsk","SKODA",IF(C56="CUPRA","CUPRA",IF(C56="AUDI","AUDI",""))))))))) -> HYUNDAI | AU56: =IF(A56="","",VLOOKUP(L56,'Base Vendeurs'!A:B,2,FALSE)) -> Hyundai Lomme | AV56: =+V56+AO56 -> 1887.53 | AW56: =IF(A56="","",+AV56/T56) -> 0.097191356 | AX56: =IF(AV56<0,"OUI","NON") -> NON | AY56: =+MargesVN[[#This Row],[Total COM]]+MargesVN[[#This Row],[EXT GIE]]+MargesVN[[#This Row],[Forfait immat]] -> 345.3802
A57: 70 | B57: C | C57: HY | D57: 46036 | E57: 46043 | I57: x | J57: x | K57: 495.13 | L57: LELBO | M57: 5891 | N57: 2105873812 | O57: KMHHC8116TU181789 | P57: TEMSYS | Q57: KONA | R57: 30795.76 | S57: 0 | T57: =+R57+S57 -> 30795.76 | U57: 48 | V57: 384.93 | W57: 0 | Y57: =+V57-W57+X57 -> 384.93 | Z57: =(V57+X57)/T57 -> 0.012499448 | AA57: -3479.01 | AB57: 0 | AD57: ok vn payé / solde facture atelier | AE57: 0.13 | AF57: 0.13 | AG57: =+Y57*AE57 -> 50.0409 | AI57: =+AG57+AH57 -> 50.0409 | AJ57: Temsys | AK57: 0 | AM57: =IF(AL57>0,100%,0%) -> 0 | AN57: =IF(A57>0,1,"") -> 1 | AQ57: =IF(AN57="","",+AM57/AN57) -> 0 | AR57: =IF(A57="","",VLOOKUP(A57,'Base Sites'!A:B,2,FALSE)) -> Valauto Lomme | AS57: =IF(C57="VW","VOLKSWAGEN",IF(C57="SE","SEAT",IF(C57="NI","NISSAN",IF(C57="HY","HYUNDAI",IF(C57="VU","VUL",IF(C57="sk","SKODA",IF(C57="ltsk","SKODA",IF(C57="CUPRA","CUPRA",IF(C57="AUDI","AUDI",""))))))))) -> HYUNDAI | AU57: =IF(A57="","",VLOOKUP(L57,'Base Vendeurs'!A:B,2,FALSE)) -> Hyundai Lomme | AV57: =+V57+AO57 -> 384.93 | AW57: =IF(A57="","",+AV57/T57) -> 0.012499448 | AX57: =IF(AV57<0,"OUI","NON") -> NON | AY57: =+MargesVN[[#This Row],[Total COM]]+MargesVN[[#This Row],[EXT GIE]]+MargesVN[[#This Row],[Forfait immat]] -> 50.0409
A58: 70 | B58: C | C58: HY | D58: 46027 | E58: 46028 | K58: 0 | L58: LELBO | M58: 5892 | N58: 2105872010 | O58: KMHHC8129SU282929 | P58: GREGOIRE INGRID | Q58: KONA | R58: 25170.76 | S58: 458.33 | T58: =+R58+S58 -> 25629.09 | U58: 39 | V58: 591.55 | W58: 0 | Y58: =+V58-W58+X58 -> 591.55 | Z58: =(V58+X58)/T58 -> 0.023081194 | AA58: -3341.68 | AB58: -2500 | AE58: 0.13 | AF58: 0.13 | AG58: =+Y58*AE58 -> 76.9015 | AI58: =+AG58+AH58 -> 76.9015 | AJ58: Hyundai Finance | AK58: 0 | AM58: =IF(AL58>0,100%,0%) -> 0 | AN58: =IF(A58>0,1,"") -> 1 | AQ58: =IF(AN58="","",+AM58/AN58) -> 0 | AR58: =IF(A58="","",VLOOKUP(A58,'Base Sites'!A:B,2,FALSE)) -> Valauto Lomme | AS58: =IF(C58="VW","VOLKSWAGEN",IF(C58="SE","SEAT",IF(C58="NI","NISSAN",IF(C58="HY","HYUNDAI",IF(C58="VU","VUL",IF(C58="sk","SKODA",IF(C58="ltsk","SKODA",IF(C58="CUPRA","CUPRA",IF(C58="AUDI","AUDI",""))))))))) -> HYUNDAI | AU58: =IF(A58="","",VLOOKUP(L58,'Base Vendeurs'!A:B,2,FALSE)) -> Hyundai Lomme | AV58: =+V58+AO58 -> 591.55 | AW58: =IF(A58="","",+AV58/T58) -> 0.023081194 | AX58: =IF(AV58<0,"OUI","NON") -> NON | AY58: =+MargesVN[[#This Row],[Total COM]]+MargesVN[[#This Row],[EXT GIE]]+MargesVN[[#This Row],[Forfait immat]] -> 76.9015
A59: 70 | B59: C | C59: HY | D59: 46041 | E59: 46024 | K59: 0 | L59: LETLE | M59: 5894 | N59: 2105872027 | O59: KMHHC8123SU282943 | P59: BLARET LAURA | Q59: KONA | R59: 25170.76 | S59: 458.33 | T59: =+R59+S59 -> 25629.09 | U59: 52 | V59: 364.93 | W59: 0 | Y59: =+V59-W59+X59 -> 364.93 | Z59: =(V59+X59)/T59 -> 0.014238898 | AA59: -3341.68 | AB59: -2500 | AE59: 0.13 | AF59: 0.13 | AG59: =+Y59*AE59 -> 47.4409 | AI59: =+AG59+AH59 -> 47.4409 | AK59: 0 | AL59: 100 | AM59: =IF(AL59>0,100%,0%) -> 1 | AN59: =IF(A59>0,1,"") -> 1 | AQ59: =IF(AN59="","",+AM59/AN59) -> 1 | AR59: =IF(A59="","",VLOOKUP(A59,'Base Sites'!A:B,2,FALSE)) -> Valauto Lomme | AS59: =IF(C59="VW","VOLKSWAGEN",IF(C59="SE","SEAT",IF(C59="NI","NISSAN",IF(C59="HY","HYUNDAI",IF(C59="VU","VUL",IF(C59="sk","SKODA",IF(C59="ltsk","SKODA",IF(C59="CUPRA","CUPRA",IF(C59="AUDI","AUDI",""))))))))) -> HYUNDAI | AU59: =IF(A59="","",VLOOKUP(L59,'Base Vendeurs'!A:B,2,FALSE)) -> Hyundai Lomme | AV59: =+V59+AO59 -> 364.93 | AW59: =IF(A59="","",+AV59/T59) -> 0.014238898 | AX59: =IF(AV59<0,"OUI","NON") -> NON | AY59: =+MargesVN[[#This Row],[Total COM]]+MargesVN[[#This Row],[EXT GIE]]+MargesVN[[#This Row],[Forfait immat]] -> 147.4409
A60: 70 | B60: C | C60: HY | D60: 46073 | E60: 46079 | K60: 0 | L60: LEGCH | M60: 5896 | N60: 2105873814 | O60: KMHHC811XTU181729 | P60: JAVAUX ALEXIS | Q60: KONA | R60: 30795.76 | S60: 0 | T60: =+R60+S60 -> 30795.76 | U60: 84 | V60: 1728.39 | W60: 0 | Y60: =+V60-W60+X60 -> 1728.39 | Z60: =(V60+X60)/T60 -> 0.056124285 | AA60: -1667 | AB60: 0 | AE60: 0.13 | AF60: 0.13 | AG60: =+Y60*AE60 -> 224.6907 | AI60: =+AG60+AH60 -> 224.6907 | AJ60: Hyundai Finance | AK60: 0 | AL60: 100 | AM60: =IF(AL60>0,100%,0%) -> 1 | AN60: =IF(A60>0,1,"") -> 1 | AQ60: =IF(AN60="","",+AM60/AN60) -> 1 | AR60: =IF(A60="","",VLOOKUP(A60,'Base Sites'!A:B,2,FALSE)) -> Valauto Lomme | AS60: =IF(C60="VW","VOLKSWAGEN",IF(C60="SE","SEAT",IF(C60="NI","NISSAN",IF(C60="HY","HYUNDAI",IF(C60="VU","VUL",IF(C60="sk","SKODA",IF(C60="ltsk","SKODA",IF(C60="CUPRA","CUPRA",IF(C60="AUDI","AUDI",""))))))))) -> HYUNDAI | AU60: =IF(A60="","",VLOOKUP(L60,'Base Vendeurs'!A:B,2,FALSE)) -> Hyundai Lomme | AV60: =+V60+AO60 -> 1728.39 | AW60: =IF(A60="","",+AV60/T60) -> 0.056124285 | AX60: =IF(AV60<0,"OUI","NON") -> NON | AY60: =+MargesVN[[#This Row],[Total COM]]+MargesVN[[#This Row],[EXT GIE]]+MargesVN[[#This Row],[Forfait immat]] -> 324.6907
A61: 70 | B61: NP | C61: HY | D61: 46122 | E61: 46113 | I61: x | K61: 30 | L61: LELBO | M61: 5899 | N61: 2105873790 | O61: NLHBR51G5SZ698070 | P61: LE FOULGOC PASCALE | Q61: I20 | R61: 21962.43 | S61: 458.33 | T61: =+R61+S61 -> 22420.76 | U61: 130 | V61: 1504.57 | W61: 0 | Y61: =+V61-W61+X61 -> 1504.57 | Z61: =(V61+X61)/T61 -> 0.067106111 | AA61: -2469.76 | AB61: 333 | AD61: ok vn payé solde client refacturation fps | AE61: 0.13 | AF61: 0.13 | AG61: =+Y61*AE61 -> 195.5941 | AI61: =+AG61+AH61 -> 195.5941 | AJ61: Hyundai Finance | AK61: 0 | AM61: =IF(AL61>0,100%,0%) -> 0 | AN61: =IF(A61>0,1,"") -> 1 | AQ61: =IF(AN61="","",+AM61/AN61) -> 0 | AR61: =IF(A61="","",VLOOKUP(A61,'Base Sites'!A:B,2,FALSE)) -> Valauto Lomme | AS61: =IF(C61="VW","VOLKSWAGEN",IF(C61="SE","SEAT",IF(C61="NI","NISSAN",IF(C61="HY","HYUNDAI",IF(C61="VU","VUL",IF(C61="sk","SKODA",IF(C61="ltsk","SKODA",IF(C61="CUPRA","CUPRA",IF(C61="AUDI","AUDI",""))))))))) -> HYUNDAI | AU61: =IF(A61="","",VLOOKUP(L61,'Base Vendeurs'!A:B,2,FALSE)) -> Hyundai Lomme | AV61: =+V61+AO61 -> 1504.57 | AW61: =IF(A61="","",+AV61/T61) -> 0.067106111 | AX61: =IF(AV61<0,"OUI","NON") -> NON | AY61: =+MargesVN[[#This Row],[Total COM]]+MargesVN[[#This Row],[EXT GIE]]+MargesVN[[#This Row],[Forfait immat]] -> 195.5941
A62: 70 | B62: C | C62: HY | D62: 46072 | E62: 46074 | K62: 0 | L62: LEGJA | M62: 5901 | N62: 2105873797 | O62: NLHDR51C7SZ404125 | P62: MEURRENS JACQUES | Q62: I10 | R62: 16670.76 | S62: 0 | T62: =+R62+S62 -> 16670.76 | U62: 80 | V62: 1539.17 | W62: 0 | Y62: =+V62-W62+X62 -> 1539.17 | Z62: =(V62+X62)/T62 -> 0.092327524 | AA62: -833 | AB62: 0 | AE62: 0.13 | AF62: 0.13 | AG62: =+Y62*AE62 -> 200.0921 | AI62: =+AG62+AH62 -> 200.0921 | AK62: 0 | AL62: 100 | AM62: =IF(AL62>0,100%,0%) -> 1 | AN62: =IF(A62>0,1,"") -> 1 | AQ62: =IF(AN62="","",+AM62/AN62) -> 1 | AR62: =IF(A62="","",VLOOKUP(A62,'Base Sites'!A:B,2,FALSE)) -> Valauto Lomme | AS62: =IF(C62="VW","VOLKSWAGEN",IF(C62="SE","SEAT",IF(C62="NI","NISSAN",IF(C62="HY","HYUNDAI",IF(C62="VU","VUL",IF(C62="sk","SKODA",IF(C62="ltsk","SKODA",IF(C62="CUPRA","CUPRA",IF(C62="AUDI","AUDI",""))))))))) -> HYUNDAI | AU62: =IF(A62="","",VLOOKUP(L62,'Base Vendeurs'!A:B,2,FALSE)) -> Hyundai Lomme | AV62: =+V62+AO62 -> 1539.17 | AW62: =IF(A62="","",+AV62/T62) -> 0.092327524 | AX62: =IF(AV62<0,"OUI","NON") -> NON | AY62: =+MargesVN[[#This Row],[Total COM]]+MargesVN[[#This Row],[EXT GIE]]+MargesVN[[#This Row],[Forfait immat]] -> 300.0921
A63: 70 | B63: NP | C63: HY | D63: 46078 | E63: 46080 | I63: x | K63: 75209.44 | L63: LTMEL | M63: 5906 | N63: 2105773809 | O63: TMAJD8116SJ410494 | P63: ARVAL SERVICE LEASE | Q63: TUCSON | R63: 34708.81 | S63: 541.67 | T63: =+R63+S63 -> 35250.48 | U63: 77 | V63: 324.64 | W63: 0.01 | Y63: =+V63-W63+X63 -> 324.63 | Z63: =(V63+X63)/T63 -> 0.00920952 | AA63: -3982.39 | AB63: 0 | AD63: ok vn payé | AF63: 0 | AG63: =+Y63*AE63 -> 0 | AI63: =+AG63+AH63 -> 0 | AK63: 0 | AL63: 0 | AM63: =IF(AL63>0,100%,0%) -> 1 | AN63: =IF(A63>0,1,"") -> 1 | AQ63: =IF(AN63="","",+AM63/AN63) -> 1 | AR63: =IF(A63="","",VLOOKUP(A63,'Base Sites'!A:B,2,FALSE)) -> Valauto Lomme | AS63: =IF(C63="VW","VOLKSWAGEN",IF(C63="SE","SEAT",IF(C63="NI","NISSAN",IF(C63="HY","HYUNDAI",IF(C63="VU","VUL",IF(C63="sk","SKODA",IF(C63="ltsk","SKODA",IF(C63="CUPRA","CUPRA",IF(C63="AUDI","AUDI",""))))))))) -> HYUNDAI | AU63: =IF(A63="","",VLOOKUP(L63,'Base Vendeurs'!A:B,2,FALSE)) -> Sociétés NORD | AV63: =+V63+AO63 -> 324.64 | AW63: =IF(A63="","",+AV63/T63) -> 0.00920952 | AX63: =IF(AV63<0,"OUI","NON") -> NON | AY63: =+MargesVN[[#This Row],[Total COM]]+MargesVN[[#This Row],[EXT GIE]]+MargesVN[[#This Row],[Forfait immat]] -> 0
A64: 70 | B64: C | C64: HY | D64: 46149 | E64: 46142 | K64: 0 | L64: LEGCH | M64: 5909 | N64: 2105873817 | O64: KMHHE8117TU190396 | P64: WARGNIER BERNARD | Q64: KONA | R64: 33420.76 | S64: 166.67 | T64: =+R64+S64 -> 33587.43 | U64: 142 | V64: 758.22 | W64: -0.01 | Y64: =+V64-W64+X64 -> 758.23 | Z64: =(V64+X64)/T64 -> 0.022574517 | AA64: -3889.76 | AB64: 0 | AE64: 0.12 | AF64: 0.13 | AG64: =+Y64*AE64 -> 90.9876 | AI64: =+AG64+AH64 -> 90.9876 | AK64: 0 | AL64: 100 | AM64: =IF(AL64>0,100%,0%) -> 1 | AN64: =IF(A64>0,1,"") -> 1 | AQ64: =IF(AN64="","",+AM64/AN64) -> 1 | AR64: =IF(A64="","",VLOOKUP(A64,'Base Sites'!A:B,2,FALSE)) -> Valauto Lomme | AS64: =IF(C64="VW","VOLKSWAGEN",IF(C64="SE","SEAT",IF(C64="NI","NISSAN",IF(C64="HY","HYUNDAI",IF(C64="VU","VUL",IF(C64="sk","SKODA",IF(C64="ltsk","SKODA",IF(C64="CUPRA","CUPRA",IF(C64="AUDI","AUDI",""))))))))) -> HYUNDAI | AU64: =IF(A64="","",VLOOKUP(L64,'Base Vendeurs'!A:B,2,FALSE)) -> Hyundai Lomme | AV64: =+V64+AO64 -> 758.22 | AW64: =IF(A64="","",+AV64/T64) -> 0.022574517 | AX64: =IF(AV64<0,"OUI","NON") -> NON | AY64: =+MargesVN[[#This Row],[Total COM]]+MargesVN[[#This Row],[EXT GIE]]+MargesVN[[#This Row],[Forfait immat]] -> 190.9876
A65: 70 | B65: C | C65: HY | D65: 46182 | E65: 46183 | K65: 0 | L65: LEGJA | M65: 5910 | N65: 2105881136 | O65: TMAH681A1TJ083318 | P65: ALGOO CHRISTIAN | Q65: KONA | R65: 34754.09 | S65: 250 | T65: =+R65+S65 -> 35004.09 | U65: 172 | V65: 1328.31 | W65: 0 | Y65: =+V65-W65+X65 -> 1328.31 | Z65: =(V65+X65)/T65 -> 0.03794728 | AA65: -2099.76 | AB65: -1333 | AE65: 0.13 | AF65: 0.13 | AG65: =+Y65*AE65 -> 172.6803 | AI65: =+AG65+AH65 -> 172.6803 | AJ65: Hyundai Finance | AK65: 0 | AM65: =IF(AL65>0,100%,0%) -> 0 | AN65: =IF(A65>0,1,"") -> 1 | AQ65: =IF(AN65="","",+AM65/AN65) -> 0 | AR65: =IF(A65="","",VLOOKUP(A65,'Base Sites'!A:B,2,FALSE)) -> Valauto Lomme | AS65: =IF(C65="VW","VOLKSWAGEN",IF(C65="SE","SEAT",IF(C65="NI","NISSAN",IF(C65="HY","HYUNDAI",IF(C65="VU","VUL",IF(C65="sk","SKODA",IF(C65="ltsk","SKODA",IF(C65="CUPRA","CUPRA",IF(C65="AUDI","AUDI",""))))))))) -> HYUNDAI | AU65: =IF(A65="","",VLOOKUP(L65,'Base Vendeurs'!A:B,2,FALSE)) -> Hyundai Lomme | AV65: =+V65+AO65 -> 1328.31 | AW65: =IF(A65="","",+AV65/T65) -> 0.03794728 | AX65: =IF(AV65<0,"OUI","NON") -> NON | AY65: =+MargesVN[[#This Row],[Total COM]]+MargesVN[[#This Row],[EXT GIE]]+MargesVN[[#This Row],[Forfait immat]] -> 172.6803
A66: 70 | B66: C | C66: HY | D66: 46146 | E66: 46147 | K66: 0 | L66: LEGJA | M66: 5911 | N66: 2105873809 | O66: KMHHB8112TU191464 | P66: PRUVOT KEVIN | Q66: KONA | R66: 28837.43 | S66: 166.67 | T66: =+R66+S66 -> 29004.1 | U66: 136 | V66: 2242.64 | W66: 0 | Y66: =+V66-W66+X66 -> 2242.64 | Z66: =(V66+X66)/T66 -> 0.077321482 | AA66: -3986.68 | AB66: 0 | AE66: 0.12 | AF66: 0.13 | AG66: =+Y66*AE66 -> 269.1168 | AI66: =+AG66+AH66 -> 269.1168 | AJ66: Hyundai Finance | AK66: 30 | AL66: 100 | AM66: =IF(AL66>0,100%,0%) -> 1 | AN66: =IF(A66>0,1,"") -> 1 | AQ66: =IF(AN66="","",+AM66/AN66) -> 1 | AR66: =IF(A66="","",VLOOKUP(A66,'Base Sites'!A:B,2,FALSE)) -> Valauto Lomme | AS66: =IF(C66="VW","VOLKSWAGEN",IF(C66="SE","SEAT",IF(C66="NI","NISSAN",IF(C66="HY","HYUNDAI",IF(C66="VU","VUL",IF(C66="sk","SKODA",IF(C66="ltsk","SKODA",IF(C66="CUPRA","CUPRA",IF(C66="AUDI","AUDI",""))))))))) -> HYUNDAI | AU66: =IF(A66="","",VLOOKUP(L66,'Base Vendeurs'!A:B,2,FALSE)) -> Hyundai Lomme | AV66: =+V66+AO66 -> 2242.64 | AW66: =IF(A66="","",+AV66/T66) -> 0.077321482 | AX66: =IF(AV66<0,"OUI","NON") -> NON | AY66: =+MargesVN[[#This Row],[Total COM]]+MargesVN[[#This Row],[EXT GIE]]+MargesVN[[#This Row],[Forfait immat]] -> 399.1168
A67: 70 | B67: C | C67: HY | D67: 46142 | E67: 46142 | K67: 0 | L67: LETLE | M67: 5912 | N67: 2105873823 | O67: KMHHE8115TU189649 | P67: MARTHE PHILIPPE | Q67: KONA | R67: 33420.77 | S67: 458.33 | T67: =+R67+S67 -> 33879.1 | U67: 132 | V67: 1841.48 | W67: 0 | Y67: =+V67-W67+X67 -> 1841.48 | Z67: =(V67+X67)/T67 -> 0.054354455 | AA67: -2032.26 | AB67: -1667 | AE67: 0.12 | AF67: 0.13 | AG67: =+Y67*AE67 -> 220.9776 | AI67: =+AG67+AH67 -> 220.9776 | AK67: 0 | AL67: 100 | AM67: =IF(AL67>0,100%,0%) -> 1 | AN67: =IF(A67>0,1,"") -> 1 | AQ67: =IF(AN67="","",+AM67/AN67) -> 1 | AR67: =IF(A67="","",VLOOKUP(A67,'Base Sites'!A:B,2,FALSE)) -> Valauto Lomme | AS67: =IF(C67="VW","VOLKSWAGEN",IF(C67="SE","SEAT",IF(C67="NI","NISSAN",IF(C67="HY","HYUNDAI",IF(C67="VU","VUL",IF(C67="sk","SKODA",IF(C67="ltsk","SKODA",IF(C67="CUPRA","CUPRA",IF(C67="AUDI","AUDI",""))))))))) -> HYUNDAI | AU67: =IF(A67="","",VLOOKUP(L67,'Base Vendeurs'!A:B,2,FALSE)) -> Hyundai Lomme | AV67: =+V67+AO67 -> 1841.48 | AW67: =IF(A67="","",+AV67/T67) -> 0.054354455 | AX67: =IF(AV67<0,"OUI","NON") -> NON | AY67: =+MargesVN[[#This Row],[Total COM]]+MargesVN[[#This Row],[EXT GIE]]+MargesVN[[#This Row],[Forfait immat]] -> 320.9776
A68: 70 | B68: C | C68: HY | D68: 46024 | E68: 46024 | K68: 0 | L68: LELBO | M68: 5913 | N68: 2105898342 | O68: KMHB15120TW058805 | P68: WAN MYLENE | Q68: INSTER | R68: 20379.09 | S68: 500 | T68: =+R68+S68 -> 20879.09 | U68: 14 | V68: 802 | W68: 0 | Y68: =+V68-W68+X68 -> 802 | Z68: =(V68+X68)/T68 -> 0.038411636 | AA68: 0 | AB68: 0 | AE68: 0.07 | AF68: 0.1 | AG68: =+Y68*AE68 -> 56.14 | AI68: =+AG68+AH68 -> 56.14 | AJ68: Hyundai Finance | AK68: 0 | AL68: 100 | AM68: =IF(AL68>0,100%,0%) -> 1 | AN68: =IF(A68>0,1,"") -> 1 | AQ68: =IF(AN68="","",+AM68/AN68) -> 1 | AR68: =IF(A68="","",VLOOKUP(A68,'Base Sites'!A:B,2,FALSE)) -> Valauto Lomme | AS68: =IF(C68="VW","VOLKSWAGEN",IF(C68="SE","SEAT",IF(C68="NI","NISSAN",IF(C68="HY","HYUNDAI",IF(C68="VU","VUL",IF(C68="sk","SKODA",IF(C68="ltsk","SKODA",IF(C68="CUPRA","CUPRA",IF(C68="AUDI","AUDI",""))))))))) -> HYUNDAI | AU68: =IF(A68="","",VLOOKUP(L68,'Base Vendeurs'!A:B,2,FALSE)) -> Hyundai Lomme | AV68: =+V68+AO68 -> 802 | AW68: =IF(A68="","",+AV68/T68) -> 0.038411636 | AX68: =IF(AV68<0,"OUI","NON") -> NON | AY68: =+MargesVN[[#This Row],[Total COM]]+MargesVN[[#This Row],[EXT GIE]]+MargesVN[[#This Row],[Forfait immat]] -> 156.14
A69: 70 | B69: C | C69: HY | D69: 46161 | E69: 46158 | K69: 0 | L69: LELBO | M69: 5916 | N69: 2105906463 | O69: TMAJE8121TJ452563 | P69: VANGREVELINGHE RAPHAELE | Q69: TUCSON | R69: 44458.81 | S69: 541.67 | T69: =+R69+S69 -> 45000.48 | U69: 151 | V69: 1467.1 | W69: 0 | Y69: =+V69-W69+X69 -> 1467.1 | Z69: =(V69+X69)/T69 -> 0.032601874 | AA69: -5313 | AB69: 0 | AE69: 0.12 | AF69: 0.13 | AG69: =+Y69*AE69 -> 176.052 | AI69: =+AG69+AH69 -> 176.052 | AJ69: Hyundai Finance | AK69: 0 | AM69: =IF(AL69>0,100%,0%) -> 0 | AN69: =IF(A69>0,1,"") -> 1 | AQ69: =IF(AN69="","",+AM69/AN69) -> 0 | AR69: =IF(A69="","",VLOOKUP(A69,'Base Sites'!A:B,2,FALSE)) -> Valauto Lomme | AS69: =IF(C69="VW","VOLKSWAGEN",IF(C69="SE","SEAT",IF(C69="NI","NISSAN",IF(C69="HY","HYUNDAI",IF(C69="VU","VUL",IF(C69="sk","SKODA",IF(C69="ltsk","SKODA",IF(C69="CUPRA","CUPRA",IF(C69="AUDI","AUDI",""))))))))) -> HYUNDAI | AU69: =IF(A69="","",VLOOKUP(L69,'Base Vendeurs'!A:B,2,FALSE)) -> Hyundai Lomme | AV69: =+V69+AO69 -> 1467.1 | AW69: =IF(A69="","",+AV69/T69) -> 0.032601874 | AX69: =IF(AV69<0,"OUI","NON") -> NON | AY69: =+MargesVN[[#This Row],[Total COM]]+MargesVN[[#This Row],[EXT GIE]]+MargesVN[[#This Row],[Forfait immat]] -> 176.052
A70: 70 | B70: C | C70: HY | D70: 46161 | E70: 46142 | K70: 0 | L70: LEGCH | M70: 5918 | N70: 2105906474 | O70: TMAJA8117TJ450710 | P70: MIENS NOLWENN | Q70: TUCSON | R70: 36625.47 | S70: 0 | T70: =+R70+S70 -> 36625.47 | U70: 151 | V70: 2743.99 | W70: 0.01 | Y70: =+V70-W70+X70 -> 2743.98 | Z70: =(V70+X70)/T70 -> 0.074920267 | AA70: -5833 | AB70: 0 | AE70: 0.12 | AF70: 0.13 | AG70: =+Y70*AE70 -> 329.2776 | AI70: =+AG70+AH70 -> 329.2776 | AJ70: Hyundai Finance | AK70: 0 | AL70: 100 | AM70: =IF(AL70>0,100%,0%) -> 1 | AN70: =IF(A70>0,1,"") -> 1 | AQ70: =IF(AN70="","",+AM70/AN70) -> 1 | AR70: =IF(A70="","",VLOOKUP(A70,'Base Sites'!A:B,2,FALSE)) -> Valauto Lomme | AS70: =IF(C70="VW","VOLKSWAGEN",IF(C70="SE","SEAT",IF(C70="NI","NISSAN",IF(C70="HY","HYUNDAI",IF(C70="VU","VUL",IF(C70="sk","SKODA",IF(C70="ltsk","SKODA",IF(C70="CUPRA","CUPRA",IF(C70="AUDI","AUDI",""))))))))) -> HYUNDAI | AU70: =IF(A70="","",VLOOKUP(L70,'Base Vendeurs'!A:B,2,FALSE)) -> Hyundai Lomme | AV70: =+V70+AO70 -> 2743.99 | AW70: =IF(A70="","",+AV70/T70) -> 0.074920267 | AX70: =IF(AV70<0,"OUI","NON") -> NON | AY70: =+MargesVN[[#This Row],[Total COM]]+MargesVN[[#This Row],[EXT GIE]]+MargesVN[[#This Row],[Forfait immat]] -> 429.2776
A71: 70 | B71: C | C71: HY | D71: 46062 | E71: 46065 | K71: 0 | L71: LEGCH | M71: 5919 | N71: 2105906494 | O71: KMHHE8111TU182956 | P71: MIDAVAINE JEAN | Q71: KONA | R71: 33420.76 | S71: 0 | T71: =+R71+S71 -> 33420.76 | U71: 52 | V71: 2953.49 | W71: 0 | Y71: =+V71-W71+X71 -> 2953.49 | Z71: =(V71+X71)/T71 -> 0.088372916 | AA71: -3584 | AB71: 0 | AE71: 0.13 | AF71: 0.13 | AG71: =+Y71*AE71 -> 383.9537 | AI71: =+AG71+AH71 -> 383.9537 | AK71: 0 | AL71: 100 | AM71: =IF(AL71>0,100%,0%) -> 1 | AN71: =IF(A71>0,1,"") -> 1 | AQ71: =IF(AN71="","",+AM71/AN71) -> 1 | AR71: =IF(A71="","",VLOOKUP(A71,'Base Sites'!A:B,2,FALSE)) -> Valauto Lomme | AS71: =IF(C71="VW","VOLKSWAGEN",IF(C71="SE","SEAT",IF(C71="NI","NISSAN",IF(C71="HY","HYUNDAI",IF(C71="VU","VUL",IF(C71="sk","SKODA",IF(C71="ltsk","SKODA",IF(C71="CUPRA","CUPRA",IF(C71="AUDI","AUDI",""))))))))) -> HYUNDAI | AU71: =IF(A71="","",VLOOKUP(L71,'Base Vendeurs'!A:B,2,FALSE)) -> Hyundai Lomme | AV71: =+V71+AO71 -> 2953.49 | AW71: =IF(A71="","",+AV71/T71) -> 0.088372916 | AX71: =IF(AV71<0,"OUI","NON") -> NON | AY71: =+MargesVN[[#This Row],[Total COM]]+MargesVN[[#This Row],[EXT GIE]]+MargesVN[[#This Row],[Forfait immat]] -> 483.9537
A72: 70 | B72: NP | C72: HY | D72: 46169 | E72: 46170 | I72: x | K72: 81071.06 | L72: LTMEL | M72: 5920 | N72: 2105771272 | O72: TMAJC8115SJ401479 | P72: ARVAL SERVICE LEASE | Q72: TUCSON | R72: 32208.81 | S72: 541.67 | T72: =+R72+S72 -> 32750.48 | U72: 148 | V72: 255.38 | W72: 0 | Y72: =+V72-W72+X72 -> 255.38 | Z72: =(V72+X72)/T72 -> 0.0077977483 | AA72: -3699.89 | AB72: 0 | AD72: ok vn payé | AF72: 0 | AG72: =+Y72*AE72 -> 0 | AI72: =+AG72+AH72 -> 0 | AK72: 0 | AL72: 0 | AM72: =IF(AL72>0,100%,0%) -> 1 | AN72: =IF(A72>0,1,"") -> 1 | AQ72: =IF(AN72="","",+AM72/AN72) -> 1 | AR72: =IF(A72="","",VLOOKUP(A72,'Base Sites'!A:B,2,FALSE)) -> Valauto Lomme | AS72: =IF(C72="VW","VOLKSWAGEN",IF(C72="SE","SEAT",IF(C72="NI","NISSAN",IF(C72="HY","HYUNDAI",IF(C72="VU","VUL",IF(C72="sk","SKODA",IF(C72="ltsk","SKODA",IF(C72="CUPRA","CUPRA",IF(C72="AUDI","AUDI",""))))))))) -> HYUNDAI | AU72: =IF(A72="","",VLOOKUP(L72,'Base Vendeurs'!A:B,2,FALSE)) -> Sociétés NORD | AV72: =+V72+AO72 -> 255.38 | AW72: =IF(A72="","",+AV72/T72) -> 0.0077977483 | AX72: =IF(AV72<0,"OUI","NON") -> NON | AY72: =+MargesVN[[#This Row],[Total COM]]+MargesVN[[#This Row],[EXT GIE]]+MargesVN[[#This Row],[Forfait immat]] -> 0
A73: 70 | B73: C | C73: HY | D73: 46121 | E73: 46123 | K73: 0 | L73: LELBO | M73: 5921 | N73: 2105847189 | O73: TMAJC8114TJ458046 | P73: VANDOORNE JULIEN | Q73: TUCSON | R73: 32958.81 | S73: 541.67 | T73: =+R73+S73 -> 33500.48 | U73: 100 | V73: 5472.44 | W73: 0 | X73: -4337.3 | Y73: =+V73-W73+X73 -> 1135.14 | Z73: =(V73+X73)/T73 -> 0.033884291 | AA73: -3750 | AB73: 0 | AE73: 0.13 | AF73: 0.13 | AG73: =+Y73*AE73 -> 147.5682 | AI73: =+AG73+AH73 -> 147.5682 | AJ73: Hyundai Finance | AK73: 0 | AM73: =IF(AL73>0,100%,0%) -> 0 | AN73: =IF(A73>0,1,"") -> 1 | AQ73: =IF(AN73="","",+AM73/AN73) -> 0 | AR73: =IF(A73="","",VLOOKUP(A73,'Base Sites'!A:B,2,FALSE)) -> Valauto Lomme | AS73: =IF(C73="VW","VOLKSWAGEN",IF(C73="SE","SEAT",IF(C73="NI","NISSAN",IF(C73="HY","HYUNDAI",IF(C73="VU","VUL",IF(C73="sk","SKODA",IF(C73="ltsk","SKODA",IF(C73="CUPRA","CUPRA",IF(C73="AUDI","AUDI",""))))))))) -> HYUNDAI | AU73: =IF(A73="","",VLOOKUP(L73,'Base Vendeurs'!A:B,2,FALSE)) -> Hyundai Lomme | AV73: =+V73+AO73 -> 5472.44 | AW73: =IF(A73="","",+AV73/T73) -> 0.16335408 | AX73: =IF(AV73<0,"OUI","NON") -> NON | AY73: =+MargesVN[[#This Row],[Total COM]]+MargesVN[[#This Row],[EXT GIE]]+MargesVN[[#This Row],[Forfait immat]] -> 147.5682
A74: 70 | B74: C | C74: HY | D74: 46072 | E74: 46073 | I74: x | J74: x | K74: 466.08 | L74: LELBO | M74: 5922 | N74: 2105912307 | O74: TMAJC8116TJ457111 | P74: ALPHABET FRANCE FLEET MANAGEMENT | Q74: TUCSON | R74: 32958.81 | S74: 541.67 | T74: =+R74+S74 -> 33500.48 | U74: 51 | V74: 1156.88 | W74: 0 | Y74: =+V74-W74+X74 -> 1156.88 | Z74: =(V74+X74)/T74 -> 0.034533237 | AA74: -5034.64 | AB74: 0 | AD74: ok vn payé / solde client facture atelier 03/2026 | AE74: 0.13 | AF74: 0.13 | AG74: =+Y74*AE74 -> 150.3944 | AI74: =+AG74+AH74 -> 150.3944 | AK74: 0 | AL74: 0 | AM74: =IF(AL74>0,100%,0%) -> 1 | AN74: =IF(A74>0,1,"") -> 1 | AQ74: =IF(AN74="","",+AM74/AN74) -> 1 | AR74: =IF(A74="","",VLOOKUP(A74,'Base Sites'!A:B,2,FALSE)) -> Valauto Lomme | AS74: =IF(C74="VW","VOLKSWAGEN",IF(C74="SE","SEAT",IF(C74="NI","NISSAN",IF(C74="HY","HYUNDAI",IF(C74="VU","VUL",IF(C74="sk","SKODA",IF(C74="ltsk","SKODA",IF(C74="CUPRA","CUPRA",IF(C74="AUDI","AUDI",""))))))))) -> HYUNDAI | AU74: =IF(A74="","",VLOOKUP(L74,'Base Vendeurs'!A:B,2,FALSE)) -> Hyundai Lomme | AV74: =+V74+AO74 -> 1156.88 | AW74: =IF(A74="","",+AV74/T74) -> 0.034533237 | AX74: =IF(AV74<0,"OUI","NON") -> NON | AY74: =+MargesVN[[#This Row],[Total COM]]+MargesVN[[#This Row],[EXT GIE]]+MargesVN[[#This Row],[Forfait immat]] -> 150.3944
A75: 70 | B75: C | C75: HY | D75: 46098 | E75: 46100 | I75: x | J75: x | K75: 41990.47 | L75: LELBO | M75: 5923 | N75: 2105912309 | O75: TMAJC8113TJ456708 | P75: ARVAL SERVICE LEASE | Q75: TUCSON | R75: 32958.81 | S75: 541.67 | T75: =+R75+S75 -> 33500.48 | U75: 77 | V75: 863.61 | W75: 0 | Y75: =+V75-W75+X75 -> 863.61 | Z75: =(V75+X75)/T75 -> 0.025779034 | AA75: -5737.98 | AB75: 0 | AD75: ok vn payé | AE75: 0.13 | AF75: 0.13 | AG75: =+Y75*AE75 -> 112.2693 | AI75: =+AG75+AH75 -> 112.2693 | AJ75: Hyundai Leasing | AK75: 0 | AL75: 100 | AM75: =IF(AL75>0,100%,0%) -> 1 | AN75: =IF(A75>0,1,"") -> 1 | AQ75: =IF(AN75="","",+AM75/AN75) -> 1 | AR75: =IF(A75="","",VLOOKUP(A75,'Base Sites'!A:B,2,FALSE)) -> Valauto Lomme | AS75: =IF(C75="VW","VOLKSWAGEN",IF(C75="SE","SEAT",IF(C75="NI","NISSAN",IF(C75="HY","HYUNDAI",IF(C75="VU","VUL",IF(C75="sk","SKODA",IF(C75="ltsk","SKODA",IF(C75="CUPRA","CUPRA",IF(C75="AUDI","AUDI",""))))))))) -> HYUNDAI | AU75: =IF(A75="","",VLOOKUP(L75,'Base Vendeurs'!A:B,2,FALSE)) -> Hyundai Lomme | AV75: =+V75+AO75 -> 863.61 | AW75: =IF(A75="","",+AV75/T75) -> 0.025779034 | AX75: =IF(AV75<0,"OUI","NON") -> NON | AY75: =+MargesVN[[#This Row],[Total COM]]+MargesVN[[#This Row],[EXT GIE]]+MargesVN[[#This Row],[Forfait immat]] -> 212.2693
A76: 70 | B76: C | C76: HY | D76: 46101 | E76: 46081 | K76: 0 | L76: LELBO | M76: 5926 | N76: 2105839972 | O76: KMHB1512XTW062117 | P76: GHOUBAYE SANDRINE | Q76: INSTER | R76: 20379.09 | S76: 0 | T76: =+R76+S76 -> 20379.09 | U76: 67 | V76: 772 | W76: 0 | Y76: =+V76-W76+X76 -> 772 | Z76: =(V76+X76)/T76 -> 0.037881966 | AA76: -833 | AB76: 833 | AE76: 0.07 | AF76: 0.07 | AG76: =+Y76*AE76 -> 54.04 | AI76: =+AG76+AH76 -> 54.04 | AJ76: Hyundai Finance | AK76: 0 | AL76: 50 | AM76: =IF(AL76>0,100%,0%) -> 1 | AN76: =IF(A76>0,1,"") -> 1 | AQ76: =IF(AN76="","",+AM76/AN76) -> 1 | AR76: =IF(A76="","",VLOOKUP(A76,'Base Sites'!A:B,2,FALSE)) -> Valauto Lomme | AS76: =IF(C76="VW","VOLKSWAGEN",IF(C76="SE","SEAT",IF(C76="NI","NISSAN",IF(C76="HY","HYUNDAI",IF(C76="VU","VUL",IF(C76="sk","SKODA",IF(C76="ltsk","SKODA",IF(C76="CUPRA","CUPRA",IF(C76="AUDI","AUDI",""))))))))) -> HYUNDAI | AU76: =IF(A76="","",VLOOKUP(L76,'Base Vendeurs'!A:B,2,FALSE)) -> Hyundai Lomme | AV76: =+V76+AO76 -> 772 | AW76: =IF(A76="","",+AV76/T76) -> 0.037881966 | AX76: =IF(AV76<0,"OUI","NON") -> NON | AY76: =+MargesVN[[#This Row],[Total COM]]+MargesVN[[#This Row],[EXT GIE]]+MargesVN[[#This Row],[Forfait immat]] -> 104.04
A77: 70 | B77: C | C77: HY | D77: 46042 | E77: 46043 | K77: 0 | L77: LELBO | M77: 5927 | N77: 2105845123 | O77: KMHB15122TW062967 | P77: BARBIER NATHALIE | Q77: INSTER | R77: 20379.09 | S77: 0 | T77: =+R77+S77 -> 20379.09 | U77: 8 | V77: 772 | W77: 0 | Y77: =+V77-W77+X77 -> 772 | Z77: =(V77+X77)/T77 -> 0.037881966 | AA77: 0 | AB77: 0 | AE77: 0.07 | AF77: 0.07 | AG77: =+Y77*AE77 -> 54.04 | AI77: =+AG77+AH77 -> 54.04 | AJ77: Hyundai Finance | AK77: 0 | AL77: 100 | AM77: =IF(AL77>0,100%,0%) -> 1 | AN77: =IF(A77>0,1,"") -> 1 | AQ77: =IF(AN77="","",+AM77/AN77) -> 1 | AR77: =IF(A77="","",VLOOKUP(A77,'Base Sites'!A:B,2,FALSE)) -> Valauto Lomme | AS77: =IF(C77="VW","VOLKSWAGEN",IF(C77="SE","SEAT",IF(C77="NI","NISSAN",IF(C77="HY","HYUNDAI",IF(C77="VU","VUL",IF(C77="sk","SKODA",IF(C77="ltsk","SKODA",IF(C77="CUPRA","CUPRA",IF(C77="AUDI","AUDI",""))))))))) -> HYUNDAI | AU77: =IF(A77="","",VLOOKUP(L77,'Base Vendeurs'!A:B,2,FALSE)) -> Hyundai Lomme | AV77: =+V77+AO77 -> 772 | AW77: =IF(A77="","",+AV77/T77) -> 0.037881966 | AX77: =IF(AV77<0,"OUI","NON") -> NON | AY77: =+MargesVN[[#This Row],[Total COM]]+MargesVN[[#This Row],[EXT GIE]]+MargesVN[[#This Row],[Forfait immat]] -> 154.04
A78: 70 | B78: NP | C78: HY | D78: 46072 | E78: 46072 | I78: x | K78: 75209.44 | L78: LTMEL | M78: 5928 | N78: 2105906484 | O78: TMAJA8115TJ453802 | P78: ARVAL SERVICE LEASE | Q78: TUCSON | R78: 36625.48 | S78: 541.67 | T78: =+R78+S78 -> 37167.15 | U78: 36 | V78: 1599.56 | W78: 0 | Y78: =+V78-W78+X78 -> 1599.56 | Z78: =(V78+X78)/T78 -> 0.043036929 | AA78: -5448.98 | AB78: 0 | AD78: ok vn payé | AF78: 0 | AG78: =+Y78*AE78 -> 0 | AI78: =+AG78+AH78 -> 0 | AK78: 0 | AL78: 0 | AM78: =IF(AL78>0,100%,0%) -> 1 | AN78: =IF(A78>0,1,"") -> 1 | AQ78: =IF(AN78="","",+AM78/AN78) -> 1 | AR78: =IF(A78="","",VLOOKUP(A78,'Base Sites'!A:B,2,FALSE)) -> Valauto Lomme | AS78: =IF(C78="VW","VOLKSWAGEN",IF(C78="SE","SEAT",IF(C78="NI","NISSAN",IF(C78="HY","HYUNDAI",IF(C78="VU","VUL",IF(C78="sk","SKODA",IF(C78="ltsk","SKODA",IF(C78="CUPRA","CUPRA",IF(C78="AUDI","AUDI",""))))))))) -> HYUNDAI | AU78: =IF(A78="","",VLOOKUP(L78,'Base Vendeurs'!A:B,2,FALSE)) -> Sociétés NORD | AV78: =+V78+AO78 -> 1599.56 | AW78: =IF(A78="","",+AV78/T78) -> 0.043036929 | AX78: =IF(AV78<0,"OUI","NON") -> NON | AY78: =+MargesVN[[#This Row],[Total COM]]+MargesVN[[#This Row],[EXT GIE]]+MargesVN[[#This Row],[Forfait immat]] -> 0
A79: 70 | B79: C | C79: HY | D79: 46154 | E79: 46155 | K79: 0 | L79: LETLE | M79: 5930 | N79: 2105906466 | O79: TMAJE8113TJ455553 | P79: HERVOT BERNARD | Q79: TUCSON | R79: 40458.81 | S79: 541.67 | T79: =+R79+S79 -> 41000.48 | U79: 113 | V79: 4830.77 | W79: 0 | Y79: =+V79-W79+X79 -> 4830.77 | Z79: =(V79+X79)/T79 -> 0.11782228 | AA79: -5000 | AB79: 0 | AE79: 0.12 | AF79: 0.13 | AG79: =+Y79*AE79 -> 579.6924 | AI79: =+AG79+AH79 -> 579.6924 | AK79: 0 | AL79: 100 | AM79: =IF(AL79>0,100%,0%) -> 1 | AN79: =IF(A79>0,1,"") -> 1 | AQ79: =IF(AN79="","",+AM79/AN79) -> 1 | AR79: =IF(A79="","",VLOOKUP(A79,'Base Sites'!A:B,2,FALSE)) -> Valauto Lomme | AS79: =IF(C79="VW","VOLKSWAGEN",IF(C79="SE","SEAT",IF(C79="NI","NISSAN",IF(C79="HY","HYUNDAI",IF(C79="VU","VUL",IF(C79="sk","SKODA",IF(C79="ltsk","SKODA",IF(C79="CUPRA","CUPRA",IF(C79="AUDI","AUDI",""))))))))) -> HYUNDAI | AU79: =IF(A79="","",VLOOKUP(L79,'Base Vendeurs'!A:B,2,FALSE)) -> Hyundai Lomme | AV79: =+V79+AO79 -> 4830.77 | AW79: =IF(A79="","",+AV79/T79) -> 0.11782228 | AX79: =IF(AV79<0,"OUI","NON") -> NON | AY79: =+MargesVN[[#This Row],[Total COM]]+MargesVN[[#This Row],[EXT GIE]]+MargesVN[[#This Row],[Forfait immat]] -> 679.6924
A80: 70 | B80: C | C80: HY | D80: 46059 | E80: 46050 | K80: 0 | L80: LETLE | M80: 5931 | N80: 2105779413 | O80: TMAH881B8SJ055596 | P80: DUQUENOY CELINE | Q80: KONA | R80: 31087.43 | S80: 541.67 | T80: =+R80+S80 -> 31629.1 | U80: 18 | V80: 1618.75 | W80: -0.01 | Y80: =+V80-W80+X80 -> 1618.76 | Z80: =(V80+X80)/T80 -> 0.051179136 | AA80: -1333 | AB80: 0 | AE80: 0.07 | AF80: 0.1 | AG80: =+Y80*AE80 -> 113.3132 | AI80: =+AG80+AH80 -> 113.3132 | AJ80: Hyundai Finance | AK80: 0 | AL80: 50 | AM80: =IF(AL80>0,100%,0%) -> 1 | AN80: =IF(A80>0,1,"") -> 1 | AQ80: =IF(AN80="","",+AM80/AN80) -> 1 | AR80: =IF(A80="","",VLOOKUP(A80,'Base Sites'!A:B,2,FALSE)) -> Valauto Lomme | AS80: =IF(C80="VW","VOLKSWAGEN",IF(C80="SE","SEAT",IF(C80="NI","NISSAN",IF(C80="HY","HYUNDAI",IF(C80="VU","VUL",IF(C80="sk","SKODA",IF(C80="ltsk","SKODA",IF(C80="CUPRA","CUPRA",IF(C80="AUDI","AUDI",""))))))))) -> HYUNDAI | AU80: =IF(A80="","",VLOOKUP(L80,'Base Vendeurs'!A:B,2,FALSE)) -> Hyundai Lomme | AV80: =+V80+AO80 -> 1618.75 | AW80: =IF(A80="","",+AV80/T80) -> 0.051179136 | AX80: =IF(AV80<0,"OUI","NON") -> NON | AY80: =+MargesVN[[#This Row],[Total COM]]+MargesVN[[#This Row],[EXT GIE]]+MargesVN[[#This Row],[Forfait immat]] -> 163.3132
A81: 70 | B81: NP | C81: HY | D81: 46065 | E81: 46069 | I81: x | K81: 75209.44 | L81: LTMEL | M81: 5932 | N81: 2105902475 | O81: TMAH881A9TJ083478 | P81: ARVAL SERVICE LEASE | Q81: KONA | R81: 33920.76 | S81: 541.67 | T81: =+R81+S81 -> 34462.43 | U81: 24 | V81: 303.86 | W81: 0.01 | Y81: =+V81-W81+X81 -> 303.85 | Z81: =(V81+X81)/T81 -> 0.008817138 | AA81: -4685.79 | AB81: 0 | AD81: ok vn payé | AF81: 0 | AG81: =+Y81*AE81 -> 0 | AI81: =+AG81+AH81 -> 0 | AK81: 0 | AL81: 0 | AM81: =IF(AL81>0,100%,0%) -> 1 | AN81: =IF(A81>0,1,"") -> 1 | AQ81: =IF(AN81="","",+AM81/AN81) -> 1 | AR81: =IF(A81="","",VLOOKUP(A81,'Base Sites'!A:B,2,FALSE)) -> Valauto Lomme | AS81: =IF(C81="VW","VOLKSWAGEN",IF(C81="SE","SEAT",IF(C81="NI","NISSAN",IF(C81="HY","HYUNDAI",IF(C81="VU","VUL",IF(C81="sk","SKODA",IF(C81="ltsk","SKODA",IF(C81="CUPRA","CUPRA",IF(C81="AUDI","AUDI",""))))))))) -> HYUNDAI | AU81: =IF(A81="","",VLOOKUP(L81,'Base Vendeurs'!A:B,2,FALSE)) -> Sociétés NORD | AV81: =+V81+AO81 -> 303.86 | AW81: =IF(A81="","",+AV81/T81) -> 0.008817138 | AX81: =IF(AV81<0,"OUI","NON") -> NON | AY81: =+MargesVN[[#This Row],[Total COM]]+MargesVN[[#This Row],[EXT GIE]]+MargesVN[[#This Row],[Forfait immat]] -> 0
A82: 70 | B82: C | C82: HY | D82: 46045 | E82: 46048 | L82: LEGCH | M82: 5933 | N82: 2105922511 | O82: TMAH081A5TJ086823 | P82: WARGNIER BERNARD | Q82: KONA | R82: 38504.09 | S82: 541.67 | T82: =+R82+S82 -> 39045.76 | U82: 4 | V82: 3488.14 | W82: 0 | Y82: =+V82-W82+X82 -> 3488.14 | Z82: =(V82+X82)/T82 -> 0.089334668 | AA82: -1333 | AB82: 0 | AE82: 0.1 | AF82: 0.1 | AG82: =+Y82*AE82 -> 348.814 | AI82: =+AG82+AH82 -> 348.814 | AK82: 0 | AL82: 100 | AM82: =IF(AL82>0,100%,0%) -> 1 | AN82: =IF(A82>0,1,"") -> 1 | AQ82: =IF(AN82="","",+AM82/AN82) -> 1 | AR82: =IF(A82="","",VLOOKUP(A82,'Base Sites'!A:B,2,FALSE)) -> Valauto Lomme | AS82: =IF(C82="VW","VOLKSWAGEN",IF(C82="SE","SEAT",IF(C82="NI","NISSAN",IF(C82="HY","HYUNDAI",IF(C82="VU","VUL",IF(C82="sk","SKODA",IF(C82="ltsk","SKODA",IF(C82="CUPRA","CUPRA",IF(C82="AUDI","AUDI",""))))))))) -> HYUNDAI | AU82: =IF(A82="","",VLOOKUP(L82,'Base Vendeurs'!A:B,2,FALSE)) -> Hyundai Lomme | AV82: =+V82+AO82 -> 3488.14 | AW82: =IF(A82="","",+AV82/T82) -> 0.089334668 | AX82: =IF(AV82<0,"OUI","NON") -> NON | AY82: =+MargesVN[[#This Row],[Total COM]]+MargesVN[[#This Row],[EXT GIE]]+MargesVN[[#This Row],[Forfait immat]] -> 448.814
A83: 70 | B83: C | C83: HY | D83: 46174 | E83: 46175 | L83: LEGJA | M83: 5934 | N83: 2105906489 | O83: TMAJB8119TJ455100 | P83: DELPLACE PERRINE | Q83: TUCSON | R83: 41292.14 | S83: 541.67 | T83: =+R83+S83 -> 41833.81 | U83: 133 | V83: 3775.57 | W83: 0 | Y83: =+V83-W83+X83 -> 3775.57 | Z83: =(V83+X83)/T83 -> 0.090251641 | AA83: -3333 | AB83: -1667 | AE83: 0.13 | AF83: 0.13 | AG83: =+Y83*AE83 -> 490.8241 | AI83: =+AG83+AH83 -> 490.8241 | AJ83: Hyundai Finance | AK83: 0 | AL83: 100 | AM83: =IF(AL83>0,100%,0%) -> 1 | AN83: =IF(A83>0,1,"") -> 1 | AQ83: =IF(AN83="","",+AM83/AN83) -> 1 | AR83: =IF(A83="","",VLOOKUP(A83,'Base Sites'!A:B,2,FALSE)) -> Valauto Lomme | AS83: =IF(C83="VW","VOLKSWAGEN",IF(C83="SE","SEAT",IF(C83="NI","NISSAN",IF(C83="HY","HYUNDAI",IF(C83="VU","VUL",IF(C83="sk","SKODA",IF(C83="ltsk","SKODA",IF(C83="CUPRA","CUPRA",IF(C83="AUDI","AUDI",""))))))))) -> HYUNDAI | AU83: =IF(A83="","",VLOOKUP(L83,'Base Vendeurs'!A:B,2,FALSE)) -> Hyundai Lomme | AV83: =+V83+AO83 -> 3775.57 | AW83: =IF(A83="","",+AV83/T83) -> 0.090251641 | AX83: =IF(AV83<0,"OUI","NON") -> NON | AY83: =+MargesVN[[#This Row],[Total COM]]+MargesVN[[#This Row],[EXT GIE]]+MargesVN[[#This Row],[Forfait immat]] -> 590.8241
A84: 70 | B84: C | C84: HY | D84: 46128 | E84: 46128 | K84: 0 | L84: LEGCH | M84: 5935 | N84: 2105847188 | O84: TMAJC8114TJ456457 | P84: BPCE LEASE | Q84: TUCSON | R84: 32958.81 | S84: 541.67 | T84: =+R84+S84 -> 33500.48 | U84: 87 | V84: 2684.74 | W84: 0 | Y84: =+V84-W84+X84 -> 2684.74 | Z84: =(V84+X84)/T84 -> 0.080140344 | AA84: -4063 | AB84: 278.36 | AE84: 0.13 | AF84: 0.13 | AG84: =+Y84*AE84 -> 349.0162 | AI84: =+AG84+AH84 -> 349.0162 | AJ84: Banque | AK84: 0 | AL84: 100 | AM84: =IF(AL84>0,100%,0%) -> 1 | AN84: =IF(A84>0,1,"") -> 1 | AQ84: =IF(AN84="","",+AM84/AN84) -> 1 | AR84: =IF(A84="","",VLOOKUP(A84,'Base Sites'!A:B,2,FALSE)) -> Valauto Lomme | AS84: =IF(C84="VW","VOLKSWAGEN",IF(C84="SE","SEAT",IF(C84="NI","NISSAN",IF(C84="HY","HYUNDAI",IF(C84="VU","VUL",IF(C84="sk","SKODA",IF(C84="ltsk","SKODA",IF(C84="CUPRA","CUPRA",IF(C84="AUDI","AUDI",""))))))))) -> HYUNDAI | AU84: =IF(A84="","",VLOOKUP(L84,'Base Vendeurs'!A:B,2,FALSE)) -> Hyundai Lomme | AV84: =+V84+AO84 -> 2684.74 | AW84: =IF(A84="","",+AV84/T84) -> 0.080140344 | AX84: =IF(AV84<0,"OUI","NON") -> NON | AY84: =+MargesVN[[#This Row],[Total COM]]+MargesVN[[#This Row],[EXT GIE]]+MargesVN[[#This Row],[Forfait immat]] -> 449.0162
A85: 70 | B85: C | C85: HY | D85: 46056 | E85: 46057 | K85: 0 | L85: LEGJA | M85: 5937 | N85: 2105853474 | O85: KMHB15125TW065779 | P85: BULTE ROMAIN | Q85: INSTER | R85: 20379.09 | S85: 0 | T85: =+R85+S85 -> 20379.09 | U85: 11 | V85: 772 | W85: 0 | Y85: =+V85-W85+X85 -> 772 | Z85: =(V85+X85)/T85 -> 0.037881966 | AA85: -833 | AB85: 833 | AE85: 0.07 | AF85: 0.07 | AG85: =+Y85*AE85 -> 54.04 | AI85: =+AG85+AH85 -> 54.04 | AJ85: Hyundai Finance | AK85: 0 | AL85: 100 | AM85: =IF(AL85>0,100%,0%) -> 1 | AN85: =IF(A85>0,1,"") -> 1 | AQ85: =IF(AN85="","",+AM85/AN85) -> 1 | AR85: =IF(A85="","",VLOOKUP(A85,'Base Sites'!A:B,2,FALSE)) -> Valauto Lomme | AS85: =IF(C85="VW","VOLKSWAGEN",IF(C85="SE","SEAT",IF(C85="NI","NISSAN",IF(C85="HY","HYUNDAI",IF(C85="VU","VUL",IF(C85="sk","SKODA",IF(C85="ltsk","SKODA",IF(C85="CUPRA","CUPRA",IF(C85="AUDI","AUDI",""))))))))) -> HYUNDAI | AU85: =IF(A85="","",VLOOKUP(L85,'Base Vendeurs'!A:B,2,FALSE)) -> Hyundai Lomme | AV85: =+V85+AO85 -> 772 | AW85: =IF(A85="","",+AV85/T85) -> 0.037881966 | AX85: =IF(AV85<0,"OUI","NON") -> NON | AY85: =+MargesVN[[#This Row],[Total COM]]+MargesVN[[#This Row],[EXT GIE]]+MargesVN[[#This Row],[Forfait immat]] -> 154.04
A86: 70 | B86: C | C86: HY | D86: 46114 | E86: 46115 | L86: LTMEL | M86: 5938 | N86: 2105934750 | O86: TMAJB8116TJ460366 | P86: ARVAL SERVICE LEASE | Q86: TUCSON | R86: 41292.14 | S86: 541.67 | T86: =+R86+S86 -> 41833.81 | U86: 69 | V86: 410.21 | W86: 0 | Y86: =+V86-W86+X86 -> 410.21 | Z86: =(V86+X86)/T86 -> 0.009805705 | AA86: -4726.31 | AB86: 0 | AF86: 0 | AG86: =+Y86*AE86 -> 0 | AI86: =+AG86+AH86 -> 0 | AK86: 0 | AM86: =IF(AL86>0,100%,0%) -> 0 | AN86: =IF(A86>0,1,"") -> 1 | AQ86: =IF(AN86="","",+AM86/AN86) -> 0 | AR86: =IF(A86="","",VLOOKUP(A86,'Base Sites'!A:B,2,FALSE)) -> Valauto Lomme | AS86: =IF(C86="VW","VOLKSWAGEN",IF(C86="SE","SEAT",IF(C86="NI","NISSAN",IF(C86="HY","HYUNDAI",IF(C86="VU","VUL",IF(C86="sk","SKODA",IF(C86="ltsk","SKODA",IF(C86="CUPRA","CUPRA",IF(C86="AUDI","AUDI",""))))))))) -> HYUNDAI | AU86: =IF(A86="","",VLOOKUP(L86,'Base Vendeurs'!A:B,2,FALSE)) -> Sociétés NORD | AV86: =+V86+AO86 -> 410.21 | AW86: =IF(A86="","",+AV86/T86) -> 0.009805705 | AX86: =IF(AV86<0,"OUI","NON") -> NON | AY86: =+MargesVN[[#This Row],[Total COM]]+MargesVN[[#This Row],[EXT GIE]]+MargesVN[[#This Row],[Forfait immat]] -> 0
A87: 70 | B87: C | C87: HY | D87: 46076 | E87: 46080 | K87: 0 | L87: LELBO | M87: 5939 | N87: 2105935464 | O87: TMAJB8110TJ460766 | P87: SARTI CLEMENT | Q87: TUCSON | R87: 31375.48 | S87: 541.67 | T87: =+R87+S87 -> 31917.15 | U87: 27 | V87: 3100.3 | W87: -0.01 | X87: -2443.76 | Y87: =+V87-W87+X87 -> 656.55 | Z87: =(V87+X87)/T87 -> 0.020570132 | AA87: -3584 | AB87: -1250 | AE87: 0.1 | AF87: 0.1 | AG87: =+Y87*AE87 -> 65.655 | AI87: =+AG87+AH87 -> 65.655 | AJ87: Hyundai Finance | AK87: 0 | AL87: 0 | AM87: =IF(AL87>0,100%,0%) -> 1 | AN87: =IF(A87>0,1,"") -> 1 | AQ87: =IF(AN87="","",+AM87/AN87) -> 1 | AR87: =IF(A87="","",VLOOKUP(A87,'Base Sites'!A:B,2,FALSE)) -> Valauto Lomme | AS87: =IF(C87="VW","VOLKSWAGEN",IF(C87="SE","SEAT",IF(C87="NI","NISSAN",IF(C87="HY","HYUNDAI",IF(C87="VU","VUL",IF(C87="sk","SKODA",IF(C87="ltsk","SKODA",IF(C87="CUPRA","CUPRA",IF(C87="AUDI","AUDI",""))))))))) -> HYUNDAI | AU87: =IF(A87="","",VLOOKUP(L87,'Base Vendeurs'!A:B,2,FALSE)) -> Hyundai Lomme | AV87: =+V87+AO87 -> 3100.3 | AW87: =IF(A87="","",+AV87/T87) -> 0.097135866 | AX87: =IF(AV87<0,"OUI","NON") -> NON | AY87: =+MargesVN[[#This Row],[Total COM]]+MargesVN[[#This Row],[EXT GIE]]+MargesVN[[#This Row],[Forfait immat]] -> 65.655
A88: 70 | B88: C | C88: HY | D88: 46069 | E88: 46070 | K88: 0 | L88: LEGCH | M88: 5940 | N88: 2105938682 | O88: TMAJB8113TJ457344 | P88: AUBRUN JUDICAEL | Q88: TUCSON | R88: 31375.48 | S88: 541.67 | T88: =+R88+S88 -> 31917.15 | U88: 19 | V88: 1532.97 | W88: -0.01 | Y88: =+V88-W88+X88 -> 1532.98 | Z88: =(V88+X88)/T88 -> 0.048029664 | AA88: -3584 | AB88: 0 | AE88: 0.07 | AF88: 0.07 | AG88: =+Y88*AE88 -> 107.3086 | AI88: =+AG88+AH88 -> 107.3086 | AJ88: Hyundai Finance | AK88: 0 | AL88: 100 | AM88: =IF(AL88>0,100%,0%) -> 1 | AN88: =IF(A88>0,1,"") -> 1 | AQ88: =IF(AN88="","",+AM88/AN88) -> 1 | AR88: =IF(A88="","",VLOOKUP(A88,'Base Sites'!A:B,2,FALSE)) -> Valauto Lomme | AS88: =IF(C88="VW","VOLKSWAGEN",IF(C88="SE","SEAT",IF(C88="NI","NISSAN",IF(C88="HY","HYUNDAI",IF(C88="VU","VUL",IF(C88="sk","SKODA",IF(C88="ltsk","SKODA",IF(C88="CUPRA","CUPRA",IF(C88="AUDI","AUDI",""))))))))) -> HYUNDAI | AU88: =IF(A88="","",VLOOKUP(L88,'Base Vendeurs'!A:B,2,FALSE)) -> Hyundai Lomme | AV88: =+V88+AO88 -> 1532.97 | AW88: =IF(A88="","",+AV88/T88) -> 0.048029664 | AX88: =IF(AV88<0,"OUI","NON") -> NON | AY88: =+MargesVN[[#This Row],[Total COM]]+MargesVN[[#This Row],[EXT GIE]]+MargesVN[[#This Row],[Forfait immat]] -> 207.3086
A89: 70 | B89: C | C89: HY | D89: 46153 | E89: 46154 | K89: 0 | L89: LEGCH | M89: 5941 | N89: 2105934022 | O89: TMAJB8111TJ457892 | P89: HOUSSOY MARIE-CHRISTINE | Q89: TUCSON | R89: 31375.48 | S89: 0 | T89: =+R89+S89 -> 31375.48 | U89: 108 | V89: 1478.81 | W89: 0 | Y89: =+V89-W89+X89 -> 1478.81 | Z89: =(V89+X89)/T89 -> 0.047132665 | AA89: -3584 | AB89: 0 | AE89: 0.08 | AF89: 0.07 | AG89: =+Y89*AE89 -> 118.3048 | AI89: =+AG89+AH89 -> 118.3048 | AJ89: Hyundai Finance | AK89: 0 | AL89: 50 | AM89: =IF(AL89>0,100%,0%) -> 1 | AN89: =IF(A89>0,1,"") -> 1 | AQ89: =IF(AN89="","",+AM89/AN89) -> 1 | AR89: =IF(A89="","",VLOOKUP(A89,'Base Sites'!A:B,2,FALSE)) -> Valauto Lomme | AS89: =IF(C89="VW","VOLKSWAGEN",IF(C89="SE","SEAT",IF(C89="NI","NISSAN",IF(C89="HY","HYUNDAI",IF(C89="VU","VUL",IF(C89="sk","SKODA",IF(C89="ltsk","SKODA",IF(C89="CUPRA","CUPRA",IF(C89="AUDI","AUDI",""))))))))) -> HYUNDAI | AU89: =IF(A89="","",VLOOKUP(L89,'Base Vendeurs'!A:B,2,FALSE)) -> Hyundai Lomme | AV89: =+V89+AO89 -> 1478.81 | AW89: =IF(A89="","",+AV89/T89) -> 0.047132665 | AX89: =IF(AV89<0,"OUI","NON") -> NON | AY89: =+MargesVN[[#This Row],[Total COM]]+MargesVN[[#This Row],[EXT GIE]]+MargesVN[[#This Row],[Forfait immat]] -> 168.3048
A90: 70 | B90: C | C90: HY | D90: 46078 | E90: 46081 | K90: 0 | L90: LETLE | M90: 5942 | N90: 2105934618 | O90: TMAH881AXTJ087331 | P90: DEMEY FLORENT | Q90: KONA | R90: 33920.76 | S90: 0 | T90: =+R90+S90 -> 33920.76 | U90: 33 | V90: 1872.94 | W90: 0 | Y90: =+V90-W90+X90 -> 1872.94 | Z90: =(V90+X90)/T90 -> 0.055215154 | AA90: -1333 | AB90: 0 | AE90: 0.07 | AF90: 0.07 | AG90: =+Y90*AE90 -> 131.1058 | AI90: =+AG90+AH90 -> 131.1058 | AJ90: Hyundai Finance | AK90: 0 | AL90: 100 | AM90: =IF(AL90>0,100%,0%) -> 1 | AN90: =IF(A90>0,1,"") -> 1 | AQ90: =IF(AN90="","",+AM90/AN90) -> 1 | AR90: =IF(A90="","",VLOOKUP(A90,'Base Sites'!A:B,2,FALSE)) -> Valauto Lomme | AS90: =IF(C90="VW","VOLKSWAGEN",IF(C90="SE","SEAT",IF(C90="NI","NISSAN",IF(C90="HY","HYUNDAI",IF(C90="VU","VUL",IF(C90="sk","SKODA",IF(C90="ltsk","SKODA",IF(C90="CUPRA","CUPRA",IF(C90="AUDI","AUDI",""))))))))) -> HYUNDAI | AU90: =IF(A90="","",VLOOKUP(L90,'Base Vendeurs'!A:B,2,FALSE)) -> Hyundai Lomme | AV90: =+V90+AO90 -> 1872.94 | AW90: =IF(A90="","",+AV90/T90) -> 0.055215154 | AX90: =IF(AV90<0,"OUI","NON") -> NON | AY90: =+MargesVN[[#This Row],[Total COM]]+MargesVN[[#This Row],[EXT GIE]]+MargesVN[[#This Row],[Forfait immat]] -> 231.1058
A91: 70 | B91: C | C91: HY | D91: 46058 | E91: 46059 | K91: 0 | L91: LEGJA | M91: 5943 | N91: 2105845454 | O91: KMHB15129TW064845 | P91: ZGHRATA ASMAE | Q91: INSTER | R91: 20670.76 | S91: 0 | T91: =+R91+S91 -> 20670.76 | U91: 9 | V91: 772 | W91: 0 | Y91: =+V91-W91+X91 -> 772 | Z91: =(V91+X91)/T91 -> 0.037347442 | AA91: -833 | AB91: 833 | AE91: 0.07 | AF91: 0.07 | AG91: =+Y91*AE91 -> 54.04 | AI91: =+AG91+AH91 -> 54.04 | AJ91: Hyundai Finance | AK91: 0 | AL91: 100 | AM91: =IF(AL91>0,100%,0%) -> 1 | AN91: =IF(A91>0,1,"") -> 1 | AQ91: =IF(AN91="","",+AM91/AN91) -> 1 | AR91: =IF(A91="","",VLOOKUP(A91,'Base Sites'!A:B,2,FALSE)) -> Valauto Lomme | AS91: =IF(C91="VW","VOLKSWAGEN",IF(C91="SE","SEAT",IF(C91="NI","NISSAN",IF(C91="HY","HYUNDAI",IF(C91="VU","VUL",IF(C91="sk","SKODA",IF(C91="ltsk","SKODA",IF(C91="CUPRA","CUPRA",IF(C91="AUDI","AUDI",""))))))))) -> HYUNDAI | AU91: =IF(A91="","",VLOOKUP(L91,'Base Vendeurs'!A:B,2,FALSE)) -> Hyundai Lomme | AV91: =+V91+AO91 -> 772 | AW91: =IF(A91="","",+AV91/T91) -> 0.037347442 | AX91: =IF(AV91<0,"OUI","NON") -> NON | AY91: =+MargesVN[[#This Row],[Total COM]]+MargesVN[[#This Row],[EXT GIE]]+MargesVN[[#This Row],[Forfait immat]] -> 154.04
A92: 70 | B92: C | C92: HY | D92: 46099 | E92: 46101 | L92: LEGCH | M92: 5944 | N92: 2105857785 | O92: KMHB15123TW065523 | P92: MACREZ MORGAN | Q92: INSTER | R92: 20670.76 | S92: 0 | T92: =+R92+S92 -> 20670.76 | U92: 47 | V92: 1747.5 | W92: 0 | Y92: =+V92-W92+X92 -> 1747.5 | Z92: =(V92+X92)/T92 -> 0.084539707 | AA92: -833 | AB92: 0 | AE92: 0.13 | AF92: 0.13 | AG92: =+Y92*AE92 -> 227.175 | AI92: =+AG92+AH92 -> 227.175 | AJ92: Hyundai Finance | AK92: 0 | AL92: 100 | AM92: =IF(AL92>0,100%,0%) -> 1 | AN92: =IF(A92>0,1,"") -> 1 | AQ92: =IF(AN92="","",+AM92/AN92) -> 1 | AR92: =IF(A92="","",VLOOKUP(A92,'Base Sites'!A:B,2,FALSE)) -> Valauto Lomme | AS92: =IF(C92="VW","VOLKSWAGEN",IF(C92="SE","SEAT",IF(C92="NI","NISSAN",IF(C92="HY","HYUNDAI",IF(C92="VU","VUL",IF(C92="sk","SKODA",IF(C92="ltsk","SKODA",IF(C92="CUPRA","CUPRA",IF(C92="AUDI","AUDI",""))))))))) -> HYUNDAI | AU92: =IF(A92="","",VLOOKUP(L92,'Base Vendeurs'!A:B,2,FALSE)) -> Hyundai Lomme | AV92: =+V92+AO92 -> 1747.5 | AW92: =IF(A92="","",+AV92/T92) -> 0.084539707 | AX92: =IF(AV92<0,"OUI","NON") -> NON | AY92: =+MargesVN[[#This Row],[Total COM]]+MargesVN[[#This Row],[EXT GIE]]+MargesVN[[#This Row],[Forfait immat]] -> 327.175
A93: 70 | B93: C | C93: HY | D93: 46078 | E93: 46079 | K93: 0 | L93: LETLE | M93: 5946 | N93: 2105935385 | O93: TMAJA8118TJ463031 | P93: DETAEVERNIER OLIVIER | Q93: TUCSON | R93: 36625.48 | S93: 541.67 | T93: =+R93+S93 -> 37167.15 | U93: 26 | V93: 3408.59 | W93: -0.01 | Y93: =+V93-W93+X93 -> 3408.6 | Z93: =(V93+X93)/T93 -> 0.091709749 | AA93: -1667 | AB93: -2500 | AE93: 0.13 | AF93: 0.13 | AG93: =+Y93*AE93 -> 443.118 | AI93: =+AG93+AH93 -> 443.118 | AJ93: Hyundai Finance | AK93: 0 | AL93: 100 | AM93: =IF(AL93>0,100%,0%) -> 1 | AN93: =IF(A93>0,1,"") -> 1 | AQ93: =IF(AN93="","",+AM93/AN93) -> 1 | AR93: =IF(A93="","",VLOOKUP(A93,'Base Sites'!A:B,2,FALSE)) -> Valauto Lomme | AS93: =IF(C93="VW","VOLKSWAGEN",IF(C93="SE","SEAT",IF(C93="NI","NISSAN",IF(C93="HY","HYUNDAI",IF(C93="VU","VUL",IF(C93="sk","SKODA",IF(C93="ltsk","SKODA",IF(C93="CUPRA","CUPRA",IF(C93="AUDI","AUDI",""))))))))) -> HYUNDAI | AU93: =IF(A93="","",VLOOKUP(L93,'Base Vendeurs'!A:B,2,FALSE)) -> Hyundai Lomme | AV93: =+V93+AO93 -> 3408.59 | AW93: =IF(A93="","",+AV93/T93) -> 0.091709749 | AX93: =IF(AV93<0,"OUI","NON") -> NON | AY93: =+MargesVN[[#This Row],[Total COM]]+MargesVN[[#This Row],[EXT GIE]]+MargesVN[[#This Row],[Forfait immat]] -> 543.118
A94: 70 | B94: C | C94: HY | D94: 46099 | E94: 46101 | L94: LETLE | M94: 5948 | N94: 2105934754 | O94: TMAJC8114TJ458791 | P94: BUTERA SILVANA | Q94: TUCSON | R94: 32958.82 | S94: 541.66 | T94: =+R94+S94 -> 33500.48 | U94: 47 | V94: 2883.9 | W94: -0.01 | Y94: =+V94-W94+X94 -> 2883.91 | Z94: =(V94+X94)/T94 -> 0.086085334 | AA94: -2083 | AB94: -2917 | AE94: 0.13 | AF94: 0.13 | AG94: =+Y94*AE94 -> 374.9083 | AI94: =+AG94+AH94 -> 374.9083 | AJ94: Hyundai Finance | AK94: 0 | AL94: 100 | AM94: =IF(AL94>0,100%,0%) -> 1 | AN94: =IF(A94>0,1,"") -> 1 | AQ94: =IF(AN94="","",+AM94/AN94) -> 1 | AR94: =IF(A94="","",VLOOKUP(A94,'Base Sites'!A:B,2,FALSE)) -> Valauto Lomme | AS94: =IF(C94="VW","VOLKSWAGEN",IF(C94="SE","SEAT",IF(C94="NI","NISSAN",IF(C94="HY","HYUNDAI",IF(C94="VU","VUL",IF(C94="sk","SKODA",IF(C94="ltsk","SKODA",IF(C94="CUPRA","CUPRA",IF(C94="AUDI","AUDI",""))))))))) -> HYUNDAI | AU94: =IF(A94="","",VLOOKUP(L94,'Base Vendeurs'!A:B,2,FALSE)) -> Hyundai Lomme | AV94: =+V94+AO94 -> 2883.9 | AW94: =IF(A94="","",+AV94/T94) -> 0.086085334 | AX94: =IF(AV94<0,"OUI","NON") -> NON | AY94: =+MargesVN[[#This Row],[Total COM]]+MargesVN[[#This Row],[EXT GIE]]+MargesVN[[#This Row],[Forfait immat]] -> 474.9083
A95: 70 | B95: C | C95: HY | D95: 46129 | E95: 46133 | K95: 0 | L95: LEGCH | M95: 5949 | N95: 2105935374 | O95: TMAJE8112TJ459612 | P95: TOURTE MURIEL | Q95: TUCSON | R95: 40458.81 | S95: 541.67 | T95: =+R95+S95 -> 41000.48 | U95: 77 | V95: 2570.44 | W95: 0 | Y95: =+V95-W95+X95 -> 2570.44 | Z95: =(V95+X95)/T95 -> 0.062692925 | AA95: -2916 | AB95: -2917 | AE95: 0.13 | AF95: 0.13 | AG95: =+Y95*AE95 -> 334.1572 | AI95: =+AG95+AH95 -> 334.1572 | AK95: 0 | AL95: 50 | AM95: =IF(AL95>0,100%,0%) -> 1 | AN95: =IF(A95>0,1,"") -> 1 | AQ95: =IF(AN95="","",+AM95/AN95) -> 1 | AR95: =IF(A95="","",VLOOKUP(A95,'Base Sites'!A:B,2,FALSE)) -> Valauto Lomme | AS95: =IF(C95="VW","VOLKSWAGEN",IF(C95="SE","SEAT",IF(C95="NI","NISSAN",IF(C95="HY","HYUNDAI",IF(C95="VU","VUL",IF(C95="sk","SKODA",IF(C95="ltsk","SKODA",IF(C95="CUPRA","CUPRA",IF(C95="AUDI","AUDI",""))))))))) -> HYUNDAI | AU95: =IF(A95="","",VLOOKUP(L95,'Base Vendeurs'!A:B,2,FALSE)) -> Hyundai Lomme | AV95: =+V95+AO95 -> 2570.44 | AW95: =IF(A95="","",+AV95/T95) -> 0.062692925 | AX95: =IF(AV95<0,"OUI","NON") -> NON | AY95: =+MargesVN[[#This Row],[Total COM]]+MargesVN[[#This Row],[EXT GIE]]+MargesVN[[#This Row],[Forfait immat]] -> 384.1572
A96: 70 | B96: C | C96: HY | D96: 46070 | E96: 46071 | K96: 0 | L96: LETLE | M96: 5951 | N96: 2105846839 | O96: KMHB15129TW064750 | P96: OUHADDA MOHAMED | Q96: INSTER | R96: 20379.09 | S96: 0 | T96: =+R96+S96 -> 20379.09 | U96: 13 | V96: 772 | W96: 0 | Y96: =+V96-W96+X96 -> 772 | Z96: =(V96+X96)/T96 -> 0.037881966 | AA96: -833 | AB96: 833 | AE96: 0.07 | AF96: 0.07 | AG96: =+Y96*AE96 -> 54.04 | AI96: =+AG96+AH96 -> 54.04 | AJ96: Hyundai Finance | AK96: 0 | AL96: 100 | AM96: =IF(AL96>0,100%,0%) -> 1 | AN96: =IF(A96>0,1,"") -> 1 | AQ96: =IF(AN96="","",+AM96/AN96) -> 1 | AR96: =IF(A96="","",VLOOKUP(A96,'Base Sites'!A:B,2,FALSE)) -> Valauto Lomme | AS96: =IF(C96="VW","VOLKSWAGEN",IF(C96="SE","SEAT",IF(C96="NI","NISSAN",IF(C96="HY","HYUNDAI",IF(C96="VU","VUL",IF(C96="sk","SKODA",IF(C96="ltsk","SKODA",IF(C96="CUPRA","CUPRA",IF(C96="AUDI","AUDI",""))))))))) -> HYUNDAI | AU96: =IF(A96="","",VLOOKUP(L96,'Base Vendeurs'!A:B,2,FALSE)) -> Hyundai Lomme | AV96: =+V96+AO96 -> 772 | AW96: =IF(A96="","",+AV96/T96) -> 0.037881966 | AX96: =IF(AV96<0,"OUI","NON") -> NON | AY96: =+MargesVN[[#This Row],[Total COM]]+MargesVN[[#This Row],[EXT GIE]]+MargesVN[[#This Row],[Forfait immat]] -> 154.04
A97: 70 | B97: C | C97: HY | D97: 46063 | E97: 46066 | K97: 0 | L97: LEGJA | M97: 5952 | N97: 2105923358 | O97: KMHHB8119TU202881 | P97: KOUAME EMMANUEL | Q97: KONA | R97: 28837.43 | S97: 458.33 | T97: =+R97+S97 -> 29295.76 | U97: 6 | V97: 1459.91 | W97: -0.01 | Y97: =+V97-W97+X97 -> 1459.92 | Z97: =(V97+X97)/T97 -> 0.049833491 | AA97: -1500 | AB97: 0 | AE97: 0.07 | AF97: 0.1 | AG97: =+Y97*AE97 -> 102.1944 | AI97: =+AG97+AH97 -> 102.1944 | AJ97: Hyundai Finance | AK97: 0 | AL97: 50 | AM97: =IF(AL97>0,100%,0%) -> 1 | AN97: =IF(A97>0,1,"") -> 1 | AQ97: =IF(AN97="","",+AM97/AN97) -> 1 | AR97: =IF(A97="","",VLOOKUP(A97,'Base Sites'!A:B,2,FALSE)) -> Valauto Lomme | AS97: =IF(C97="VW","VOLKSWAGEN",IF(C97="SE","SEAT",IF(C97="NI","NISSAN",IF(C97="HY","HYUNDAI",IF(C97="VU","VUL",IF(C97="sk","SKODA",IF(C97="ltsk","SKODA",IF(C97="CUPRA","CUPRA",IF(C97="AUDI","AUDI",""))))))))) -> HYUNDAI | AU97: =IF(A97="","",VLOOKUP(L97,'Base Vendeurs'!A:B,2,FALSE)) -> Hyundai Lomme | AV97: =+V97+AO97 -> 1459.91 | AW97: =IF(A97="","",+AV97/T97) -> 0.049833491 | AX97: =IF(AV97<0,"OUI","NON") -> NON | AY97: =+MargesVN[[#This Row],[Total COM]]+MargesVN[[#This Row],[EXT GIE]]+MargesVN[[#This Row],[Forfait immat]] -> 152.1944
A98: 70 | B98: C | C98: HY | D98: 46100 | E98: 46104 | I98: x | J98: x | K98: 41990.47 | L98: LEGCH | M98: 5953 | N98: 2105938240 | O98: TMAJC8116TJ456802 | P98: ARVAL SERVICE LEASE | Q98: TUCSON | R98: 32958.81 | S98: 541.67 | T98: =+R98+S98 -> 33500.48 | U98: 38 | V98: 663.55 | W98: 0 | Y98: =+V98-W98+X98 -> 663.55 | Z98: =(V98+X98)/T98 -> 0.019807179 | AA98: -4487.98 | AB98: 0 | AD98: ok vn payé | AE98: 0.07 | AF98: 0.07 | AG98: =+Y98*AE98 -> 46.4485 | AI98: =+AG98+AH98 -> 46.4485 | AJ98: Hyundai Leasing | AK98: 0 | AM98: =IF(AL98>0,100%,0%) -> 0 | AN98: =IF(A98>0,1,"") -> 1 | AQ98: =IF(AN98="","",+AM98/AN98) -> 0 | AR98: =IF(A98="","",VLOOKUP(A98,'Base Sites'!A:B,2,FALSE)) -> Valauto Lomme | AS98: =IF(C98="VW","VOLKSWAGEN",IF(C98="SE","SEAT",IF(C98="NI","NISSAN",IF(C98="HY","HYUNDAI",IF(C98="VU","VUL",IF(C98="sk","SKODA",IF(C98="ltsk","SKODA",IF(C98="CUPRA","CUPRA",IF(C98="AUDI","AUDI",""))))))))) -> HYUNDAI | AU98: =IF(A98="","",VLOOKUP(L98,'Base Vendeurs'!A:B,2,FALSE)) -> Hyundai Lomme | AV98: =+V98+AO98 -> 663.55 | AW98: =IF(A98="","",+AV98/T98) -> 0.019807179 | AX98: =IF(AV98<0,"OUI","NON") -> NON | AY98: =+MargesVN[[#This Row],[Total COM]]+MargesVN[[#This Row],[EXT GIE]]+MargesVN[[#This Row],[Forfait immat]] -> 46.4485
A99: 70 | B99: C | C99: HY | D99: 46098 | E99: 46099 | L99: LELBO | M99: 5954 | N99: 2105951992 | O99: TMAH881B1TJ083127 | P99: MAHIEU DOMINIQUE | Q99: KONA | R99: 30254.09 | S99: 0 | T99: =+R99+S99 -> 30254.09 | U99: 36 | V99: 2254.4 | W99: 0 | X99: -3277.76 | Y99: =+V99-W99+X99 -> -1023.36 | Z99: =(V99+X99)/T99 -> -0.033825509 | AA99: -1333 | AB99: 0 | AD99: marge négative | AF99: 0.07 | AG99: =+Y99*AE99 -> 0 | AI99: =+AG99+AH99 -> 0 | AJ99: Hyundai Finance | AK99: 0 | AL99: 50 | AM99: =IF(AL99>0,100%,0%) -> 1 | AN99: =IF(A99>0,1,"") -> 1 | AQ99: =IF(AN99="","",+AM99/AN99) -> 1 | AR99: =IF(A99="","",VLOOKUP(A99,'Base Sites'!A:B,2,FALSE)) -> Valauto Lomme | AS99: =IF(C99="VW","VOLKSWAGEN",IF(C99="SE","SEAT",IF(C99="NI","NISSAN",IF(C99="HY","HYUNDAI",IF(C99="VU","VUL",IF(C99="sk","SKODA",IF(C99="ltsk","SKODA",IF(C99="CUPRA","CUPRA",IF(C99="AUDI","AUDI",""))))))))) -> HYUNDAI | AU99: =IF(A99="","",VLOOKUP(L99,'Base Vendeurs'!A:B,2,FALSE)) -> Hyundai Lomme | AV99: =+V99+AO99 -> 2254.4 | AW99: =IF(A99="","",+AV99/T99) -> 0.074515545 | AX99: =IF(AV99<0,"OUI","NON") -> NON | AY99: =+MargesVN[[#This Row],[Total COM]]+MargesVN[[#This Row],[EXT GIE]]+MargesVN[[#This Row],[Forfait immat]] -> 50
A100: 70 | B100: C | C100: HY | D100: 46070 | E100: 46071 | K100: 0 | L100: LEGCH | M100: 5955 | N100: 2105804388 | O100: KMHB35111TW066994 | P100: DELOBEAU FRANCIS | Q100: INSTER | R100: 26462.43 | S100: 1908.34 | T100: =+R100+S100 -> 28370.77 | U100: 7 | V100: 2025.32 | W100: -0.01 | Y100: =+V100-W100+X100 -> 2025.33 | Z100: =(V100+X100)/T100 -> 0.071387558 | AA100: -833 | AB100: 0 | AE100: 0.07 | AF100: 0.07 | AG100: =+Y100*AE100 -> 141.7731 | AI100: =+AG100+AH100 -> 141.7731 | AK100: 0 | AL100: 100 | AM100: =IF(AL100>0,100%,0%) -> 1 | AN100: =IF(A100>0,1,"") -> 1 | AQ100: =IF(AN100="","",+AM100/AN100) -> 1 | AR100: =IF(A100="","",VLOOKUP(A100,'Base Sites'!A:B,2,FALSE)) -> Valauto Lomme | AS100: =IF(C100="VW","VOLKSWAGEN",IF(C100="SE","SEAT",IF(C100="NI","NISSAN",IF(C100="HY","HYUNDAI",IF(C100="VU","VUL",IF(C100="sk","SKODA",IF(C100="ltsk","SKODA",IF(C100="CUPRA","CUPRA",IF(C100="AUDI","AUDI",""))))))))) -> HYUNDAI | AU100: =IF(A100="","",VLOOKUP(L100,'Base Vendeurs'!A:B,2,FALSE)) -> Hyundai Lomme | AV100: =+V100+AO100 -> 2025.32 | AW100: =IF(A100="","",+AV100/T100) -> 0.071387558 | AX100: =IF(AV100<0,"OUI","NON") -> NON | AY100: =+MargesVN[[#This Row],[Total COM]]+MargesVN[[#This Row],[EXT GIE]]+MargesVN[[#This Row],[Forfait immat]] -> 241.7731
...

Sheet VérifCARBASE
A1: Date de Facturation | B1: (Tous)
A3: Nombre de N° VN | B3: Étiquettes de colonnes | M3: Ecart | N3: MAJ FB 28/07 au 30/06/2026
A4: Étiquettes de lignes | B4: HY | C4: SE | D4: SK | E4: VU | F4: VW | G4: CUPRA | H4: AUDI | I4: Total général
A5: 10 | C5: 32 | D5: 135 | F5: 325 | G5: 61 | I5: 553 | L5: =627-5-69 -> 553 | M5: =I5-L5 -> 0 | N5: OK
A6: 20 | E6: 90 | I6: 90 | L6: =92-4 -> 88 | M6: =I6-L6 -> 2 | N6: VN514231 et 519509 (valauto Rent) classés en groupe en compta
A7: 30 | D7: 427 | F7: 363 | I7: 790 | L7: =825-38 -> 787 | M7: =I7-L7 -> 3 | N7: VN548334, 524807 et 519691 (valauto Rent) classés en groupe en compta
A8: 60 | F8: 188 | I8: 188 | L8: =232-1-43 -> 188 | M8: =I8-L8 -> 0 | N8: OK
A9: 70 | B9: 150 | I9: 150 | L9: 150 | M9: =I9-L9 -> 0 | N9: OK
A10: 15 | E10: 40 | F10: 238 | H10: 98 | I10: 376 | L10: =426-2-50 -> 374 | M10: =I10-L10 -> 2 | N10: VN20062 et 519546 (valauto Rent) classés en groupe en compta
A11: 25 | F11: 45 | I11: 45 | L11: =64-1-20 -> 43 | M11: =I11-L11 -> 2 | N11: VN519536 et 519545 (valauto Rent) classés en groupe en compta
A12: 35 | C12: 17 | D12: 47 | F12: 81 | G12: 5 | I12: 150 | L12: =187-40 -> 147 | M12: =I12-L12 -> 3 | N12: VN517836, 537924 et 519515 (valauto Rent) classés en groupe en compta
A13: 45 | C13: 2 | D13: 17 | E13: 9 | F13: 150 | G13: 15 | I13: 193 | L13: =225-32 -> 193 | M13: =I13-L13 -> 0 | N13: OK
A14: Total général | B14: 150 | C14: 51 | D14: 626 | E14: 139 | F14: 1390 | G14: 81 | H14: 98 | I14: 2535

Sheet CLE REPARTITION CELL ENT
A1: Tableau - Clef de répartition pour facturation MAD Cellule Entreprise
B11: Étiquettes de colonnes
B12: AUDI | D12: CUPRA | F12: HY | H12: SE | J12: SK | L12: VU | N12: VW | P12: Total Nbre VN | Q12: Total Somme de Marge nette recalculée
A13: Étiquettes de lignes | B13: Nbre VN | C13: Somme de Marge nette recalculée | D13: Nbre VN | E13: Somme de Marge nette recalculée | F13: Nbre VN | G13: Somme de Marge nette recalculée | H13: Nbre VN | I13: Somme de Marge nette recalculée | J13: Nbre VN | K13: Somme de Marge nette recalculée | L13: Nbre VN | M13: Somme de Marge nette recalculée | N13: Nbre VN | O13: Somme de Marge nette recalculée
A14: 10 | D14: 22 | E14: 23053.65 | H14: 15 | I14: 9114.93 | J14: 22 | K14: 22981.49 | N14: 2 | O14: 2402.85 | P14: 61 | Q14: 57552.92
A15: 15 | B15: 31 | C15: 53342.2 | L15: 7 | M15: 12224.16 | N15: 117 | O15: 112271.07 | P15: 155 | Q15: 177837.43
A16: 20 | L16: 36 | M16: 33172.24 | P16: 36 | Q16: 33172.24
A17: 25 | N17: 5 | O17: 4417.88 | P17: 5 | Q17: 4417.88
A18: 30 | J18: 271 | K18: 210056.36 | N18: 189 | O18: 197182.52 | P18: 460 | Q18: 407238.88
A19: 35 | D19: 1 | E19: 1246.83 | H19: 3 | I19: 1870.62 | J19: 16 | K19: 14431.65 | N19: 9 | O19: 5948.09 | P19: 29 | Q19: 23497.19
A20: 45 | D20: 1 | E20: 932.2 | J20: 3 | K20: 3511.21 | L20: 5 | M20: 3629.39 | N20: 13 | O20: 12756.91 | P20: 22 | Q20: 20829.71
A21: 60 | N21: 61 | O21: 31053.12 | P21: 61 | Q21: 31053.12
A22: 70 | F22: 15 | G22: 7605.84 | P22: 15 | Q22: 7605.84
A23: Total général | B23: 31 | C23: 53342.2 | D23: 24 | E23: 25232.68 | F23: 15 | G23: 7605.84 | H23: 18 | I23: 10985.55 | J23: 312 | K23: 250980.71 | L23: 48 | M23: 49025.79 | N23: 396 | O23: 366032.44 | P23: 844 | Q23: 763205.21

Sheet Détails1
A1: Détails pou for Somme de Marge nette recalculée - Marque: VU, CLIENT: WULLENS YOANN, Modèle livré: ID BUZZ, Date de Livraison: 1/3/2022, Marque4 : (+)
A3: Site | B3: Etat | C3: Marque | D3: Date de Facturation | E3: Date de Livraison | F3: Manque Marge | G3: PB Marge | H3: Justif ? | I3: Solde Client | J3: Validé DF | K3: Solde client2 | L3: Vendeur | M3: N° VN | N3: N° CDE | O3: Châssis | P3: CLIENT | Q3: Modèle livré | R3: Prix de Vte | S3: Options | T3: Total | U3: Jours de Stock | V3: Marge nette | W3: Marge s/transport | X3: déduction diverse | Y3: Marge restante | Z3: % PV | AA3: OP Clos | AB3: OP Ouverts | AC3: OP non visible | AD3: libellé OP non visible | AE3: TX COM | AF3: TX COM Opticar | AG3: Commission de Base | AH3: Prime opération | AI3: Total COM | AJ3: Sté de Financement | AK3: EXT GIE | AL3: Forfait immat | AM3: nbre de forfait | AN3: nbre de livraison | AO3: OP "+ / -" | AP3: date | AQ3: % forfait | AR3: AU | AS3: Marque4 | AT3: non utilisé | AU3: Equipe | AV3: Marge nette recalculée | AW3: % PV5 | AX3: Marge négative | AY3: TOTAL COM VENDEUR
A4: 30 | B4: C | C4: VU | D4: 45847 | E4: 45849 | K4: 0 | L4: VRGWI | M4: 32702 | N4: 9500 | O4: WV2ZZZEB4PH005520 | P4: WULLENS YOANN | Q4: ID BUZZ | R4: 48861.47 | S4: 0 | T4: 48861.47 | U4: 145 | V4: 1406.8 | Y4: 1406.8 | Z4: 0.028791602 | AA4: 0 | AB4: 0 | AD4: 0 comm demandé // Forfait // PDV hors CG 41104€ au lieu de 41119€ | AF4: 0.12 | AG4: 0 | AH4: 200 | AI4: 200 | AL4: 20 | AM4: 1 | AN4: 1 | AO4: -21792 | AP4: 45869 | AQ4: 1 | AR4: Valauto Lambersart VW | AU4: Valauto PRO NORD | AV4: -20385.2 | AW4: -0.41720399 | AX4: NON | AY4: 220

Sheet CALCUL RETRO COM
A1: RETROCESSION COMMISSIONS VN du 30/06/2026
AP2: =IF(AM2="","",+AL2/AM2) | AQ2: =IF(A2="","",VLOOKUP(A2,'Base Sites'!A:B,2,FALSE)) | AT2: =IF(A2="","",VLOOKUP(L2,'Base Vendeurs'!A:B,2,FALSE)) | AV2: =IF(A2="","",+AU2/S2)
AP3: =IF(AM3="","",+AL3/AM3) | AQ3: =IF(A3="","",VLOOKUP(A3,'Base Sites'!A:B,2,FALSE)) | AT3: =IF(A3="","",VLOOKUP(L3,'Base Vendeurs'!A:B,2,FALSE)) | AV3: =IF(A3="","",+AU3/S3)
A4: Date de Livraison | B4: (Tous) | AP4: =IF(AM4="","",+AL4/AM4) | AQ4: =IF(A4="","",VLOOKUP(A4,'Base Sites'!A:B,2,FALSE)) -> #N/A | AT4: =IF(A4="","",VLOOKUP(L4,'Base Vendeurs'!A:B,2,FALSE)) -> #N/A | AV4: =IF(A4="","",+AU4/S4) -> #DIV/0!
A5: Marque4 | B5: (Tous) | AP5: =IF(AM5="","",+AL5/AM5) | AQ5: =IF(A5="","",VLOOKUP(A5,'Base Sites'!A:B,2,FALSE)) -> #N/A | AT5: =IF(A5="","",VLOOKUP(L5,'Base Vendeurs'!A:B,2,FALSE)) -> #N/A | AV5: =IF(A5="","",+AU5/S5) -> #DIV/0!
AP6: =IF(AM6="","",+AL6/AM6) | AQ6: =IF(A6="","",VLOOKUP(A6,'Base Sites'!A:B,2,FALSE)) | AT6: =IF(A6="","",VLOOKUP(L6,'Base Vendeurs'!A:B,2,FALSE)) | AV6: =IF(A6="","",+AU6/S6)
A7: Site | B7: Marque | C7: Vendeur | D7: N° CDE | E7: Modèle livré | F7: CLIENT | G7: Somme de Marge nette recalculée | AP7: =IF(AM7="","",+AL7/AM7) | AQ7: =IF(A7="","",VLOOKUP(A7,'Base Sites'!A:B,2,FALSE)) -> #N/A | AT7: =IF(A7="","",VLOOKUP(L7,'Base Vendeurs'!A:B,2,FALSE)) -> #N/A | AV7: =IF(A7="","",+AU7/S7) -> #DIV/0!
A8: 10 | B8: SE | C8: LTMEL | D8: 2089 | E8: LEON | F8: LYS AUTO 59 | G8: 759.8 | AP8: =IF(AM8="","",+AL8/AM8) | AQ8: =IF(A8="","",VLOOKUP(A8,'Base Sites'!A:B,2,FALSE)) -> Valauto Roncq | AT8: =IF(A8="","",VLOOKUP(L8,'Base Vendeurs'!A:B,2,FALSE)) -> #N/A | AV8: =IF(A8="","",+AU8/S8) -> #DIV/0!
D9: 2090 | E9: LEON | F9: LYS AUTO 59 | G9: 759.8 | AP9: =IF(AM9="","",+AL9/AM9) | AQ9: =IF(A9="","",VLOOKUP(A9,'Base Sites'!A:B,2,FALSE)) | AT9: =IF(A9="","",VLOOKUP(L9,'Base Vendeurs'!A:B,2,FALSE)) | AV9: =IF(A9="","",+AU9/S9)
D10: 2091 | E10: LEON | F10: LYS AUTO 59 | G10: 759.8 | AP10: =IF(AM10="","",+AL10/AM10) | AQ10: =IF(A10="","",VLOOKUP(A10,'Base Sites'!A:B,2,FALSE)) | AT10: =IF(A10="","",VLOOKUP(L10,'Base Vendeurs'!A:B,2,FALSE)) | AV10: =IF(A10="","",+AU10/S10)
D11: 2105 | E11: LEON | F11: LYS AUTO 59 | G11: 759.8 | AP11: =IF(AM11="","",+AL11/AM11) | AQ11: =IF(A11="","",VLOOKUP(A11,'Base Sites'!A:B,2,FALSE)) | AT11: =IF(A11="","",VLOOKUP(L11,'Base Vendeurs'!A:B,2,FALSE)) | AV11: =IF(A11="","",+AU11/S11)
C12: Total LTMEL | G12: 3039.2 | AP12: =IF(AM12="","",+AL12/AM12) | AQ12: =IF(A12="","",VLOOKUP(A12,'Base Sites'!A:B,2,FALSE)) | AT12: =IF(A12="","",VLOOKUP(L12,'Base Vendeurs'!A:B,2,FALSE)) | AV12: =IF(A12="","",+AU12/S12)
C13: VSGNI | D13: 1306 | E13: ATECA | F13: CHRYSALIDES-PHYGITAL | G13: 1187.87 | AP13: =IF(AM13="","",+AL13/AM13) | AQ13: =IF(A13="","",VLOOKUP(A13,'Base Sites'!A:B,2,FALSE)) | AT13: =IF(A13="","",VLOOKUP(L13,'Base Vendeurs'!A:B,2,FALSE)) | AV13: =IF(A13="","",+AU13/S13)
D14: 1384 | E14: ATECA | F14: HOUZIAUX AMANDINE | G14: 638.69 | AP14: =IF(AM14="","",+AL14/AM14) | AQ14: =IF(A14="","",VLOOKUP(A14,'Base Sites'!A:B,2,FALSE)) | AT14: =IF(A14="","",VLOOKUP(L14,'Base Vendeurs'!A:B,2,FALSE)) | AV14: =IF(A14="","",+AU14/S14)
D15: 1582 | E15: IBIZA | F15: DELANOY MARIE | G15: 587.78 | AP15: =IF(AM15="","",+AL15/AM15) | AQ15: =IF(A15="","",VLOOKUP(A15,'Base Sites'!A:B,2,FALSE)) | AT15: =IF(A15="","",VLOOKUP(L15,'Base Vendeurs'!A:B,2,FALSE)) | AV15: =IF(A15="","",+AU15/S15)
D16: 1854 | E16: ARONA | F16: MAETIE JONATHAN | G16: 1043.65 | AP16: =IF(AM16="","",+AL16/AM16) | AQ16: =IF(A16="","",VLOOKUP(A16,'Base Sites'!A:B,2,FALSE)) | AT16: =IF(A16="","",VLOOKUP(L16,'Base Vendeurs'!A:B,2,FALSE)) | AV16: =IF(A16="","",+AU16/S16)
D17: 1863 | E17: IBIZA | F17: OURIACHI SAMIR | G17: 418.59 | AP17: =IF(AM17="","",+AL17/AM17) | AQ17: =IF(A17="","",VLOOKUP(A17,'Base Sites'!A:B,2,FALSE)) | AT17: =IF(A17="","",VLOOKUP(L17,'Base Vendeurs'!A:B,2,FALSE)) | AV17: =IF(A17="","",+AU17/S17)
D18: 1931 | E18: IBIZA | F18: TOUZANI ADIL | G18: 718.97 | AP18: =IF(AM18="","",+AL18/AM18) | AQ18: =IF(A18="","",VLOOKUP(A18,'Base Sites'!A:B,2,FALSE)) | AT18: =IF(A18="","",VLOOKUP(L18,'Base Vendeurs'!A:B,2,FALSE)) | AV18: =IF(A18="","",+AU18/S18)
D19: 1933 | E19: IBIZA | F19: YAHIAOUI FATAH | G19: 771.1 | AP19: =IF(AM19="","",+AL19/AM19) | AQ19: =IF(A19="","",VLOOKUP(A19,'Base Sites'!A:B,2,FALSE)) | AT19: =IF(A19="","",VLOOKUP(L19,'Base Vendeurs'!A:B,2,FALSE)) | AV19: =IF(A19="","",+AU19/S19)
C20: Total VSGNI | G20: 5366.65 | AP20: =IF(AM20="","",+AL20/AM20) | AQ20: =IF(A20="","",VLOOKUP(A20,'Base Sites'!A:B,2,FALSE)) | AT20: =IF(A20="","",VLOOKUP(L20,'Base Vendeurs'!A:B,2,FALSE)) | AV20: =IF(A20="","",+AU20/S20)
C21: RQNBA | D21: 1490 | E21: IBIZA | F21: KHELKHAL MABJID | G21: 392.04 | AP21: =IF(AM21="","",+AL21/AM21) | AQ21: =IF(A21="","",VLOOKUP(A21,'Base Sites'!A:B,2,FALSE)) | AT21: =IF(A21="","",VLOOKUP(L21,'Base Vendeurs'!A:B,2,FALSE)) | AV21: =IF(A21="","",+AU21/S21)
D22: 1771 | E22: IBIZA | F22: FEUILLOY FREDERIC | G22: 561.25 | AP22: =IF(AM22="","",+AL22/AM22) | AQ22: =IF(A22="","",VLOOKUP(A22,'Base Sites'!A:B,2,FALSE)) | AT22: =IF(A22="","",VLOOKUP(L22,'Base Vendeurs'!A:B,2,FALSE)) | AV22: =IF(A22="","",+AU22/S22)
D23: 1773 | E23: IBIZA | F23: VIRASONE ALLISSON | G23: 718.21 | AP23: =IF(AM23="","",+AL23/AM23) | AQ23: =IF(A23="","",VLOOKUP(A23,'Base Sites'!A:B,2,FALSE)) | AT23: =IF(A23="","",VLOOKUP(L23,'Base Vendeurs'!A:B,2,FALSE)) | AV23: =IF(A23="","",+AU23/S23)
D24: 1788 | E24: IBIZA | F24: DELESCLUSE CATHY | G24: 373.59 | AP24: =IF(AM24="","",+AL24/AM24) | AQ24: =IF(A24="","",VLOOKUP(A24,'Base Sites'!A:B,2,FALSE)) | AT24: =IF(A24="","",VLOOKUP(L24,'Base Vendeurs'!A:B,2,FALSE)) | AV24: =IF(A24="","",+AU24/S24)
D25: 1793 | E25: ARONA | F25: COINCE AURELIE | G25: 1066.73 | AP25: =IF(AM25="","",+AL25/AM25) | AQ25: =IF(A25="","",VLOOKUP(A25,'Base Sites'!A:B,2,FALSE)) | AT25: =IF(A25="","",VLOOKUP(L25,'Base Vendeurs'!A:B,2,FALSE)) | AV25: =IF(A25="","",+AU25/S25)
D26: 1807 | E26: IBIZA | F26: LOUIS AXELLE | G26: 430.5 | AP26: =IF(AM26="","",+AL26/AM26) | AQ26: =IF(A26="","",VLOOKUP(A26,'Base Sites'!A:B,2,FALSE)) | AT26: =IF(A26="","",VLOOKUP(L26,'Base Vendeurs'!A:B,2,FALSE)) | AV26: =IF(A26="","",+AU26/S26)
D27: 1811 | E27: IBIZA | F27: CABANELLAS MICHEL | G27: 859.26 | AP27: =IF(AM27="","",+AL27/AM27) | AQ27: =IF(A27="","",VLOOKUP(A27,'Base Sites'!A:B,2,FALSE)) | AT27: =IF(A27="","",VLOOKUP(L27,'Base Vendeurs'!A:B,2,FALSE)) | AV27: =IF(A27="","",+AU27/S27)
D28: 1812 | E28: ARONA | F28: GOLAZ SERGE | G28: 943.15 | AP28: =IF(AM28="","",+AL28/AM28) | AQ28: =IF(A28="","",VLOOKUP(A28,'Base Sites'!A:B,2,FALSE)) | AT28: =IF(A28="","",VLOOKUP(L28,'Base Vendeurs'!A:B,2,FALSE)) | AV28: =IF(A28="","",+AU28/S28)
D29: 1852 | E29: IBIZA | F29: GUILBERT VIRGINIE | G29: 350.2 | AP29: =IF(AM29="","",+AL29/AM29) | AQ29: =IF(A29="","",VLOOKUP(A29,'Base Sites'!A:B,2,FALSE)) | AT29: =IF(A29="","",VLOOKUP(L29,'Base Vendeurs'!A:B,2,FALSE)) | AV29: =IF(A29="","",+AU29/S29)
D30: 1887 | E30: ARONA | F30: DEBONNET COLETTE | G30: 907.64 | AP30: =IF(AM30="","",+AL30/AM30) | AQ30: =IF(A30="","",VLOOKUP(A30,'Base Sites'!A:B,2,FALSE)) | AT30: =IF(A30="","",VLOOKUP(L30,'Base Vendeurs'!A:B,2,FALSE)) | AV30: =IF(A30="","",+AU30/S30)
D31: 2154 | E31: IBIZA | F31: DUHAMEL JEROME | G31: 924.01 | AP31: =IF(AM31="","",+AL31/AM31) | AQ31: =IF(A31="","",VLOOKUP(A31,'Base Sites'!A:B,2,FALSE)) | AT31: =IF(A31="","",VLOOKUP(L31,'Base Vendeurs'!A:B,2,FALSE)) | AV31: =IF(A31="","",+AU31/S31)
C32: Total RQNBA | G32: 7526.58 | AP32: =IF(AM32="","",+AL32/AM32) | AQ32: =IF(A32="","",VLOOKUP(A32,'Base Sites'!A:B,2,FALSE)) | AT32: =IF(A32="","",VLOOKUP(L32,'Base Vendeurs'!A:B,2,FALSE)) | AV32: =IF(A32="","",+AU32/S32)
C33: RQTHC | D33: 1851 | E33: IBIZA | F33: DUBOQUET ANTONIN | G33: 1050.84 | AP33: =IF(AM33="","",+AL33/AM33) | AQ33: =IF(A33="","",VLOOKUP(A33,'Base Sites'!A:B,2,FALSE)) | AT33: =IF(A33="","",VLOOKUP(L33,'Base Vendeurs'!A:B,2,FALSE)) | AV33: =IF(A33="","",+AU33/S33)
D34: 1855 | E34: IBIZA | F34: CARREZ FLORIAN | G34: 499.8 | AP34: =IF(AM34="","",+AL34/AM34) | AQ34: =IF(A34="","",VLOOKUP(A34,'Base Sites'!A:B,2,FALSE)) | AT34: =IF(A34="","",VLOOKUP(L34,'Base Vendeurs'!A:B,2,FALSE)) | AV34: =IF(A34="","",+AU34/S34)
D35: 1879 | E35: IBIZA | F35: TAHON FABIEN | G35: 505.71 | AP35: =IF(AM35="","",+AL35/AM35) | AQ35: =IF(A35="","",VLOOKUP(A35,'Base Sites'!A:B,2,FALSE)) | AT35: =IF(A35="","",VLOOKUP(L35,'Base Vendeurs'!A:B,2,FALSE)) | AV35: =IF(A35="","",+AU35/S35)
C36: Total RQTHC | G36: 2056.35 | AP36: =IF(AM36="","",+AL36/AM36) | AQ36: =IF(A36="","",VLOOKUP(A36,'Base Sites'!A:B,2,FALSE)) | AT36: =IF(A36="","",VLOOKUP(L36,'Base Vendeurs'!A:B,2,FALSE)) | AV36: =IF(A36="","",+AU36/S36)
C37: VSJTI | D37: 1794 | E37: IBIZA | F37: SCIEGAJ YOHAN | G37: 587.78 | AP37: =IF(AM37="","",+AL37/AM37) | AQ37: =IF(A37="","",VLOOKUP(A37,'Base Sites'!A:B,2,FALSE)) | AT37: =IF(A37="","",VLOOKUP(L37,'Base Vendeurs'!A:B,2,FALSE)) | AV37: =IF(A37="","",+AU37/S37)
D38: 1795 | E38: IBIZA | F38: SCIEGAJ YOHAN | G38: 587.78 | AP38: =IF(AM38="","",+AL38/AM38) | AQ38: =IF(A38="","",VLOOKUP(A38,'Base Sites'!A:B,2,FALSE)) | AT38: =IF(A38="","",VLOOKUP(L38,'Base Vendeurs'!A:B,2,FALSE)) | AV38: =IF(A38="","",+AU38/S38)
C39: Total VSJTI | G39: 1175.56 | AP39: =IF(AM39="","",+AL39/AM39) | AQ39: =IF(A39="","",VLOOKUP(A39,'Base Sites'!A:B,2,FALSE)) | AT39: =IF(A39="","",VLOOKUP(L39,'Base Vendeurs'!A:B,2,FALSE)) | AV39: =IF(A39="","",+AU39/S39)
C40: RQLMO | D40: 1934 | E40: IBIZA | F40: DESROUSSEAUX ROMAIN | G40: 628.72 | AP40: =IF(AM40="","",+AL40/AM40) | AQ40: =IF(A40="","",VLOOKUP(A40,'Base Sites'!A:B,2,FALSE)) | AT40: =IF(A40="","",VLOOKUP(L40,'Base Vendeurs'!A:B,2,FALSE)) | AV40: =IF(A40="","",+AU40/S40)
D41: 2159 | E41: IBIZA | F41: LEFEBVRE JEAN CHARLES | G41: 698.03 | AP41: =IF(AM41="","",+AL41/AM41) | AQ41: =IF(A41="","",VLOOKUP(A41,'Base Sites'!A:B,2,FALSE)) | AT41: =IF(A41="","",VLOOKUP(L41,'Base Vendeurs'!A:B,2,FALSE)) | AV41: =IF(A41="","",+AU41/S41)
C42: Total RQLMO | G42: 1326.75 | AP42: =IF(AM42="","",+AL42/AM42) | AQ42: =IF(A42="","",VLOOKUP(A42,'Base Sites'!A:B,2,FALSE)) | AT42: =IF(A42="","",VLOOKUP(L42,'Base Vendeurs'!A:B,2,FALSE)) | AV42: =IF(A42="","",+AU42/S42)
B43: Somme SE | G43: 20491.09 | AP43: =IF(AM43="","",+AL43/AM43) | AQ43: =IF(A43="","",VLOOKUP(A43,'Base Sites'!A:B,2,FALSE)) | AT43: =IF(A43="","",VLOOKUP(L43,'Base Vendeurs'!A:B,2,FALSE)) | AV43: =IF(A43="","",+AU43/S43)
B44: SK | C44: LTMEL | D44: 1476 | E44: ENYAQ | F44: TEMSYS | G44: 2232.29 | AP44: =IF(AM44="","",+AL44/AM44) | AQ44: =IF(A44="","",VLOOKUP(A44,'Base Sites'!A:B,2,FALSE)) | AT44: =IF(A44="","",VLOOKUP(L44,'Base Vendeurs'!A:B,2,FALSE)) | AV44: =IF(A44="","",+AU44/S44)
D45: 1538 | E45: ELROQ | F45: CABRE | G45: 755.18 | AP45: =IF(AM45="","",+AL45/AM45) | AQ45: =IF(A45="","",VLOOKUP(A45,'Base Sites'!A:B,2,FALSE)) | AT45: =IF(A45="","",VLOOKUP(L45,'Base Vendeurs'!A:B,2,FALSE)) | AV45: =IF(A45="","",+AU45/S45)
D46: 1699 | E46: ELROQ | F46: CABRE | G46: 421.09 | AP46: =IF(AM46="","",+AL46/AM46) | AQ46: =IF(A46="","",VLOOKUP(A46,'Base Sites'!A:B,2,FALSE)) | AT46: =IF(A46="","",VLOOKUP(L46,'Base Vendeurs'!A:B,2,FALSE)) | AV46: =IF(A46="","",+AU46/S46)
D47: 1700 | E47: ELROQ | F47: ARVAL SERVICE LEASE | G47: 818.57 | AP47: =IF(AM47="","",+AL47/AM47) | AQ47: =IF(A47="","",VLOOKUP(A47,'Base Sites'!A:B,2,FALSE)) | AT47: =IF(A47="","",VLOOKUP(L47,'Base Vendeurs'!A:B,2,FALSE)) | AV47: =IF(A47="","",+AU47/S47)
D48: 2035 | E48: OCTAVIA | F48: LE CASIER FRANCAIS | G48: 858.33 | AP48: =IF(AM48="","",+AL48/AM48) | AQ48: =IF(A48="","",VLOOKUP(A48,'Base Sites'!A:B,2,FALSE)) | AT48: =IF(A48="","",VLOOKUP(L48,'Base Vendeurs'!A:B,2,FALSE)) | AV48: =IF(A48="","",+AU48/S48)
C49: Total LTMEL | G49: 5085.46 | AP49: =IF(AM49="","",+AL49/AM49) | AQ49: =IF(A49="","",VLOOKUP(A49,'Base Sites'!A:B,2,FALSE)) | AT49: =IF(A49="","",VLOOKUP(L49,'Base Vendeurs'!A:B,2,FALSE)) | AV49: =IF(A49="","",+AU49/S49)
C50: VSGNI | D50: 1541 | E50: OCTAVIA | F50: TRATO INDUSTRIES | G50: 450.99 | AP50: =IF(AM50="","",+AL50/AM50) | AQ50: =IF(A50="","",VLOOKUP(A50,'Base Sites'!A:B,2,FALSE)) | AT50: =IF(A50="","",VLOOKUP(L50,'Base Vendeurs'!A:B,2,FALSE)) | AV50: =IF(A50="","",+AU50/S50)
D51: 1634 | E51: KAMIQ/YETI | F51: MERZOUK DJERRIDI | G51: 721.45 | AP51: =IF(AM51="","",+AL51/AM51) | AQ51: =IF(A51="","",VLOOKUP(A51,'Base Sites'!A:B,2,FALSE)) | AT51: =IF(A51="","",VLOOKUP(L51,'Base Vendeurs'!A:B,2,FALSE)) | AV51: =IF(A51="","",+AU51/S51)
D52: 2015 | E52: KAMIQ/YETI | F52: MAGNUM | G52: 515.51 | AP52: =IF(AM52="","",+AL52/AM52) | AQ52: =IF(A52="","",VLOOKUP(A52,'Base Sites'!A:B,2,FALSE)) | AT52: =IF(A52="","",VLOOKUP(L52,'Base Vendeurs'!A:B,2,FALSE)) | AV52: =IF(A52="","",+AU52/S52)
D53: 2108 | E53: KODIAQ | F53: LEGAA | G53: 1784.02 | AP53: =IF(AM53="","",+AL53/AM53) | AQ53: =IF(A53="","",VLOOKUP(A53,'Base Sites'!A:B,2,FALSE)) | AT53: =IF(A53="","",VLOOKUP(L53,'Base Vendeurs'!A:B,2,FALSE)) | AV53: =IF(A53="","",+AU53/S53)
D54: 2354 | E54: KODIAQ | F54: ECNV | G54: 1788.52 | AP54: =IF(AM54="","",+AL54/AM54) | AQ54: =IF(A54="","",VLOOKUP(A54,'Base Sites'!A:B,2,FALSE)) | AT54: =IF(A54="","",VLOOKUP(L54,'Base Vendeurs'!A:B,2,FALSE)) | AV54: =IF(A54="","",+AU54/S54)
D55: 2544 | E55: ELROQ | F55: BRASSERIE TANDEM | G55: 875 | AP55: =IF(AM55="","",+AL55/AM55) | AQ55: =IF(A55="","",VLOOKUP(A55,'Base Sites'!A:B,2,FALSE)) | AT55: =IF(A55="","",VLOOKUP(L55,'Base Vendeurs'!A:B,2,FALSE)) | AV55: =IF(A55="","",+AU55/S55)
D56: 2585 | E56: KODIAQ | F56: LUMINET | G56: 1950.38 | AP56: =IF(AM56="","",+AL56/AM56) | AQ56: =IF(A56="","",VLOOKUP(A56,'Base Sites'!A:B,2,FALSE)) | AT56: =IF(A56="","",VLOOKUP(L56,'Base Vendeurs'!A:B,2,FALSE)) | AV56: =IF(A56="","",+AU56/S56)
D57: 2594 | E57: FABIA | F57: HDF CARRELAGE | G57: 501.66 | AP57: =IF(AM57="","",+AL57/AM57) | AQ57: =IF(A57="","",VLOOKUP(A57,'Base Sites'!A:B,2,FALSE)) | AT57: =IF(A57="","",VLOOKUP(L57,'Base Vendeurs'!A:B,2,FALSE)) | AV57: =IF(A57="","",+AU57/S57)
C58: Total VSGNI | G58: 8587.53 | AP58: =IF(AM58="","",+AL58/AM58) | AQ58: =IF(A58="","",VLOOKUP(A58,'Base Sites'!A:B,2,FALSE)) | AT58: =IF(A58="","",VLOOKUP(L58,'Base Vendeurs'!A:B,2,FALSE)) | AV58: =IF(A58="","",+AU58/S58)
C59: RQNBA | D59: 1470 | E59: KAMIQ/YETI | F59: DUMOULIN MANDY | G59: 956.26 | AP59: =IF(AM59="","",+AL59/AM59) | AQ59: =IF(A59="","",VLOOKUP(A59,'Base Sites'!A:B,2,FALSE)) | AT59: =IF(A59="","",VLOOKUP(L59,'Base Vendeurs'!A:B,2,FALSE)) | AV59: =IF(A59="","",+AU59/S59)
D60: 1705 | E60: FABIA | F60: ROBIN SAMANTHA | G60: 900.85 | AP60: =IF(AM60="","",+AL60/AM60) | AQ60: =IF(A60="","",VLOOKUP(A60,'Base Sites'!A:B,2,FALSE)) | AT60: =IF(A60="","",VLOOKUP(L60,'Base Vendeurs'!A:B,2,FALSE)) | AV60: =IF(A60="","",+AU60/S60)
D61: 2017 | E61: FABIA | F61: LEPERS CAROLINE | G61: 572.5 | AP61: =IF(AM61="","",+AL61/AM61) | AQ61: =IF(A61="","",VLOOKUP(A61,'Base Sites'!A:B,2,FALSE)) | AT61: =IF(A61="","",VLOOKUP(L61,'Base Vendeurs'!A:B,2,FALSE)) | AV61: =IF(A61="","",+AU61/S61)
D62: 2020 | E62: FABIA | F62: LEMOINE CATHERINE | G62: 328.5 | AP62: =IF(AM62="","",+AL62/AM62) | AQ62: =IF(A62="","",VLOOKUP(A62,'Base Sites'!A:B,2,FALSE)) | AT62: =IF(A62="","",VLOOKUP(L62,'Base Vendeurs'!A:B,2,FALSE)) | AV62: =IF(A62="","",+AU62/S62)
D63: 2195 | E63: KAMIQ/YETI | F63: HEINTJE AMELIE | G63: 1228 | AP63: =IF(AM63="","",+AL63/AM63) | AQ63: =IF(A63="","",VLOOKUP(A63,'Base Sites'!A:B,2,FALSE)) | AT63: =IF(A63="","",VLOOKUP(L63,'Base Vendeurs'!A:B,2,FALSE)) | AV63: =IF(A63="","",+AU63/S63)
D64: 2350 | E64: KODIAQ | F64: BELORGEY NICOLAS | G64: 3104.35 | AP64: =IF(AM64="","",+AL64/AM64) | AQ64: =IF(A64="","",VLOOKUP(A64,'Base Sites'!A:B,2,FALSE)) | AT64: =IF(A64="","",VLOOKUP(L64,'Base Vendeurs'!A:B,2,FALSE)) | AV64: =IF(A64="","",+AU64/S64)
D65: 2547 | E65: ENYAQ | F65: BALANCHE PIERRE | G65: 2468.26 | AP65: =IF(AM65="","",+AL65/AM65) | AQ65: =IF(A65="","",VLOOKUP(A65,'Base Sites'!A:B,2,FALSE)) | AT65: =IF(A65="","",VLOOKUP(L65,'Base Vendeurs'!A:B,2,FALSE)) | AV65: =IF(A65="","",+AU65/S65)
C66: Total RQNBA | G66: 9558.72 | AP66: =IF(AM66="","",+AL66/AM66) | AQ66: =IF(A66="","",VLOOKUP(A66,'Base Sites'!A:B,2,FALSE)) | AT66: =IF(A66="","",VLOOKUP(L66,'Base Vendeurs'!A:B,2,FALSE)) | AV66: =IF(A66="","",+AU66/S66)
C67: LTHVI | D67: 1801 | E67: ELROQ | F67: POUILLON SAMUEL | G67: 1948.7 | AP67: =IF(AM67="","",+AL67/AM67) | AQ67: =IF(A67="","",VLOOKUP(A67,'Base Sites'!A:B,2,FALSE)) | AT67: =IF(A67="","",VLOOKUP(L67,'Base Vendeurs'!A:B,2,FALSE)) | AV67: =IF(A67="","",+AU67/S67)
C68: Total LTHVI | G68: 1948.7 | AP68: =IF(AM68="","",+AL68/AM68) | AQ68: =IF(A68="","",VLOOKUP(A68,'Base Sites'!A:B,2,FALSE)) | AT68: =IF(A68="","",VLOOKUP(L68,'Base Vendeurs'!A:B,2,FALSE)) | AV68: =IF(A68="","",+AU68/S68)
C69: RQTHC | D69: 1255 | E69: FABIA | F69: BIZ DAVID | G69: 1326.17 | AP69: =IF(AM69="","",+AL69/AM69) | AQ69: =IF(A69="","",VLOOKUP(A69,'Base Sites'!A:B,2,FALSE)) | AT69: =IF(A69="","",VLOOKUP(L69,'Base Vendeurs'!A:B,2,FALSE)) | AV69: =IF(A69="","",+AU69/S69)
D70: 1421 | E70: OCTAVIA | F70: MOUTON TATIANA | G70: 828.75 | AP70: =IF(AM70="","",+AL70/AM70) | AQ70: =IF(A70="","",VLOOKUP(A70,'Base Sites'!A:B,2,FALSE)) | AT70: =IF(A70="","",VLOOKUP(L70,'Base Vendeurs'!A:B,2,FALSE)) | AV70: =IF(A70="","",+AU70/S70)
D71: 1424 | E71: KODIAQ | F71: WROBEL FABIENNE | G71: 2478.17 | AP71: =IF(AM71="","",+AL71/AM71) | AQ71: =IF(A71="","",VLOOKUP(A71,'Base Sites'!A:B,2,FALSE)) | AT71: =IF(A71="","",VLOOKUP(L71,'Base Vendeurs'!A:B,2,FALSE)) | AV71: =IF(A71="","",+AU71/S71)
D72: 1439 | E72: KAMIQ/YETI | F72: CUVELIER ESTELLE | G72: 656.19 | AP72: =IF(AM72="","",+AL72/AM72) | AQ72: =IF(A72="","",VLOOKUP(A72,'Base Sites'!A:B,2,FALSE)) | AT72: =IF(A72="","",VLOOKUP(L72,'Base Vendeurs'!A:B,2,FALSE)) | AV72: =IF(A72="","",+AU72/S72)
D73: 1442 | E73: ENYAQ | F73: FERME DE LA GONTIERE | G73: 1559.27 | AP73: =IF(AM73="","",+AL73/AM73) | AQ73: =IF(A73="","",VLOOKUP(A73,'Base Sites'!A:B,2,FALSE)) | AT73: =IF(A73="","",VLOOKUP(L73,'Base Vendeurs'!A:B,2,FALSE)) | AV73: =IF(A73="","",+AU73/S73)
D74: 1447 | E74: ENYAQ | F74: IGT COURTAGE ET SOLUTIONS | G74: 1980.62 | AP74: =IF(AM74="","",+AL74/AM74) | AQ74: =IF(A74="","",VLOOKUP(A74,'Base Sites'!A:B,2,FALSE)) | AT74: =IF(A74="","",VLOOKUP(L74,'Base Vendeurs'!A:B,2,FALSE)) | AV74: =IF(A74="","",+AU74/S74)
D75: 1451 | E75: OCTAVIA | F75: MASSELOT MICHAEL | G75: 1380.59 | AP75: =IF(AM75="","",+AL75/AM75) | AQ75: =IF(A75="","",VLOOKUP(A75,'Base Sites'!A:B,2,FALSE)) | AT75: =IF(A75="","",VLOOKUP(L75,'Base Vendeurs'!A:B,2,FALSE)) | AV75: =IF(A75="","",+AU75/S75)
D76: 1453 | E76: OCTAVIA | F76: LIGNON STEPHANE | G76: 1020.65 | AP76: =IF(AM76="","",+AL76/AM76) | AQ76: =IF(A76="","",VLOOKUP(A76,'Base Sites'!A:B,2,FALSE)) | AT76: =IF(A76="","",VLOOKUP(L76,'Base Vendeurs'!A:B,2,FALSE)) | AV76: =IF(A76="","",+AU76/S76)
D77: 1454 | E77: FABIA | F77: LAMBOLEZ CHRISTOPHER | G77: 962.75 | AP77: =IF(AM77="","",+AL77/AM77) | AQ77: =IF(A77="","",VLOOKUP(A77,'Base Sites'!A:B,2,FALSE)) | AT77: =IF(A77="","",VLOOKUP(L77,'Base Vendeurs'!A:B,2,FALSE)) | AV77: =IF(A77="","",+AU77/S77)
D78: 1460 | E78: ELROQ | F78: VANHULLE MYLENE | G78: 1005.01 | AP78: =IF(AM78="","",+AL78/AM78) | AQ78: =IF(A78="","",VLOOKUP(A78,'Base Sites'!A:B,2,FALSE)) | AT78: =IF(A78="","",VLOOKUP(L78,'Base Vendeurs'!A:B,2,FALSE)) | AV78: =IF(A78="","",+AU78/S78)
D79: 1461 | E79: ELROQ | F79: SCRIVE ANNE | G79: 1087.05 | AP79: =IF(AM79="","",+AL79/AM79) | AQ79: =IF(A79="","",VLOOKUP(A79,'Base Sites'!A:B,2,FALSE)) | AT79: =IF(A79="","",VLOOKUP(L79,'Base Vendeurs'!A:B,2,FALSE)) | AV79: =IF(A79="","",+AU79/S79)
D80: 1463 | E80: KAMIQ/YETI | F80: ASSOCIATION POUR LA REEDUCATION | G80: 1591.27 | AP80: =IF(AM80="","",+AL80/AM80) | AQ80: =IF(A80="","",VLOOKUP(A80,'Base Sites'!A:B,2,FALSE)) | AT80: =IF(A80="","",VLOOKUP(L80,'Base Vendeurs'!A:B,2,FALSE)) | AV80: =IF(A80="","",+AU80/S80)
D81: 1466 | E81: KODIAQ | F81: DUPIRE FRANCK | G81: 1880.34 | AP81: =IF(AM81="","",+AL81/AM81) | AQ81: =IF(A81="","",VLOOKUP(A81,'Base Sites'!A:B,2,FALSE)) | AT81: =IF(A81="","",VLOOKUP(L81,'Base Vendeurs'!A:B,2,FALSE)) | AV81: =IF(A81="","",+AU81/S81)
... D158: 511811 | E158: KODIAQ | F158: PARIS TERMINAL SA | G158: 1189.23 | AP158: =IF(AM158="","",+AL158/AM158) | AQ158: =IF(A158="","",VLOOKUP(A158,'Base Sites'!A:B,2,FALSE)) | AT158: =IF(A158="","",VLOOKUP(L158,'Base Vendeurs'!A:B,2,FALSE)) | AV158: =IF(A158="","",+AU158/S158)
C159: Total RQTHC | G159: 112604.78 | AP159: =IF(AM159="","",+AL159/AM159) | AQ159: =IF(A159="","",VLOOKUP(A159,'Base Sites'!A:B,2,FALSE)) | AT159: =IF(A159="","",VLOOKUP(L159,'Base Vendeurs'!A:B,2,FALSE)) | AV159: =IF(A159="","",+AU159/S159)
C160: VSFCA | D160: 1540 | E160: OCTAVIA | F160: CH4 SYSTEMES | G160: 381.25 | AP160: =IF(AM160="","",+AL160/AM160) | AQ160: =IF(A160="","",VLOOKUP(A160,'Base Sites'!A:B,2,FALSE)) | AT160: =IF(A160="","",VLOOKUP(L160,'Base Vendeurs'!A:B,2,FALSE)) | AV160: =IF(A160="","",+AU160/S160)
D161: 1908 | E161: OCTAVIA | F161: STICK IT FRANCE | G161: 1046.12 | AP161: =IF(AM161="","",+AL161/AM161) | AQ161: =IF(A161="","",VLOOKUP(A161,'Base Sites'!A:B,2,FALSE)) | AT161: =IF(A161="","",VLOOKUP(L161,'Base Vendeurs'!A:B,2,FALSE)) | AV161: =IF(A161="","",+AU161/S161)
C162: Total VSFCA | G162: 1427.37 | AP162: =IF(AM162="","",+AL162/AM162) | AQ162: =IF(A162="","",VLOOKUP(A162,'Base Sites'!A:B,2,FALSE)) | AT162: =IF(A162="","",VLOOKUP(L162,'Base Vendeurs'!A:B,2,FALSE)) | AV162: =IF(A162="","",+AU162/S162)
C163: VRGWI | D163: 1818 | E163: OCTAVIA | F163: ADISS | G163: 953.07 | AP163: =IF(AM163="","",+AL163/AM163) | AQ163: =IF(A163="","",VLOOKUP(A163,'Base Sites'!A:B,2,FALSE)) | AT163: =IF(A163="","",VLOOKUP(L163,'Base Vendeurs'!A:B,2,FALSE)) | AV163: =IF(A163="","",+AU163/S163)
C164: Total VRGWI | G164: 953.07 | AP164: =IF(AM164="","",+AL164/AM164) | AQ164: =IF(A164="","",VLOOKUP(A164,'Base Sites'!A:B,2,FALSE)) | AT164: =IF(A164="","",VLOOKUP(L164,'Base Vendeurs'!A:B,2,FALSE)) | AV164: =IF(A164="","",+AU164/S164)
C165: VSRPO | D165: 1816 | E165: KAMIQ/YETI | F165: DAUPHIN DENIS | G165: 887.75 | AP165: =IF(AM165="","",+AL165/AM165) | AQ165: =IF(A165="","",VLOOKUP(A165,'Base Sites'!A:B,2,FALSE)) | AT165: =IF(A165="","",VLOOKUP(L165,'Base Vendeurs'!A:B,2,FALSE)) | AV165: =IF(A165="","",+AU165/S165)
D166: 1823 | E166: ENYAQ | F166: FRENCH PAYROLL SERVICES SECRETA | G166: 1490.51 | AP166: =IF(AM166="","",+AL166/AM166) | AQ166: =IF(A166="","",VLOOKUP(A166,'Base Sites'!A:B,2,FALSE)) | AT166: =IF(A166="","",VLOOKUP(L166,'Base Vendeurs'!A:B,2,FALSE)) | AV166: =IF(A166="","",+AU166/S166)
D167: 2043 | E167: KODIAQ | F167: S D O SARL | G167: 1385.18 | AP167: =IF(AM167="","",+AL167/AM167) | AQ167: =IF(A167="","",VLOOKUP(A167,'Base Sites'!A:B,2,FALSE)) | AT167: =IF(A167="","",VLOOKUP(L167,'Base Vendeurs'!A:B,2,FALSE)) | AV167: =IF(A167="","",+AU167/S167)
D168: 2347 | E168: KAMIQ/YETI | F168: HOLDING COOK | G168: 860.5 | AP168: =IF(AM168="","",+AL168/AM168) | AQ168: =IF(A168="","",VLOOKUP(A168,'Base Sites'!A:B,2,FALSE)) | AT168: =IF(A168="","",VLOOKUP(L168,'Base Vendeurs'!A:B,2,FALSE)) | AV168: =IF(A168="","",+AU168/S168)
C169: Total VSRPO | G169: 4623.94 | AP169: =IF(AM169="","",+AL169/AM169) | AQ169: =IF(A169="","",VLOOKUP(A169,'Base Sites'!A:B,2,FALSE)) | AT169: =IF(A169="","",VLOOKUP(L169,'Base Vendeurs'!A:B,2,FALSE)) | AV169: =IF(A169="","",+AU169/S169)
C170: VSJTI | D170: 1731 | E170: OCTAVIA | F170: IPH INGENIERIE | G170: 725.99 | AP170: =IF(AM170="","",+AL170/AM170) | AQ170: =IF(A170="","",VLOOKUP(A170,'Base Sites'!A:B,2,FALSE)) | AT170: =IF(A170="","",VLOOKUP(L170,'Base Vendeurs'!A:B,2,FALSE)) | AV170: =IF(A170="","",+AU170/S170)
D171: 2049 | E171: KAMIQ/YETI | F171: LEKOEUGE ELODIE | G171: 938.27 | AP171: =IF(AM171="","",+AL171/AM171) | AQ171: =IF(A171="","",VLOOKUP(A171,'Base Sites'!A:B,2,FALSE)) | AT171: =IF(A171="","",VLOOKUP(L171,'Base Vendeurs'!A:B,2,FALSE)) | AV171: =IF(A171="","",+AU171/S171)
C172: Total VSJTI | G172: 1664.26 | AP172: =IF(AM172="","",+AL172/AM172) | AQ172: =IF(A172="","",VLOOKUP(A172,'Base Sites'!A:B,2,FALSE)) | AT172: =IF(A172="","",VLOOKUP(L172,'Base Vendeurs'!A:B,2,FALSE)) | AV172: =IF(A172="","",+AU172/S172)
C173: VANBU | D173: 1812 | E173: OCTAVIA | F173: ELECTEKA | G173: 1652.99 | AP173: =IF(AM173="","",+AL173/AM173) | AQ173: =IF(A173="","",VLOOKUP(A173,'Base Sites'!A:B,2,FALSE)) | AT173: =IF(A173="","",VLOOKUP(L173,'Base Vendeurs'!A:B,2,FALSE)) | AV173: =IF(A173="","",+AU173/S173)
C174: Total VANBU | G174: 1652.99 | AP174: =IF(AM174="","",+AL174/AM174) | AQ174: =IF(A174="","",VLOOKUP(A174,'Base Sites'!A:B,2,FALSE)) | AT174: =IF(A174="","",VLOOKUP(L174,'Base Vendeurs'!A:B,2,FALSE)) | AV174: =IF(A174="","",+AU174/S174)
C175: VRTVA | D175: 2006 | E175: ELROQ | F175: CARPENTIER-DORCHY | G175: 386.02 | AP175: =IF(AM175="","",+AL175/AM175) | AQ175: =IF(A175="","",VLOOKUP(A175,'Base Sites'!A:B,2,FALSE)) | AT175: =IF(A175="","",VLOOKUP(L175,'Base Vendeurs'!A:B,2,FALSE)) | AV175: =IF(A175="","",+AU175/S175)
C176: Total VRTVA | G176: 386.02 | AP176: =IF(AM176="","",+AL176/AM176) | AQ176: =IF(A176="","",VLOOKUP(A176,'Base Sites'!A:B,2,FALSE)) | AT176: =IF(A176="","",VLOOKUP(L176,'Base Vendeurs'!A:B,2,FALSE)) | AV176: =IF(A176="","",+AU176/S176)
...

Sheet Détails2
A1: Détails pou for Nbre de LIV. - Modèle livré: ID BUZZ, Site: 20, Marque: VW, Vendeur: LEGCH (+)
A3: Site | B3: Etat | C3: Marque | D3: Date de Facturation | E3: Date de Livraison | F3: Manque Marge | G3: PB Marge | H3: Justif ? | I3: Solde Client | J3: Validé DF | K3: Solde client2 | L3: Vendeur | M3: N° VN | N3: N° CDE | O3: Châssis | P3: CLIENT | Q3: Modèle livré | R3: Prix de Vte | S3: Options | T3: Total | U3: Jours de Stock | V3: Marge nette | W3: Marge s/transport | X3: déduction diverse | Y3: Marge restante | Z3: % PV | AA3: OP Clos | AB3: OP Ouverts | AC3: OP non visible | AD3: libellé OP non visible | AE3: TX COM | AF3: TX COM Opticar | AG3: Commission de Base | AH3: Prime opération | AI3: Total COM | AJ3: Sté de Financement | AK3: EXT GIE | AL3: Forfait immat | AM3: nbre de forfait | AN3: nbre de livraison | AO3: OP "+ / -" | AP3: date | AQ3: % forfait | AR3: AU | AS3: Marque4 | AT3: non utilisé | AU3: Equipe | AV3: Marge nette recalculée | AW3: % PV5 | AX3: Marge négative | AY3: TOTAL COM VENDEUR
A4: 20 | B4: NC | C4: VU | D4: 45833 | E4: 45827 | G4: x | K4: 0 | L4: VRGWI | M4: 519508 | N4: 9508 | O4: WV2ZZZEB3SH013679 | P4: JSDENTAIRE | Q4: ID BUZZ | R4: 47499.77 | S4: 9741.67 | T4: 57241.44 | U4: 15 | V4: 3129.76 | W4: 0 | Y4: 3129.76 | Z4: 0.054676472 | AA4: 0 | AB4: 0 | AD4: Ecart de marge | AE4: 0.13 | AF4: 0.1 | AG4: 406.8688 | AI4: 406.8688 | AJ4: VWB | AK4: 0 | AL4: 20 | AM4: 1 | AN4: 1 | AQ4: 1 | AR4: Valauto Professionnels | AS4: VUL | AU4: Valauto PRO NORD | AV4: 3129.76 | AW4: 0.054676472 | AX4: NON | AY4: 426.8688
A5: 20 | B5: C | C5: VU | D5: 45856 | E5: 45856 | K5: 0 | L5: VRGWI | M5: 523635 | N5: 635 | O5: WV2ZZZEB3SH049274 | P5: SAMECA | Q5: ID BUZZ | R5: 42874.77 | S5: 5975 | T5: 48849.77 | U5: 3 | V5: 2115.84 | W5: 0.9 | Y5: 2114.94 | Z5: 0.043313203 | AA5: 0 | AB5: 0 | AE5: 0.1 | AF5: 0.1 | AG5: 211.494 | AI5: 211.494 | AK5: 0 | AL5: 20 | AM5: 1 | AN5: 1 | AQ5: 1 | AR5: Valauto Professionnels | AS5: VUL | AU5: Valauto PRO NORD | AV5: 2115.84 | AW5: 0.043313203 | AX5: NON | AY5: 231.494
A6: 20 | B6: C | C6: VU | D6: 45861 | E6: 45862 | K6: 0 | L6: VRGWI | M6: 514223 | N6: 4223 | O6: WV2ZZZEB6SH050693 | P6: ADISS | Q6: ID BUZZ | R6: 59499.77 | S6: 4787.5 | T6: 64287.27 | U6: 8 | V6: 1853.08 | W6: 0.9 | Y6: 1852.18 | Z6: 0.028824991 | AA6: 0 | AB6: -997.69 | AE6: 0.1 | AF6: 0.1 | AG6: 185.218 | AI6: 185.218 | AJ6: VWB | AK6: 0 | AL6: 20 | AM6: 1 | AN6: 1 | AQ6: 1 | AR6: Valauto Professionnels | AS6: VUL | AU6: Valauto PRO NORD | AV6: 1853.08 | AW6: 0.028824991 | AX6: NON | AY6: 205.218
A7: 20 | B7: NC | C7: VU | D7: 45848 | E7: 45847 | G7: x | K7: 0 | L7: VRGWI | M7: 519503 | N7: 9503 | O7: WV1ZZZEB9PH004996 | P7: TRANSPORT STOCK AND LOG | Q7: ID BUZZ | R7: 47471.86 | S7: 7050 | T7: 54521.86 | U7: 146 | V7: 1079.94 | W7: 0 | Y7: 1079.94 | Z7: 0.019807468 | AA7: 0 | AB7: 0 | AD7: 0 comm demandé // Forfait // Ecart de marge // VN vendu 37990€ au lieu de 38118€ | AF7: 0.12 | AG7: 0 | AH7: 200 | AI7: 200 | AJ7: Banque | AM7: 0 | AN7: 1 | AQ7: 0 | AR7: Valauto Professionnels | AS7: VUL | AU7: Valauto PRO NORD | AV7: 1079.94 | AW7: 0.019807468 | AX7: NON | AY7: 200

Sheet Détails3
A1: Détails pou for Nbre de LIV. - Modèle livré: POLO, Site: 80, Marque: VW, Vendeur: LEGCH (+)
A3: Site | B3: Etat | C3: Marque | D3: Date de Facturation | E3: Date de Livraison | F3: Manque Marge | G3: PB Marge | H3: Justif ? | I3: Solde Client | J3: Validé DF | K3: Solde client2 | L3: Vendeur | M3: N° VN | N3: N° CDE | O3: Châssis | P3: CLIENT | Q3: Modèle livré | R3: Prix de Vte | S3: Options | T3: Total | U3: Jours de Stock | V3: Marge nette | W3: Marge s/transport | X3: déduction diverse | Y3: Marge restante | Z3: % PV | AA3: OP Clos | AB3: OP Ouverts | AC3: OP non visible | AD3: libellé OP non visible | AE3: TX COM | AF3: TX COM Opticar | AG3: Commission de Base | AH3: Prime opération | AI3: Total COM | AJ3: Sté de Financement | AK3: EXT GIE | AL3: Forfait immat | AM3: nbre de forfait | AN3: nbre de livraison | AO3: OP "+ / -" | AP3: date | AQ3: % forfait | AR3: AU | AS3: Marque4 | AT3: non utilisé | AU3: Equipe | AV3: Marge nette recalculée | AW3: % PV5 | AX3: Marge négative | AY3: TOTAL COM VENDEUR
A4: 15 | B4: C | C4: VW | D4: 46097 | E4: 46097 | K4: 0 | L4: VSJTI | M4: 512062 | N4: 2062 | O4: WVWZZZAW9TU009622 | P4: NSI 4 | Q4: POLO | R4: 22014 | S4: 450 | T4: 22464 | U4: 25 | V4: 3801.72 | W4: 95 | X4: -3257.44 | Y4: 449.28 | Z4: 0.024228989 | AA4: -6514.88 | AB4: 0 | AE4: 0.13 | AF4: 0.13 | AG4: 58.4064 | AI4: 58.4064 | AJ4: VWB | AM4: 0 | AN4: 1 | AQ4: 0 | AR4: Valauto Hainaut | AS4: VOLKSWAGEN | AU4: Sociétés EST | AV4: 3801.72 | AW4: 0.16923611 | AX4: NON | AY4: 58.4064
A5: 15 | B5: NP | C5: VW | D5: 46072 | E5: 46073 | I5: x | K5: -427.15 | L5: VSJTI | M5: 511282 | N5: 1282 | O5: WVWZZZAW6SU097737 | P5: NSI 1 | Q5: POLO | R5: 20201.5 | S5: 1858.34 | T5: 22059.84 | U5: 16 | V5: 626.23 | W5: 95 | Y5: 531.23 | Z5: 0.028387785 | AA5: -90 | AB5: 0 | AD5: solde client reprise balance slba 2023 | AE5: 0.1 | AF5: 0.1 | AG5: 53.123 | AI5: 53.123 | AJ5: VWB | AK5: 0 | AL5: 0 | AM5: 1 | AN5: 1 | AQ5: 1 | AR5: Valauto Hainaut | AS5: VOLKSWAGEN | AU5: Sociétés EST | AV5: 626.23 | AW5: 0.028387785 | AX5: NON | AY5: 53.123
A6: 15 | B6: C | C6: VW | D6: 46098 | E6: 46098 | K6: 0 | L6: VSJTI | M6: 512063 | N6: 2063 | O6: WVWZZZAW0TU010948 | P6: NSI 4 | Q6: POLO | R6: 20605.67 | S6: 850 | T6: 21455.67 | U6: 25 | V6: 416.86 | W6: 95 | Y6: 321.86 | Z6: 0.019428897 | AA6: -2789.25 | AB6: 0 | AE6: 0.13 | AF6: 0.13 | AG6: 41.8418 | AI6: 41.8418 | AJ6: VWB | AM6: 0 | AN6: 1 | AQ6: 0 | AR6: Valauto Hainaut | AS6: VOLKSWAGEN | AU6: Sociétés EST | AV6: 416.86 | AW6: 0.019428897 | AX6: NON | AY6: 41.8418
A7: 15 | B7: C | C7: VW | D7: 46042 | E7: 46042 | L7: VAJSA | M7: 511414 | N7: 1414 | O7: WVWZZZAWXTU031208 | P7: MELCHIORRE PAULINE | Q7: POLO | R7: 20605.67 | S7: 179.16 | T7: 20784.83 | U7: 7 | V7: -343.4 | W7: 95 | Y7: -438.4 | Z7: -0.016521665 | AA7: 0 | AB7: -1440 | AD7: marge négative // | AF7: 0.1 | AG7: 0 | AI7: 0 | AJ7: VWB | AM7: 0 | AN7: 1 | AQ7: 0 | AR7: Valauto Hainaut | AS7: VOLKSWAGEN | AU7: Valauto Hainaut VW | AV7: -343.4 | AW7: -0.016521665 | AX7: OUI | AY7: 0
A8: 15 | B8: C | C8: VW | D8: 46078 | E8: 46078 | K8: 0 | L8: VAGWO | M8: 511997 | N8: 1997 | O8: WVWZZZAWXTU022301 | P8: -MME SEGUIN SEBASTIEN ET AURELIE | Q8: POLO | R8: 23014 | S8: 1187.49 | T8: 24201.49 | U8: 14 | V8: 979.1 | W8: 95 | Y8: 884.1 | Z8: 0.040456187 | AA8: 0 | AB8: -2356.67 | AE8: 0.1 | AF8: 0.13 | AG8: 88.41 | AI8: 88.41 | AK8: 30 | AL8: 50 | AM8: 1 | AN8: 1 | AQ8: 1 | AR8: Valauto Hainaut | AS8: VOLKSWAGEN | AU8: Valauto Hainaut VW | AV8: 979.1 | AW8: 0.040456187 | AX8: NON | AY8: 168.41
A9: 15 | B9: C | C9: VW | D9: 46062 | E9: 46062 | K9: 0 | L9: VACLE | M9: 511786 | N9: 1786 | O9: WVWZZZAW9TU035718 | P9: YAKIMOVICH YULIYA | Q9: POLO | R9: 24705.67 | S9: 1287.49 | T9: 25993.16 | U9: 27 | V9: -343.48 | W9: 95 | Y9: -438.48 | Z9: -0.013214246 | AA9: 0 | AB9: -856.67 | AD9: marge négative // 0 forfait demandé | AF9: 0.07 | AG9: 0 | AI9: 0 | AJ9: VWB | AK9: 30 | AL9: 50 | AM9: 1 | AN9: 1 | AQ9: 1 | AR9: Valauto Hainaut | AS9: VOLKSWAGEN | AU9: Valauto Hainaut VW | AV9: -343.48 | AW9: -0.013214246 | AX9: OUI | AY9: 80
A10: 15 | B10: C | C10: VW | D10: 46080 | E10: 46080 | K10: 0 | L10: VAFFA | M10: 519553 | N10: 9553 | O10: WVWZZZAW9TU026078 | P10: DI BARBORA MICHAEL | Q10: POLO | R10: 23014 | S10: 1187.49 | T10: 24201.49 | U10: 65 | V10: 979.09 | W10: 94.99 | Y10: 884.1 | Z10: 0.040455774 | AA10: 0 | AB10: -2356.67 | AE10: 0.13 | AF10: 0.13 | AG10: 114.933 | AI10: 114.933 | AJ10: VWB | AK10: 30 | AL10: 50 | AM10: 1 | AN10: 1 | AQ10: 1 | AR10: Valauto Hainaut | AS10: VOLKSWAGEN | AU10: Valauto Hainaut VW | AV10: 979.09 | AW10: 0.040455774 | AX10: NON | AY10: 194.933
A11: 15 | B11: C | C11: VW | D11: 46050 | E11: 46041 | K11: 0 | L11: VAGWO | M11: 511381 | N11: 1381 | O11: WVWZZZAW9TU009328 | P11: DETOULET YOHAN | Q11: POLO | R11: 21605.67 | S11: 1833.33 | T11: 23439 | U11: 61 | V11: 853.48 | W11: 95 | Y11: 758.48 | Z11: 0.036412816 | AA11: 0 | AB11: -1800.01 | AE11: 0.13 | AF11: 0.13 | AG11: 98.6024 | AI11: 98.6024 | AJ11: VWB | AK11: 30 | AL11: 20 | AM11: 1 | AN11: 1 | AQ11: 1 | AR11: Valauto Hainaut | AS11: VOLKSWAGEN | AU11: Valauto Hainaut VW | AV11: 853.48 | AW11: 0.036412816 | AX11: NON | AY11: 148.6024
A12: 15 | B12: C | C12: VW | D12: 46104 | E12: 46099 | K12: 0 | L12: VAGWO | M12: 512086 | N12: 2086 | O12: WVWZZZAW8TU032292 | P12: MOYAUX CORINE | Q12: POLO | R12: 21605.67 | S12: 1233.33 | T12: 22839 | U12: 14 | V12: 930.48 | W12: 95 | Y12: 835.48 | Z12: 0.040740838 | AA12: -228.4 | AB12: -2466.67 | AE12: 0.1 | AF12: 0.13 | AG12: 83.548 | AI12: 83.548 | AJ12: VWB | AK12: 30 | AM12: 0 | AN12: 1 | AQ12: 0 | AR12: Valauto Hainaut | AS12: VOLKSWAGEN | AU12: Valauto Hainaut VW | AV12: 930.48 | AW12: 0.040740838 | AX12: NON | AY12: 113.548
A13: 15 | B13: C | C13: VW | D13: 46069 | E13: 46070 | K13: 0 | L13: VAJSA | M13: 511371 | N13: 1371 | O13: WVWZZZAW8TU031949 | P13: DELENATTE CHRISTIAN | Q13: POLO | R13: 20605.67 | S13: 679.16 | T13: 21284.83 | U13: 34 | V13: -315.06 | W13: 95 | Y13: -410.06 | Z13: -0.014802091 | AA13: 0 | AB13: -856.67 | AD13: mare négative | AF13: 0.1 | AG13: 0 | AI13: 0 | AJ13: VWB | AM13: 0 | AN13: 1 | AQ13: 0 | AR13: Valauto Hainaut | AS13: VOLKSWAGEN | AU13: Valauto Hainaut VW | AV13: -315.06 | AW13: -0.014802091 | AX13: OUI | AY13: 0
A14: 15 | B14: C | C14: VW | D14: 46098 | E14: 46098 | K14: 0 | L14: VAGWO | M14: 512065 | N14: 2065 | O14: WVWZZZAW6TU018312 | P14: LEBRUN ANNE SOPHIE | Q14: POLO | R14: 21605.67 | S14: 1233.33 | T14: 22839 | U14: 21 | V14: 972.14 | W14: 95 | Y14: 877.14 | Z14: 0.042564911 | AA14: 0 | AB14: -2466.67 | AE14: 0.1 | AF14: 0.13 | AG14: 87.714 | AI14: 87.714 | AK14: 30 | AL14: 50 | AM14: 1 | AN14: 1 | AQ14: 1 | AR14: Valauto Hainaut | AS14: VOLKSWAGEN | AU14: Valauto Hainaut VW | AV14: 972.14 | AW14: 0.042564911 | AX14: NON | AY14: 167.714
A15: 15 | B15: C | C15: VW | D15: 46055 | E15: 46055 | K15: 0 | L15: VACLE | M15: 521012 | N15: 1012 | O15: WVWZZZAW6RU066594 | P15: VERWAERDE MARYVONNE | Q15: POLO | R15: 21176.5 | S15: 891.67 | T15: 22068.17 | U15: 416 | V15: 1354.18 | W15: 95 | Y15: 1259.18 | Z15: 0.061363493 | AA15: 0 | AB15: 0 | AE15: 0.13 | AF15: 0.13 | AG15: 163.6934 | AI15: 163.6934 | AK15: 30 | AM15: 0 | AN15: 1 | AQ15: 0 | AR15: Valauto Hainaut | AS15: VOLKSWAGEN | AU15: Valauto Hainaut VW | AV15: 1354.18 | AW15: 0.061363493 | AX15: NON | AY15: 193.6934
A16: 15 | B16: C | C16: VW | D16: 46106 | E16: 46107 | K16: 0 | L16: VAFFA | M16: 512064 | N16: 2064 | O16: WVWZZZAW4TU005901 | P16: DUPONT CHRISTOPHE | Q16: POLO | R16: 21605.67 | S16: 1233.33 | T16: 22839 | U16: 33 | V16: 1055.48 | W16: 95 | Y16: 960.48 | Z16: 0.046213932 | AA16: 0 | AB16: -2466.67 | AE16: 0.13 | AF16: 0.13 | AG16: 124.8624 | AI16: 124.8624 | AJ16: VWB | AK16: 30 | AL16: 50 | AM16: 1 | AN16: 1 | AQ16: 1 | AR16: Valauto Hainaut | AS16: VOLKSWAGEN | AU16: Valauto Hainaut VW | AV16: 1055.48 | AW16: 0.046213932 | AX16: NON | AY16: 204.8624
A17: 15 | B17: C | C17: VW | D17: 46106 | E17: 46106 | L17: VAGWO | M17: 512002 | N17: 2002 | O17: WVWZZZAW2TU035429 | P17: LEVEAUX HELENE | Q17: POLO | R17: 20605.67 | S17: 179.16 | T17: 20784.83 | U17: 42 | V17: 739.94 | W17: 95 | Y17: 644.94 | Z17: 0.035600003 | AA17: 0 | AB17: -2356.67 | AE17: 0.1 | AF17: 0.13 | AG17: 64.494 | AI17: 64.494 | AJ17: VWB | AK17: 30 | AM17: 0 | AN17: 1 | AQ17: 0 | AR17: Valauto Hainaut | AS17: VOLKSWAGEN | AU17: Valauto Hainaut VW | AV17: 739.94 | AW17: 0.035600003 | AX17: NON | AY17: 94.494
A18: 15 | B18: NP | C18: VW | D18: 46092 | E18: 46087 | I18: x | K18: 90 | L18: VAFFA | M18: 511958 | N18: 1958 | O18: WVWZZZAW0TU041519 | P18: AGNOLETTI SIMON | Q18: POLO | R18: 17714 | S18: 233.33 | T18: 17947.33 | U18: 40 | V18: 497.45 | W18: 95 | Y18: 402.45 | Z18: 0.027717215 | AA18: -966.67 | AB18: 0 | AD18: solde client écart CG | AE18: 0.1 | AF18: 0.07 | AG18: 40.245 | AI18: 40.245 | AJ18: VWB | AK18: 30 | AM18: 0 | AN18: 1 | AQ18: 0 | AR18: Valauto Hainaut | AS18: VOLKSWAGEN | AU18: Valauto Hainaut VW | AV18: 497.45 | AW18: 0.027717215 | AX18: NON | AY18: 70.245

Sheet Marges_VN_Modèles
A1: VALAUTO - Marges / Modèles
A3: Site | B3: 10
A4: Marque | B4: SK
A5: Vendeur | B5: (Tous)
A7: Étiquettes de lignes | B7: Nbre de LIV. | C7: Somme de Total | D7: Somme de Marge nette2 | E7: PV TOTAL hors transport | F7: Somme de OP Clos | G7: Somme de OP Ouverts | H7: Somme de Marge nette | I7: Somme de OP "+ / -" | J7: Somme de Marge nette recalculée | K7: Moyenne de Marge nette recalculée2
A8: ELROQ | B8: 28 | C8: 954958.15 | D8: 32467.09 | E8: 954958.15 | F8: -25997.68 | G8: -52586.79 | H8: 32467.09 | I8: 186 | J8: 32653.09 | K8: 1166.1818
A9: ENYAQ | B9: 15 | C9: 682899.9 | D9: 24078.03 | E9: 682899.9 | F9: -18905.16 | G9: -20311.71 | H9: 24078.03 | J9: 24078.03 | K9: 1605.202
A10: FABIA | B10: 29 | C10: 642608.28 | D10: 21830.28 | E10: 642608.28 | F10: -9448.75 | G10: -69880 | H10: 21830.28 | J10: 21830.28 | K10: 752.76828
A11: KAMIQ/YETI | B11: 20 | C11: 558900.04 | D11: 19279.01 | E11: 558900.04 | F11: -27504.74 | G11: -49611.29 | H11: 19279.01 | I11: 250 | J11: 19529.01 | K11: 976.4505
A12: KAROQ | B12: 4 | C12: 150258.36 | D12: 4134.11 | E12: 150258.36 | F12: -3412.5 | G12: -7625 | H12: 4134.11 | J12: 4134.11 | K12: 1033.5275
A13: KODIAQ | B13: 25 | C13: 1170391.6 | D13: 40667.78 | E13: 1170391.6 | F13: -57662.69 | G13: -34224.17 | H13: 40667.78 | J13: 40667.78 | K13: 1626.7112
A14: OCTAVIA | B14: 14 | C14: 477958.35 | D14: 13413.9 | E14: 477958.35 | F14: -14700.9 | G14: -29168.01 | H14: 13413.9 | J14: 13413.9 | K14: 958.13571
A15: Total général | B15: 135 | C15: 4637974.7 | D15: 155870.2 | E15: 4637974.7 | F15: -157632.42 | G15: -263406.97 | H15: 155870.2 | I15: 436 | J15: 156306.2 | K15: 1157.8237

Sheet Marges_VN_Modèles_unitaire
A1: VALAUTO - Marge Unitaire / Modèles
A3: Site | B3: 10
A4: Marque | B4: VW
A5: Vendeur | B5: (Tous)
A7: Étiquettes de lignes | B7: Nbre de LIV. | C7: Moyenne de Total | D7: Moyenne de Marge nette2 | E7: Moyenne de Total2 | F7: Moyenne de OP Clos | G7: Moyenne de OP Ouverts | H7: Moyenne de Marge nette | I7: Moyenne de OP "+ / -" | J7: Moyenne de Marge nette recalculée | K7: Moyenne de Marge nette recalculée2 | L7: Moyenne de TOTAL COM VENDEUR
A8: Total général

Sheet Marges_VN_Modèles_unitaire CD
A1: VALAUTO - Marge Unitaire / Modèles
A4: Site | B4: 10
A5: Marque | B5: (Tous)
A7: Étiquettes de lignes | B7: Equipe | C7: Vendeur | D7: N° CDE | E7: Date de Livraison | F7: Nbre de LIV. | G7: Moyenne de Jours de Stock | H7: Somme de Total | I7: Somme de Total2 | J7: Somme de OP Clos | K7: Somme de OP Ouverts | L7: Somme de Marge nette | M7: Moyenne de Marge nette recalculée2 | N7: Moyenne de TOTAL COM VENDEUR
A8: Total général

Sheet Marges_VN_Modèles_Equipes
A1: VALAUTO - Marges VN / Modèles / Equipes
A3: Site | B3: 30
A4: Marque | B4: (Tous)
A5: Equipe | B5: (Plusieurs éléments)
A6: Vendeur | B6: (Tous)
A8: Étiquettes de lignes | B8: Nbre de LIV. | C8: Somme de Total | D8: Somme de Marge nette2 | E8: PV TOTAL hors transport | F8: Somme de OP Clos | G8: Somme de OP Ouverts | H8: Somme de Marge nette | I8: Somme de OP "+ / -" | J8: Somme de Marge nette recalculée | K8: Moyenne de Marge nette recalculée2
A9: Total général

Sheet Marges_VN_Equipes
A1: VALAUTO - Marges VN / Equipes
A3: Site | B3: (Tous)
A4: Marque | B4: HY
A5: Equipe | B5: (Tous)
A7: Étiquettes de lignes | B7: Nbre de LIV. | C7: Somme de Total | D7: Somme de Marge nette2 | E7: PV TOTAL hors transport | F7: Somme de OP Clos | G7: Somme de OP Ouverts | H7: Somme de Marge nette | I7: Somme de OP "+ / -" | J7: Somme de Marge nette recalculée | K7: Moyenne de Marge nette recalculée2
A8: LEGCH | B8: 14 | C8: 411655.91 | D8: 29084.74 | E8: 411655.91 | F8: -33343.28 | G8: -1667 | H8: 29084.74 | J8: 29084.74 | K8: 2077.4814
A9: LTMEL | B9: 8 | C9: 275858.86 | D9: 5073.92 | E9: 275858.86 | F9: -37092.79 | G9: 0 | H9: 5073.92 | J9: 5073.92 | K9: 634.24
A10: LETLE | B10: 16 | C10: 458884.37 | D10: 10821.31 | E10: 458884.37 | F10: -29891.09 | G10: -7084 | H10: 10821.31 | J10: 10821.31 | K10: 676.33187
A11: LEGJA | B11: 11 | C11: 317188.88 | D11: 21195.99 | E11: 317188.88 | F11: -29145.79 | G11: -417 | H11: 21195.99 | J11: 21195.99 | K11: 1926.9082
A12: LELBO | B12: 23 | C12: 700061.63 | D12: 25167.41 | E12: 700061.63 | F12: -62662.3 | G12: -10713.45 | H12: 25167.41 | J12: 25167.41 | K12: 1094.2352
A13: Total général | B13: 72 | C13: 2163649.7 | D13: 91343.37 | E13: 2163649.7 | F13: -192135.25 | G13: -19881.45 | H13: 91343.37 | J13: 91343.37 | K13: 1268.6579

Sheet Marges_VN_Vendeurs
A1: VALAUTO - Marges VN / Vendeurs
A4: Site | B4: (Tous)
A5: Marque | B5: (Tous)
A7: Étiquettes de lignes | B7: Nbre de LIV. | C7: Somme de Total | D7: Somme de Marge nette2 | E7: PV TOTAL hors transport | F7: Somme de OP Clos | G7: Somme de OP Ouverts | H7: Somme de Marge nette | I7: Somme de OP "+ / -" | J7: Somme de Marge nette recalculée | K7: Moyenne de Marge nette recalculée2
A8: Total général
